Workbook

Sheet Cover
B1: FPT CORPORATION - INTEGRATED FINANCIAL MODEL
B2: Cleaned & consolidated build - navigation index
B3: Last structural update: 2026-07-20 | 15 sheets (12 visible)
B5: BASIS CHANGE (FY2026): | C5: FPT Telecom now equity-method (deconsolidated); 2025 restated. 1Q26/2Q26/6M26 = NEW basis, history = OLD basis - see YoY sheet.
B6: MERGES: | C6: Data feeds -> Data. FI&FE folded into PL (rows 371+). Capex_WC folded into BS (rows 211+).
B8: GROUP | C8: SHEET | D8: DESCRIPTION
B9: Control | C9: Scenarios | D9: Scenario switch + macro assumptions
B10: Analysis | C10: YoY | D10: YoY dashboard - annual + quarterly + 2026 new-basis
B11: Model | C11: Revenue | D11: Revenue & PBT build by segment
B12: Output | C12: Valuation | D12: DCF / FCFF valuation
B13: Model | C13: PL | D13: Income statement (now incl. FI&FE schedule, rows 371+)
B14: Model | C14: BS | D14: Balance sheet (now incl. Capex/WC schedule, rows 211+)
B15: Model | C15: CF | D15: Cash flow / FCFF
B16: Control | C16: Assumptions | D16: Forecast drivers: growth rates, margins
B17: Data | C17: Data | D17: Merged FiinPro actuals (Fi_BS+Fi_PL+Fi_CF+Data_Quarterly, extract 03/2023 - STALE)
B18: Output | C18: Report | D18: Formatted statements for publication
B19: Output | C19: Ratios | D19: Financial ratios
... B22: Data | C22: Beta (hidden) | D22: Beta regression vs VN-Index

Sheet YoY
B1: FPT — YoY COMPARISON DASHBOARD
B2: A & B = consolidated (old) basis incl. Telecom. C = 2026 actuals on NEW (post-deconsolidation) basis; YoY vs restated 2025 — not comparable to A/B.
B3: Live formulas link to the Revenue sheet. Growth auto-coloured: green = up, red = down.
B5: A. ANNUAL (VND bn; % = YoY)
B6: Metric | C6: 2018 | D6: 2019 | E6: 2020 | F6: 2021 | G6: 2022 | H6: 2023 | I6: 2024 | J6: 2025 | K6: 2026F | L6: 2027F | M6: 2028F
B7: Total net revenue | C7: =IF(Revenue!B10=0,"",Revenue!B10) -> 23213.537 | D7: =IF(Revenue!C10=0,"",Revenue!C10) -> 27716.96 | E7: =IF(Revenue!D10=0,"",Revenue!D10) -> 29830.401 | F7: =IF(Revenue!E10=0,"",Revenue!E10) -> 35657.263 | G7: =IF(Revenue!F10=0,"",Revenue!F10) -> 44009.528 | H7: =IF(Revenue!G10=0,"",Revenue!G10) -> 52618 | I7: =IF(Revenue!H10=0,"",Revenue!H10) -> 62850 | J7: =IF(Revenue!I10=0,"",Revenue!I10) -> 70114 | ... M7: =IF(Revenue!L10=0,"",Revenue!L10) -> 103820.32
B8: % YoY | D8: =IF(OR(Revenue!C10=0,Revenue!B10=0),"",Revenue!C10/Revenue!B10-1) -> 0.19399988 | E8: =IF(OR(Revenue!D10=0,Revenue!C10=0),"",Revenue!D10/Revenue!C10-1) -> 0.0762508 | F8: =IF(OR(Revenue!E10=0,Revenue!D10=0),"",Revenue!E10/Revenue!D10-1) -> 0.19533301 | G8: =IF(OR(Revenue!F10=0,Revenue!E10=0),"",Revenue!F10/Revenue!E10-1) -> 0.23423742 | H8: =IF(OR(Revenue!G10=0,Revenue!F10=0),"",Revenue!G10/Revenue!F10-1) -> 0.19560474 | I8: =IF(OR(Revenue!H10=0,Revenue!G10=0),"",Revenue!H10/Revenue!G10-1) -> 0.19445817 | J8: =IF(OR(Revenue!I10=0,Revenue!H10=0),"",Revenue!I10/Revenue!H10-1) -> 0.11557677 | K8: =IF(OR(Revenue!J10=0,Revenue!I10=0),"",Revenue!J10/Revenue!I10-1) -> 0.12595076 | ... M8: =IF(OR(Revenue!L10=0,Revenue!K10=0),"",Revenue!L10/Revenue!K10-1) -> 0.14965845
B9: Technology (Total IT services) | C9: =IF(Revenue!B11=0,"",Revenue!B11) -> 13401.574 | D9: =IF(Revenue!C11=0,"",Revenue!C11) -> 15783.421 | E9: =IF(Revenue!D11=0,"",Revenue!D11) -> 16804.932 | F9: =IF(Revenue!E11=0,"",Revenue!E11) -> 20872.244 | G9: =IF(Revenue!F11=0,"",Revenue!F11) -> 25762.902 | H9: =IF(Revenue!G11=0,"",Revenue!G11) -> 31449 | I9: =IF(Revenue!H11=0,"",Revenue!H11) -> 39110 | J9: =IF(Revenue!I11=0,"",Revenue!I11) -> 44475 | ... M9: =IF(Revenue!L11=0,"",Revenue!L11) -> 68460.16
B10: % YoY | D10: =IF(OR(Revenue!C11=0,Revenue!B11=0),"",Revenue!C11/Revenue!B11-1) -> 0.1777289 | E10: =IF(OR(Revenue!D11=0,Revenue!C11=0),"",Revenue!D11/Revenue!C11-1) -> 0.064720506 | F10: =IF(OR(Revenue!E11=0,Revenue!D11=0),"",Revenue!E11/Revenue!D11-1) -> 0.24203085 | G10: =IF(OR(Revenue!F11=0,Revenue!E11=0),"",Revenue!F11/Revenue!E11-1) -> 0.23431395 | H10: =IF(OR(Revenue!G11=0,Revenue!F11=0),"",Revenue!G11/Revenue!F11-1) -> 0.22070875 | I10: =IF(OR(Revenue!H11=0,Revenue!G11=0),"",Revenue!H11/Revenue!G11-1) -> 0.24360075 | J10: =IF(OR(Revenue!I11=0,Revenue!H11=0),"",Revenue!I11/Revenue!H11-1) -> 0.13717719 | K10: =IF(OR(Revenue!J11=0,Revenue!I11=0),"",Revenue!J11/Revenue!I11-1) -> 0.14122556 | ... M10: =IF(OR(Revenue!L11=0,Revenue!K11=0),"",Revenue!L11/Revenue!K11-1) -> 0.16560096
B11: Global IT (foreign) | C11: =IF(Revenue!B12=0,"",Revenue!B12) -> 8443.472 | D11: =IF(Revenue!C12=0,"",Revenue!C12) -> 10848.063 | E11: =IF(Revenue!D12=0,"",Revenue!D12) -> 12000.26 | F11: =IF(Revenue!E12=0,"",Revenue!E12) -> 14540.801 | G11: =IF(Revenue!F12=0,"",Revenue!F12) -> 18915.494 | H11: =IF(Revenue!G12=0,"",Revenue!G12) -> 24288 | I11: =IF(Revenue!H12=0,"",Revenue!H12) -> 30953 | J11: =IF(Revenue!I12=0,"",Revenue!I12) -> 35382 | ... M11: =IF(Revenue!L12=0,"",Revenue!L12) -> 55685.15
B12: % YoY | D12: =IF(OR(Revenue!C12=0,Revenue!B12=0),"",Revenue!C12/Revenue!B12-1) -> 0.28478699 | E12: =IF(OR(Revenue!D12=0,Revenue!C12=0),"",Revenue!D12/Revenue!C12-1) -> 0.10621223 | F12: =IF(OR(Revenue!E12=0,Revenue!D12=0),"",Revenue!E12/Revenue!D12-1) -> 0.21170716 | G12: =IF(OR(Revenue!F12=0,Revenue!E12=0),"",Revenue!F12/Revenue!E12-1) -> 0.3008564 | H12: =IF(OR(Revenue!G12=0,Revenue!F12=0),"",Revenue!G12/Revenue!F12-1) -> 0.28402673 | I12: =IF(OR(Revenue!H12=0,Revenue!G12=0),"",Revenue!H12/Revenue!G12-1) -> 0.27441535 | J12: =IF(OR(Revenue!I12=0,Revenue!H12=0),"",Revenue!I12/Revenue!H12-1) -> 0.14308791 | K12: =IF(OR(Revenue!J12=0,Revenue!I12=0),"",Revenue!J12/Revenue!I12-1) -> 0.14668042 | ... M12: =IF(OR(Revenue!L12=0,Revenue!K12=0),"",Revenue!L12/Revenue!K12-1) -> 0.17659111
B13: Domestic IT | C13: =IF(Revenue!B13=0,"",Revenue!B13) -> 4958.102 | D13: =IF(Revenue!C13=0,"",Revenue!C13) -> 4935.358 | E13: =IF(Revenue!D13=0,"",Revenue!D13) -> 4804.672 | F13: =IF(Revenue!E13=0,"",Revenue!E13) -> 6331.443 | G13: =IF(Revenue!F13=0,"",Revenue!F13) -> 6847.408 | H13: =IF(Revenue!G13=0,"",Revenue!G13) -> 7161 | I13: =IF(Revenue!H13=0,"",Revenue!H13) -> 8157 | J13: =IF(Revenue!I13=0,"",Revenue!I13) -> 9093 | ... M13: =IF(Revenue!L13=0,"",Revenue!L13) -> 12775.01
B14: % YoY | D14: =IF(OR(Revenue!C13=0,Revenue!B13=0),"",Revenue!C13/Revenue!B13-1) -> -0.0045872392 | E14: =IF(OR(Revenue!D13=0,Revenue!C13=0),"",Revenue!D13/Revenue!C13-1) -> -0.026479538 | F14: =IF(OR(Revenue!E13=0,Revenue!D13=0),"",Revenue!E13/Revenue!D13-1) -> 0.317768 | G14: =IF(OR(Revenue!F13=0,Revenue!E13=0),"",Revenue!F13/Revenue!E13-1) -> 0.081492481 | H14: =IF(OR(Revenue!G13=0,Revenue!F13=0),"",Revenue!G13/Revenue!F13-1) -> 0.045797183 | I14: =IF(OR(Revenue!H13=0,Revenue!G13=0),"",Revenue!H13/Revenue!G13-1) -> 0.13908672 | J14: =IF(OR(Revenue!I13=0,Revenue!H13=0),"",Revenue!I13/Revenue!H13-1) -> 0.11474807 | K14: =IF(OR(Revenue!J13=0,Revenue!I13=0),"",Revenue!J13/Revenue!I13-1) -> 0.12 | ... M14: =IF(OR(Revenue!L13=0,Revenue!K13=0),"",Revenue!L13/Revenue!K13-1) -> 0.12
B15: Telecom | C15: =IF(Revenue!B14=0,"",Revenue!B14) -> 8831.003 | D15: =IF(Revenue!C14=0,"",Revenue!C14) -> 10398.427 | E15: =IF(Revenue!D14=0,"",Revenue!D14) -> 11466.154 | F15: =IF(Revenue!E14=0,"",Revenue!E14) -> 12686.416 | G15: =IF(Revenue!F14=0,"",Revenue!F14) -> 14729.649 | H15: =IF(Revenue!G14=0,"",Revenue!G14) -> 15806 | I15: =IF(Revenue!H14=0,"",Revenue!H14) -> 17610 | J15: =IF(Revenue!I14=0,"",Revenue!I14) -> 19507 | ... M15: =IF(Revenue!L14=0,"",Revenue!L14) -> 27283.583
B16: % YoY | D16: =IF(OR(Revenue!C14=0,Revenue!B14=0),"",Revenue!C14/Revenue!B14-1) -> 0.17749105 | E16: =IF(OR(Revenue!D14=0,Revenue!C14=0),"",Revenue!D14/Revenue!C14-1) -> 0.10268159 | F16: =IF(OR(Revenue!E14=0,Revenue!D14=0),"",Revenue!E14/Revenue!D14-1) -> 0.10642296 | G16: =IF(OR(Revenue!F14=0,Revenue!E14=0),"",Revenue!F14/Revenue!E14-1) -> 0.16105676 | H16: =IF(OR(Revenue!G14=0,Revenue!F14=0),"",Revenue!G14/Revenue!F14-1) -> 0.073073771 | I16: =IF(OR(Revenue!H14=0,Revenue!G14=0),"",Revenue!H14/Revenue!G14-1) -> 0.11413387 | J16: =IF(OR(Revenue!I14=0,Revenue!H14=0),"",Revenue!I14/Revenue!H14-1) -> 0.10772288 | K16: =IF(OR(Revenue!J14=0,Revenue!I14=0),"",Revenue!J14/Revenue!I14-1) -> 0.115 | ... M16: =IF(OR(Revenue!L14=0,Revenue!K14=0),"",Revenue!L14/Revenue!K14-1) -> 0.12
B17: Education, Investment & others | C17: =IF(Revenue!B17=0,"",Revenue!B17) -> 980.95986 | D17: =IF(Revenue!C17=0,"",Revenue!C17) -> 1535.1122 | E17: =IF(Revenue!D17=0,"",Revenue!D17) -> 1559.3145 | F17: =IF(Revenue!E17=0,"",Revenue!E17) -> 2098.6025 | G17: =IF(Revenue!F17=0,"",Revenue!F17) -> 3516.9767 | H17: =IF(Revenue!G17=0,"",Revenue!G17) -> 5363 | I17: =IF(Revenue!H17=0,"",Revenue!H17) -> 6129 | J17: =IF(Revenue!I17=0,"",Revenue!I17) -> 6132 | ... M17: =IF(Revenue!L17=0,"",Revenue!L17) -> 8076.5798
B18: % YoY | D18: =IF(OR(Revenue!C17=0,Revenue!B17=0),"",Revenue!C17/Revenue!B17-1) -> 0.56490823 | E18: =IF(OR(Revenue!D17=0,Revenue!C17=0),"",Revenue!D17/Revenue!C17-1) -> 0.015765867 | F18: =IF(OR(Revenue!E17=0,Revenue!D17=0),"",Revenue!E17/Revenue!D17-1) -> 0.34584942 | G18: =IF(OR(Revenue!F17=0,Revenue!E17=0),"",Revenue!F17/Revenue!E17-1) -> 0.67586601 | H18: =IF(OR(Revenue!G17=0,Revenue!F17=0),"",Revenue!G17/Revenue!F17-1) -> 0.52488927 | I18: =IF(OR(Revenue!H17=0,Revenue!G17=0),"",Revenue!H17/Revenue!G17-1) -> 0.14283051 | J18: =IF(OR(Revenue!I17=0,Revenue!H17=0),"",Revenue!I17/Revenue!H17-1) -> 0.00048947626 | K18: =IF(OR(Revenue!J17=0,Revenue!I17=0),"",Revenue!J17/Revenue!I17-1) -> 0.05 | ... M18: =IF(OR(Revenue!L17=0,Revenue!K17=0),"",Revenue!L17/Revenue!K17-1) -> 0.12
B19: Gross profit | C19: =IF(Revenue!B7=0,"",Revenue!B7) -> 8722.879 | D19: =IF(Revenue!C7=0,"",Revenue!C7) -> 10712.05 | E19: =IF(Revenue!D7=0,"",Revenue!D7) -> 11813.657 | F19: =IF(Revenue!E7=0,"",Revenue!E7) -> 13631.964 | G19: =IF(Revenue!F7=0,"",Revenue!F7) -> 17167.279 | H19: =IF(Revenue!G7=0,"",Revenue!G7) -> 20319.553 | I19: =IF(Revenue!H7=0,"",Revenue!H7) -> 23698.34 | J19: =IF(Revenue!I7=0,"",Revenue!I7) -> 25990.27 | ... M19: =IF(Revenue!L7=0,"",Revenue!L7) -> 25577.75
B20: % YoY | D20: =IF(OR(Revenue!C7=0,Revenue!B7=0),"",Revenue!C7/Revenue!B7-1) -> 0.22804061 | E20: =IF(OR(Revenue!D7=0,Revenue!C7=0),"",Revenue!D7/Revenue!C7-1) -> 0.1028382 | F20: =IF(OR(Revenue!E7=0,Revenue!D7=0),"",Revenue!E7/Revenue!D7-1) -> 0.15391565 | G20: =IF(OR(Revenue!F7=0,Revenue!E7=0),"",Revenue!F7/Revenue!E7-1) -> 0.25934006 | H20: =IF(OR(Revenue!G7=0,Revenue!F7=0),"",Revenue!G7/Revenue!F7-1) -> 0.18362111 | I20: =IF(OR(Revenue!H7=0,Revenue!G7=0),"",Revenue!H7/Revenue!G7-1) -> 0.16628252 | J20: =IF(OR(Revenue!I7=0,Revenue!H7=0),"",Revenue!I7/Revenue!H7-1) -> 0.096712681 | K20: =IF(OR(Revenue!J7=0,Revenue!I7=0),"",Revenue!J7/Revenue!I7-1) -> -0.23726361 | ... M20: =IF(OR(Revenue!L7=0,Revenue!K7=0),"",Revenue!L7/Revenue!K7-1) -> 0.1481887
B21: Profit before tax (PBT) | C21: =IF(Revenue!B115=0,"",Revenue!B115) -> 3857.6026 | D21: =IF(Revenue!C115=0,"",Revenue!C115) -> 4664.5305 | E21: =IF(Revenue!D115=0,"",Revenue!D115) -> 5263.4566 | F21: =IF(Revenue!E115=0,"",Revenue!E115) -> 6337.2064 | G21: =IF(Revenue!F115=0,"",Revenue!F115) -> 7662.283 | H21: =IF(Revenue!G115=0,"",Revenue!G115) -> 9203.0061 | I21: =IF(Revenue!H115=0,"",Revenue!H115) -> 11069.66 | J21: =IF(Revenue!I115=0,"",Revenue!I115) -> 13133.72 | ... M21: =IF(Revenue!L115=0,"",Revenue!L115) -> 17014.728
B22: % YoY | D22: =IF(OR(Revenue!C115=0,Revenue!B115=0),"",Revenue!C115/Revenue!B115-1) -> 0.20917861 | E22: =IF(OR(Revenue!D115=0,Revenue!C115=0),"",Revenue!D115/Revenue!C115-1) -> 0.12840009 | F22: =IF(OR(Revenue!E115=0,Revenue!D115=0),"",Revenue!E115/Revenue!D115-1) -> 0.20400089 | G22: =IF(OR(Revenue!F115=0,Revenue!E115=0),"",Revenue!F115/Revenue!E115-1) -> 0.20909474 | H22: =IF(OR(Revenue!G115=0,Revenue!F115=0),"",Revenue!G115/Revenue!F115-1) -> 0.20107886 | I22: =IF(OR(Revenue!H115=0,Revenue!G115=0),"",Revenue!H115/Revenue!G115-1) -> 0.20283089 | J22: =IF(OR(Revenue!I115=0,Revenue!H115=0),"",Revenue!I115/Revenue!H115-1) -> 0.18646101 | K22: =IF(OR(Revenue!J115=0,Revenue!I115=0),"",Revenue!J115/Revenue!I115-1) | ... M22: =IF(OR(Revenue!L115=0,Revenue!K115=0),"",Revenue!L115/Revenue!K115-1) -> 0.13307511
B23: Gross margin (level) | C23: =IF(Revenue!B10=0,"",Revenue!B7/Revenue!B10) -> 0.37576691 | D23: =IF(Revenue!C10=0,"",Revenue!C7/Revenue!C10) -> 0.38647996 | E23: =IF(Revenue!D10=0,"",Revenue!D7/Revenue!D10) -> 0.39602745 | F23: =IF(Revenue!E10=0,"",Revenue!E7/Revenue!E10) -> 0.38230541 | G23: =IF(Revenue!F10=0,"",Revenue!F7/Revenue!F10) -> 0.39008096 | H23: =IF(Revenue!G10=0,"",Revenue!G7/Revenue!G10) -> 0.38617115 | I23: =IF(Revenue!H10=0,"",Revenue!H7/Revenue!H10) -> 0.37706189 | J23: =IF(Revenue!I10=0,"",Revenue!I7/Revenue!I10) -> 0.37068588 | ... M23: =IF(Revenue!L10=0,"",Revenue!L7/Revenue!L10) -> 0.24636554
B24: PBT margin (level) | C24: =IF(Revenue!B10=0,"",Revenue!B115/Revenue!B10) -> 0.16617901 | D24: =IF(Revenue!C10=0,"",Revenue!C115/Revenue!C10) -> 0.16829156 | E24: =IF(Revenue!D10=0,"",Revenue!D115/Revenue!D10) -> 0.17644606 | F24: =IF(Revenue!E10=0,"",Revenue!E115/Revenue!E10) -> 0.17772555 | G24: =IF(Revenue!F10=0,"",Revenue!F115/Revenue!F10) -> 0.17410509 | H24: =IF(Revenue!G10=0,"",Revenue!G115/Revenue!G10) -> 0.17490224 | I24: =IF(Revenue!H10=0,"",Revenue!H115/Revenue!H10) -> 0.17612824 | J24: =IF(Revenue!I10=0,"",Revenue!I115/Revenue!I10) -> 0.18731951 | ... M24: =IF(Revenue!L10=0,"",Revenue!L115/Revenue!L10) -> 0.1638863
B26: B. QUARTERLY (VND bn; % = YoY vs same quarter prior year)
B27: Metric | C27: 1Q23 | D27: 2Q23 | E27: 3Q23 | F27: 4Q23 | G27: 1Q24 | H27: 2Q24 | I27: 3Q24 | J27: 4Q24 | K27: 1Q25 | L27: 2Q25 | M27: 3Q25 | N27: 4Q25
B28: Total net revenue | C28: =IF(Revenue!AQ10=0,"",Revenue!AQ10) -> 11687.891 | D28: =IF(Revenue!AR10=0,"",Revenue!AR10) -> 12478.109 | E28: =IF(Revenue!AS10=0,"",Revenue!AS10) -> 13761 | F28: =IF(Revenue!AT10=0,"",Revenue!AT10) -> 14691 | G28: =IF(Revenue!AU10=0,"",Revenue!AU10) -> 14092 | H28: =IF(Revenue!AV10=0,"",Revenue!AV10) -> 15246 | I28: =IF(Revenue!AW10=0,"",Revenue!AW10) -> 15903 | J28: =IF(Revenue!AX10=0,"",Revenue!AX10) -> 17608 | ... N28: =IF(Revenue!BB10=0,"",Revenue!BB10) -> 16058
B29: % YoY | C29: =IF(OR(Revenue!AQ10=0,Revenue!AM10=0),"",Revenue!AQ10/Revenue!AM10-1) -> 0.20119076 | D29: =IF(OR(Revenue!AR10=0,Revenue!AN10=0),"",Revenue!AR10/Revenue!AN10-1) -> 0.23593846 | E29: =IF(OR(Revenue!AS10=0,Revenue!AO10=0),"",Revenue!AS10/Revenue!AO10-1) -> 0.23432992 | F29: =IF(OR(Revenue!AT10=0,Revenue!AP10=0),"",Revenue!AT10/Revenue!AP10-1) -> 0.12640085 | G29: =IF(OR(Revenue!AU10=0,Revenue!AQ10=0),"",Revenue!AU10/Revenue!AQ10-1) -> 0.20569228 | H29: =IF(OR(Revenue!AV10=0,Revenue!AR10=0),"",Revenue!AV10/Revenue!AR10-1) -> 0.22181975 | I29: =IF(OR(Revenue!AW10=0,Revenue!AS10=0),"",Revenue!AW10/Revenue!AS10-1) -> 0.15565729 | J29: =IF(OR(Revenue!AX10=0,Revenue!AT10=0),"",Revenue!AX10/Revenue!AT10-1) -> 0.19855694 | ... N29: =IF(OR(Revenue!BB10=0,Revenue!AX10=0),"",Revenue!BB10/Revenue!AX10-1) -> -0.088028169
B30: Technology (Total IT services) | C30: =IF(Revenue!AQ11=0,"",Revenue!AQ11) -> 6844.791 | D30: =IF(Revenue!AR11=0,"",Revenue!AR11) -> 7357.209 | E30: =IF(Revenue!AS11=0,"",Revenue!AS11) -> 8315 | F30: =IF(Revenue!AT11=0,"",Revenue!AT11) -> 8932 | G30: =IF(Revenue!AU11=0,"",Revenue!AU11) -> 8471 | H30: =IF(Revenue!AV11=0,"",Revenue!AV11) -> 9606 | I30: =IF(Revenue!AW11=0,"",Revenue!AW11) -> 9887 | J30: =IF(Revenue!AX11=0,"",Revenue!AX11) -> 11146 | ... N30: =IF(Revenue!BB11=0,"",Revenue!BB11) -> 13526
B31: % YoY | C31: =IF(OR(Revenue!AQ11=0,Revenue!AM11=0),"",Revenue!AQ11/Revenue!AM11-1) -> 0.21337619 | D31: =IF(OR(Revenue!AR11=0,Revenue!AN11=0),"",Revenue!AR11/Revenue!AN11-1) -> 0.28771297 | E31: =IF(OR(Revenue!AS11=0,Revenue!AO11=0),"",Revenue!AS11/Revenue!AO11-1) -> 0.26675788 | F31: =IF(OR(Revenue!AT11=0,Revenue!AP11=0),"",Revenue!AT11/Revenue!AP11-1) -> 0.13752024 | G31: =IF(OR(Revenue!AU11=0,Revenue!AQ11=0),"",Revenue!AU11/Revenue!AQ11-1) -> 0.23758344 | H31: =IF(OR(Revenue!AV11=0,Revenue!AR11=0),"",Revenue!AV11/Revenue!AR11-1) -> 0.30565816 | I31: =IF(OR(Revenue!AW11=0,Revenue!AS11=0),"",Revenue!AW11/Revenue!AS11-1) -> 0.18905592 | J31: =IF(OR(Revenue!AX11=0,Revenue!AT11=0),"",Revenue!AX11/Revenue!AT11-1) -> 0.24787282 | ... N31: =IF(OR(Revenue!BB11=0,Revenue!AX11=0),"",Revenue!BB11/Revenue!AX11-1) -> 0.21352952
B32: Global IT (foreign) | C32: =IF(Revenue!AQ12=0,"",Revenue!AQ12) -> 5437.791 | D32: =IF(Revenue!AR12=0,"",Revenue!AR12) -> 5789.209 | E32: =IF(Revenue!AS12=0,"",Revenue!AS12) -> 6399 | F32: =IF(Revenue!AT12=0,"",Revenue!AT12) -> 6662 | G32: =IF(Revenue!AU12=0,"",Revenue!AU12) -> 6999 | H32: =IF(Revenue!AV12=0,"",Revenue!AV12) -> 7574 | I32: =IF(Revenue!AW12=0,"",Revenue!AW12) -> 8095 | J32: =IF(Revenue!AX12=0,"",Revenue!AX12) -> 8285 | ... N32: =IF(Revenue!BB12=0,"",Revenue!BB12) -> 9808
B33: % YoY | C33: =IF(OR(Revenue!AQ12=0,Revenue!AM12=0),"",Revenue!AQ12/Revenue!AM12-1) -> 0.32262359 | D33: =IF(OR(Revenue!AR12=0,Revenue!AN12=0),"",Revenue!AR12/Revenue!AN12-1) -> 0.28343347 | E33: =IF(OR(Revenue!AS12=0,Revenue!AO12=0),"",Revenue!AS12/Revenue!AO12-1) -> 0.31746826 | F33: =IF(OR(Revenue!AT12=0,Revenue!AP12=0),"",Revenue!AT12/Revenue!AP12-1) -> 0.2237022 | G33: =IF(OR(Revenue!AU12=0,Revenue!AQ12=0),"",Revenue!AU12/Revenue!AQ12-1) -> 0.28710353 | H33: =IF(OR(Revenue!AV12=0,Revenue!AR12=0),"",Revenue!AV12/Revenue!AR12-1) -> 0.30829618 | I33: =IF(OR(Revenue!AW12=0,Revenue!AS12=0),"",Revenue!AW12/Revenue!AS12-1) -> 0.26504141 | J33: =IF(OR(Revenue!AX12=0,Revenue!AT12=0),"",Revenue!AX12/Revenue!AT12-1) -> 0.24362053 | ... N33: =IF(OR(Revenue!BB12=0,Revenue!AX12=0),"",Revenue!BB12/Revenue!AX12-1) -> 0.18382619
B34: Domestic IT | C34: =IF(Revenue!AQ13=0,"",Revenue!AQ13) -> 1407 | D34: =IF(Revenue!AR13=0,"",Revenue!AR13) -> 1568 | E34: =IF(Revenue!AS13=0,"",Revenue!AS13) -> 1916 | F34: =IF(Revenue!AT13=0,"",Revenue!AT13) -> 2270 | G34: =IF(Revenue!AU13=0,"",Revenue!AU13) -> 1472 | H34: =IF(Revenue!AV13=0,"",Revenue!AV13) -> 2032 | I34: =IF(Revenue!AW13=0,"",Revenue!AW13) -> 1792 | J34: =IF(Revenue!AX13=0,"",Revenue!AX13) -> 2861 | ... N34: =IF(Revenue!BB13=0,"",Revenue!BB13) -> 3717
B35: % YoY | C35: =IF(OR(Revenue!AQ13=0,Revenue!AM13=0),"",Revenue!AQ13/Revenue!AM13-1) -> -0.080238863 | D35: =IF(OR(Revenue!AR13=0,Revenue!AN13=0),"",Revenue!AR13/Revenue!AN13-1) -> 0.30376362 | E35: =IF(OR(Revenue!AS13=0,Revenue!AO13=0),"",Revenue!AS13/Revenue!AO13-1) -> 0.12246464 | F35: =IF(OR(Revenue!AT13=0,Revenue!AP13=0),"",Revenue!AT13/Revenue!AP13-1) -> -0.057321889 | G35: =IF(OR(Revenue!AU13=0,Revenue!AQ13=0),"",Revenue!AU13/Revenue!AQ13-1) -> 0.046197584 | H35: =IF(OR(Revenue!AV13=0,Revenue!AR13=0),"",Revenue!AV13/Revenue!AR13-1) -> 0.29591837 | I35: =IF(OR(Revenue!AW13=0,Revenue!AS13=0),"",Revenue!AW13/Revenue!AS13-1) -> -0.064718163 | J35: =IF(OR(Revenue!AX13=0,Revenue!AT13=0),"",Revenue!AX13/Revenue!AT13-1) -> 0.26035242 | ... N35: =IF(OR(Revenue!BB13=0,Revenue!AX13=0),"",Revenue!BB13/Revenue!AX13-1) -> 0.29919609
B36: Telecom | C36: =IF(Revenue!AQ14=0,"",Revenue!AQ14) -> 3790.224 | D36: =IF(Revenue!AR14=0,"",Revenue!AR14) -> 3891.776 | E36: =IF(Revenue!AS14=0,"",Revenue!AS14) -> 4008 | F36: =IF(Revenue!AT14=0,"",Revenue!AT14) -> 4116 | G36: =IF(Revenue!AU14=0,"",Revenue!AU14) -> 4012 | H36: =IF(Revenue!AV14=0,"",Revenue!AV14) -> 4232 | I36: =IF(Revenue!AW14=0,"",Revenue!AW14) -> 4556 | J36: =IF(Revenue!AX14=0,"",Revenue!AX14) -> 4810 | ... N36: =IF(Revenue!BB14=0,"",Revenue!BB14) -> 5220
B37: % YoY | C37: =IF(OR(Revenue!AQ14=0,Revenue!AM14=0),"",Revenue!AQ14/Revenue!AM14-1) -> 0.091928933 | D37: =IF(OR(Revenue!AR14=0,Revenue!AN14=0),"",Revenue!AR14/Revenue!AN14-1) -> 0.07938843 | E37: =IF(OR(Revenue!AS14=0,Revenue!AO14=0),"",Revenue!AS14/Revenue!AO14-1) -> 0.07435974 | F37: =IF(OR(Revenue!AT14=0,Revenue!AP14=0),"",Revenue!AT14/Revenue!AP14-1) -> 0.049360212 | G37: =IF(OR(Revenue!AU14=0,Revenue!AQ14=0),"",Revenue!AU14/Revenue!AQ14-1) -> 0.058512637 | H37: =IF(OR(Revenue!AV14=0,Revenue!AR14=0),"",Revenue!AV14/Revenue!AR14-1) -> 0.08742127 | I37: =IF(OR(Revenue!AW14=0,Revenue!AS14=0),"",Revenue!AW14/Revenue!AS14-1) -> 0.13672655 | J37: =IF(OR(Revenue!AX14=0,Revenue!AT14=0),"",Revenue!AX14/Revenue!AT14-1) -> 0.1686103 | ... N37: =IF(OR(Revenue!BB14=0,Revenue!AX14=0),"",Revenue!BB14/Revenue!AX14-1) -> 0.085239085
B38: Education, Investment & others | C38: =IF(Revenue!AQ17=0,"",Revenue!AQ17) -> 1052.876 | D38: =IF(Revenue!AR17=0,"",Revenue!AR17) -> 1228.124 | E38: =IF(Revenue!AS17=0,"",Revenue!AS17) -> 1439 | F38: =IF(Revenue!AT17=0,"",Revenue!AT17) -> 1643 | G38: =IF(Revenue!AU17=0,"",Revenue!AU17) -> 1609 | H38: =IF(Revenue!AV17=0,"",Revenue!AV17) -> 1408 | I38: =IF(Revenue!AW17=0,"",Revenue!AW17) -> 1460 | J38: =IF(Revenue!AX17=0,"",Revenue!AX17) -> 1652 | ... N38: =IF(Revenue!BB17=0,"",Revenue!BB17) -> 1481
B39: % YoY | C39: =IF(OR(Revenue!AQ17=0,Revenue!AM17=0),"",Revenue!AQ17/Revenue!AM17-1) -> 0.70364193 | D39: =IF(OR(Revenue!AR17=0,Revenue!AN17=0),"",Revenue!AR17/Revenue!AN17-1) -> 0.58033258 | E39: =IF(OR(Revenue!AS17=0,Revenue!AO17=0),"",Revenue!AS17/Revenue!AO17-1) -> 0.6850827 | F39: =IF(OR(Revenue!AT17=0,Revenue!AP17=0),"",Revenue!AT17/Revenue!AP17-1) -> 0.29587595 | G39: =IF(OR(Revenue!AU17=0,Revenue!AQ17=0),"",Revenue!AU17/Revenue!AQ17-1) -> 0.52819515 | H39: =IF(OR(Revenue!AV17=0,Revenue!AR17=0),"",Revenue!AV17/Revenue!AR17-1) -> 0.14646404 | I39: =IF(OR(Revenue!AW17=0,Revenue!AS17=0),"",Revenue!AW17/Revenue!AS17-1) -> 0.014593468 | J39: =IF(OR(Revenue!AX17=0,Revenue!AT17=0),"",Revenue!AX17/Revenue!AT17-1) -> 0.0054777845 | ... N39: =IF(OR(Revenue!BB17=0,Revenue!AX17=0),"",Revenue!BB17/Revenue!AX17-1) -> -0.1035109
B40: Gross profit | C40: =IF(Revenue!AQ7=0,"",Revenue!AQ7) -> 4567.879 | D40: =IF(Revenue!AR7=0,"",Revenue!AR7) -> 4633.8243 | E40: =IF(Revenue!AS7=0,"",Revenue!AS7) -> 5496.369 | F40: =IF(Revenue!AT7=0,"",Revenue!AT7) -> 5631.8636 | G40: =IF(Revenue!AU7=0,"",Revenue!AU7) -> 5510.4657 | H40: =IF(Revenue!AV7=0,"",Revenue!AV7) -> 5651.3573 | I40: =IF(Revenue!AW7=0,"",Revenue!AW7) -> 6158.9557 | J40: =IF(Revenue!AX7=0,"",Revenue!AX7) -> 6377.57 | ... N40: =IF(Revenue!BB7=0,"",Revenue!BB7) -> 7047.2751
B41: % YoY | C41: =IF(OR(Revenue!AQ7=0,Revenue!AM7=0),"",Revenue!AQ7/Revenue!AM7-1) -> 0.15545352 | D41: =IF(OR(Revenue!AR7=0,Revenue!AN7=0),"",Revenue!AR7/Revenue!AN7-1) -> 0.20588085 | E41: =IF(OR(Revenue!AS7=0,Revenue!AO7=0),"",Revenue!AS7/Revenue!AO7-1) -> 0.26078381 | F41: =IF(OR(Revenue!AT7=0,Revenue!AP7=0),"",Revenue!AT7/Revenue!AP7-1) -> 0.074521918 | G41: =IF(OR(Revenue!AU7=0,Revenue!AQ7=0),"",Revenue!AU7/Revenue!AQ7-1) -> 0.20635106 | H41: =IF(OR(Revenue!AV7=0,Revenue!AR7=0),"",Revenue!AV7/Revenue!AR7-1) -> 0.21958817 | I41: =IF(OR(Revenue!AW7=0,Revenue!AS7=0),"",Revenue!AW7/Revenue!AS7-1) -> 0.12054989 | J41: =IF(OR(Revenue!AX7=0,Revenue!AT7=0),"",Revenue!AX7/Revenue!AT7-1) -> 0.13240847 | ... N41: =IF(OR(Revenue!BB7=0,Revenue!AX7=0),"",Revenue!BB7/Revenue!AX7-1) -> 0.10500945
B42: Profit before tax (PBT) | C42: =IF(Revenue!AQ115=0,"",Revenue!AQ115) -> 2120.643 | D42: =IF(Revenue!AR115=0,"",Revenue!AR115) -> 2218.357 | E42: =IF(Revenue!AS115=0,"",Revenue!AS115) -> 2429 | F42: =IF(Revenue!AT115=0,"",Revenue!AT115) -> 2435 | G42: =IF(Revenue!AU115=0,"",Revenue!AU115) -> 2534 | H42: =IF(Revenue!AV115=0,"",Revenue!AV115) -> 2663 | I42: =IF(Revenue!AW115=0,"",Revenue!AW115) -> 2914 | J42: =IF(Revenue!AX115=0,"",Revenue!AX115) -> 2960 | ... N42: =IF(Revenue!BB115=0,"",Revenue!BB115) -> 3499
B43: % YoY | C43: =IF(OR(Revenue!AQ115=0,Revenue!AM115=0),"",Revenue!AQ115/Revenue!AM115-1) -> 0.1920101 | D43: =IF(OR(Revenue!AR115=0,Revenue!AN115=0),"",Revenue!AR115/Revenue!AN115-1) -> 0.19404872 | E43: =IF(OR(Revenue!AS115=0,Revenue!AO115=0),"",Revenue!AS115/Revenue!AO115-1) -> 0.1977171 | F43: =IF(OR(Revenue!AT115=0,Revenue!AP115=0),"",Revenue!AT115/Revenue!AP115-1) -> 0.22421566 | G43: =IF(OR(Revenue!AU115=0,Revenue!AQ115=0),"",Revenue!AU115/Revenue!AQ115-1) -> 0.1949206 | H43: =IF(OR(Revenue!AV115=0,Revenue!AR115=0),"",Revenue!AV115/Revenue!AR115-1) -> 0.20043798 | I43: =IF(OR(Revenue!AW115=0,Revenue!AS115=0),"",Revenue!AW115/Revenue!AS115-1) -> 0.19967065 | J43: =IF(OR(Revenue!AX115=0,Revenue!AT115=0),"",Revenue!AX115/Revenue!AT115-1) -> 0.21560575 | ... N43: =IF(OR(Revenue!BB115=0,Revenue!AX115=0),"",Revenue!BB115/Revenue!AX115-1) -> 0.18209459
B45: C. 2026 ACTUALS — NEW basis (Telecom equity-method); 6M26 %YoY as reported vs restated 2025
B46: Metric | C46: 1Q26 | D46: 2Q26 | E46: 6M26 | F46: 6M26 %YoY (reported)
B47: Total net revenue | C47: =Revenue!BC3 -> 12480 | D47: =Revenue!BQ10 -> 13789 | E47: =Revenue!BP10 -> 26269 | F47: 0.126
B48: Technology (Total IT services) | C48: =Revenue!BC11 -> 10842 | D48: =Revenue!BQ11 -> 12296 | E48: =Revenue!BP11 -> 23138 | F48: 0.15
B49: Global IT (foreign) | E49: =Revenue!BP12 -> 18902 | F49: 0.134
B50: Domestic IT | E50: =Revenue!BP13 -> 4236 | F50: 0.225
B51: Education, Investment & others | C51: =Revenue!BC17 -> 1638 | D51: =Revenue!BQ17 -> 1493 | E51: =Revenue!BP17 -> 3131 | F51: -0.021
B52: Profit before tax (PBT) | C52: =Revenue!BC115 -> 2804 | D52: =Revenue!BQ115 -> 2910 | E52: =Revenue!BP115 -> 5714 | F52: 0.181
B53: Technology PBT | C53: =Revenue!BC116 -> 1566 | D53: =Revenue!BQ116 -> 1748 | E53: =Revenue!BP116 -> 3314 | F53: 0.169
B54: Domestic IT PBT | E54: =Revenue!BP118 -> 308 | F54: 1.005
B55: Investment, education & others PBT | C55: =Revenue!BC122 -> 1238 | D55: =Revenue!BQ122 -> 1162 | E55: =Revenue!BP122 -> 2400 | F55: 0.198

Sheet Scenarios
B1: FPT VN Equity
B2: Revenue growth, margins, income
B5: SCENARIO SWITCH | E5: 1
G6: 2025 | H6: 2026F | I6: 2027F | J6: 2028F | M6: Kịch bản | N6: Giả định vĩ mô & doanh nghiệp | O6: Doanh thu CAGR (2025–2028F) | P6: Biên LNST TB | Q6: LNST CAGR | R6: Rủi ro / Yếu tố hỗ trợ
A7: 1 | B7: IT Revenue Growth
B9: Global IT Revenue Growth | G9: =OFFSET(G10,$E$5,0) -> -3.2307046e-05 | H9: =OFFSET(H10,$E$5,0) -> 0.14668042 | I9: =OFFSET(I10,$E$5,0) -> 0.16651158 | J9: =OFFSET(J10,$E$5,0) -> 0.17659111
C11: Base case | G11: =Revenue!N169 -> -3.2307046e-05 | H11: =Revenue!J169 -> 0.14668042 | I11: =Revenue!K169 -> 0.16651158 | J11: =Revenue!L169 -> 0.17659111 | M11: 🔻 Tiêu cực | N11: Chi tiêu CNTT toàn cầu chững lại Lạm phát lương, tỷ giá bất lợi GDP VN ~5.5% | O11: ~15.6% | P11: ~14.9% | Q11: ~14.5% | R11: Biên lợi nhuận thu hẹp, biến động tỷ giá
C12: Worst case | G12: 0.18 | H12: 0.22 | I12: 0.201 | J12: 0.196 | M12: 🟢 Cơ sở | N12: Vĩ mô ổn định, tỷ giá trung lập Khách hàng tiếp tục mở rộng GDP VN ~6.2% | O12: ~17.8% | P12: ~15.9% | Q12: ~17.6% | R12: Phù hợp xu hướng lịch sử & kế hoạch công ty
C13: Best case | G13: 0.23 | H13: 0.24 | I13: 0.242 | J13: 0.238 | M13: 🔼 Tích cực | N13: Chu kỳ công nghệ phục hồi Tăng giá bán, tỷ giá thuận lợi GDP VN ~7% | O13: ~20.1% | P13: ~16.5% | Q13: ~20.1% | R13: Hợp đồng lớn, hiệu suất cải thiện
B15: Domestic IT Revenue Growth | G15: =OFFSET(G16,$E$5,0) -> 0.09 | H15: =OFFSET(H16,$E$5,0) -> 0.12 | I15: =OFFSET(I16,$E$5,0) -> 0.12 | J15: =OFFSET(J16,$E$5,0) -> 0.12
C17: =$C$11 -> Base case | G17: 0.09 | H17: 0.126858 | I17: 0.12 | J17: 0.12
C18: =$C$12 -> Worst case | G18: 0.05 | H18: 0.11 | I18: 0.1 | J18: 0.1
C19: =$C$13 -> Best case | G19: 0.12 | H19: 0.15 | I19: 0.14 | J19: 0.13
A21: 2 | B21: Telecom & Education Revenue Growth
B22: Telecom Revenue Growth | G22: =OFFSET(G23,$E$5,0) -> 0.12 | H22: =OFFSET(H23,$E$5,0) -> 0.115 | I22: =OFFSET(I23,$E$5,0) -> 0.12 | J22: =OFFSET(J23,$E$5,0) -> 0.12
C24: =$C$11 -> Base case | G24: 0.12 | H24: 0.115 | I24: 0.12 | J24: 0.12
C25: =$C$12 -> Worst case | G25: 0.12 | H25: 0.115 | I25: 0.113 | J25: 0.11
C26: =$C$13 -> Best case | G26: 0.15 | H26: 0.13 | I26: 0.135 | J26: 0.135
A28: 3 | B28: Education Revenue Growth | G28: =OFFSET(G29,$E$5,0) -> 0.1 | H28: =OFFSET(H29,$E$5,0) -> 0.05 | I28: =OFFSET(I29,$E$5,0) -> 0.12 | J28: =OFFSET(J29,$E$5,0) -> 0.12
C30: =$C$11 -> Base case | G30: 0.1 | H30: 0.05 | I30: 0.12 | J30: 0.12
C31: Worst case: +5.0% | G31: 0.13 | H31: 0.127 | I31: 0.124 | J31: 0.12
C32: Best case: -5.0% | G32: 0.16 | H32: 0.15 | I32: 0.14 | J32: 0.13
A42: 5 | B42: JVs income/ Revenue
B43: Average growth rate | G43: =OFFSET(G44,$E$5,0) -> 0.01 | H43: =OFFSET(H44,$E$5,0) -> 0.05 | I43: =OFFSET(I44,$E$5,0) -> 0.047 | J43: =OFFSET(J44,$E$5,0) -> 0.047
C45: =$C$11 -> Base case | G45: 0.01 | H45: 0.045525 | I45: 0.047578 | J45: 0.052837
C46: =$C$12 -> Worst case | G46: 0.002 | H46: 0.002 | I46: 0.002 | J46: 0.002
C47: =$C$13 -> Best case | G47: 0.01 | H47: 0.01 | I47: 0.01 | J47: 0.01
C52: Dự phóng : Kịch bản cơ sở
C53: Doanh thu: Kịch bản | E53: 2025F | F53: 2026F | G53: 2027F | H53: 2028F
C54: Doanh thu CNTT nước ngoài | D54: (VNDbn) | E54: =Revenue!N12 -> 30952 | F54: =Revenue!J12 -> 40571.847 | G54: =Revenue!K12 -> 47327.529 | H54: =Revenue!L12 -> 55685.15
C55: Doanh thu CNTT trong nước | D55: (VNDbn) | E55: =Revenue!N13 -> 8891.13 | F55: =Revenue!J13 -> 10184.16 | G55: =Revenue!K13 -> 11406.259 | H55: =Revenue!L13 -> 12775.01
C56: Doanh thu viễn thông | D56: (VNDbn) | E56: =Revenue!N14 -> 19723.2 | F56: =Revenue!J14 -> 21750.305 | G56: =Revenue!K14 -> 24360.342 | H56: =Revenue!L14 -> 27283.583
C57: Doanh thu giáo dục | D57: (VNDbn) | E57: =Revenue!N17 -> 6741.9 | F57: =Revenue!J17 -> 6438.6 | G57: =Revenue!K17 -> 7211.232 | H57: =Revenue!L17 -> 8076.5798
C58: Tổng doanh thu | D58: (VNDbn) | E58: =Revenue!N10 -> 66308.23 | F58: =Revenue!J10 -> 78944.912 | G58: =Revenue!K10 -> 90305.362 | H58: =Revenue!L10 -> 103820.32
E59: =E58/PL!O9-1 -> 0.05504386 | F59: =F58/E58-1 -> 0.19057486 | G59: =G58/F58-1 -> 0.14390351 | H59: =H58/G58-1 -> 0.14965845
C61: Summary values: Kịch bản | E61: 2025F | F61: 2026F | G61: 2027F | H61: 2028F
C62: Doanh thu | D62: (VNDbn) | E62: =Revenue!N3 -> 66308.23 | F62: =Revenue!J3 -> 78944.912 | G62: =Revenue!K3 -> 90305.362 | H62: =Revenue!L3 -> 103820.32
C63: LN gộp | D63: (VNDbn) | E63: =PL!W13 -> 24854.645 | F63: =PL!Q13 -> 19823.725 | G63: =PL!R13 -> 22276.608 | H63: =PL!S13 -> 25577.75
C64: LNHĐKD | D64: (VNDbn) | E64: =PL!W24 -> 10266.834 | F64: =PL!Q24 -> 9757.474 | G64: =PL!R24 -> 10802.175 | H64: =PL!S24 -> 12260.357
C65: Biên LNHĐ | D65: (%) | E65: =PL!W26 -> 0.15483499 | F65: =PL!Q26 -> 0.17060129 | G65: =PL!R26 -> 0.16380577 | H65: =PL!S26 -> 0.16018917
C66: LNTT | D66: (VNDbn) | E66: =PL!W47 -> 11045.934 | F66: =PL!Q47 -> 13271.822 | G66: =PL!R47 -> 15016.417 | H66: =PL!S47 -> 17014.728
C67: LNST | D67: (VNDbn) | E67: =PL!W53 -> 9389.0441 | F67: =PL!Q53 -> 11281.049 | G67: =PL!R53 -> 12763.954 | H67: =PL!S53 -> 14462.519
C68: EPS | D68: (VND) | E68: =PL!W94 -> 4593.3402 | F68: =PL!Q94 -> 6139.6016 | G68: =PL!R94 -> 6936.1467 | H68: =PL!S94 -> 7859.1752
C69: ROE | D69: (%) | E69: =Ratios!P37 -> 0.28557864 | F69: =Ratios!Q37 -> 0.2798103 | G69: =Ratios!R37 -> 0.26795793 | H69: =Ratios!S37 -> 0.2565207
C70: P/E | D70: (x) | E70: =Report!G87 -> 19.19979 | F70: =Report!H87 -> 16.351273 | G70: =Report!I87 -> 14.473498 | H70: =Report!J87 -> 12.773644
C71: P/B | D71: (x) | E71: =Report!G88 -> 4.9802129 | F71: =Report!H88 -> 4.2312012 | G71: =Report!I88 -> 3.5797145 | H71: =Report!J88 -> 3.0209879
C72: Tài sản | D72: (VNDbn) | E72: =BS!X38 -> 0 | F72: =BS!Q38 -> 92111.939 | G72: =BS!R38 -> 102999.43 | H72: =BS!S38 -> 115400.63
C73: VCSH | D73: (VNDbn) | E73: =BS!X76 -> 0 | F73: =BS!Q76 -> 42945.223 | G73: =BS!R76 -> 50760.998 | H73: =BS!S76 -> 60149.159
D76: Lịch sử | G76: Our forecast | I76: Market consensus | K76: Company's guidance
D77: 2024 | E77: 2023 | F77: %YoY | G77: 2025F | H77: 2026F | I77: 2025F | J77: 2026F | K77: 2025F
C78: Doanh thu | D78: 62849 | E78: 52618 | F78: 0.194 | G78: =E62 -> 66308.23 | H78: =F62 -> 78944.912 | I78: 75355 | J78: 90525 | K78: 75400
C79: LNST | D79: 7857 | E79: 6465 | F79: 0.218 | G79: =E67 -> 9389.0441 | H79: =F67 -> 11281.049 | I79: 9689 | J79: 11948 | K79: 10585
I81: 32683 | J81: =I81/K78 -> 0.43346154
I82: 6152 | J82: =I82/K79 -> 0.58119981
C86: Main Outputs
D87: Enterprise Value | F87: Equity value | H87: Equity per share
C88: Best case
C89: Base case | D89: =Valuation!K36 -> 165556.59 | F89: =Valuation!E45 -> 181709.88 | H89: =Valuation!I45 -> 106668.11
C90: Worst case
C95: Inputs
C97: Terminal Growth Rate | F97: =Valuation!C7 -> 0.025
C98: WACC | F98: =Valuation!C27 -> 0.099249688
C99: Net Debt | F99: =Valuation!J16 -> -16153.29
C100: Shares Outstanding | F100: =Valuation!J19 -> 1703507121
C101: Current Stock Price | F101: 111600

Sheet Revenue
A1: VNDbn | B1: 2018 | C1: =B1+1 -> 2019 | D1: 2020 | E1: 2021 | F1: 2022 | G1: 2023 | H1: 2024 | I1: 2025 | J1: 2026F | K1: 2027F | L1: 2028F | N1: 2025F | O1: 2024 | V1: QUARTER REPORT | Z1: 4Q18 | AA1: Q1/19 | AB1: Q2/19 | AC1: Q3/19 | AD1: 4Q19 | AE1: Q1/20 | AF1: Q2/20 | AG1: Q3/20 | AH1: 4Q20 | AI1: 1Q21 | AJ1: 2Q21 | AK1: 3Q21 | AL1: 4Q21 | AM1: 1Q22 | AN1: 2Q22 | AO1: 3Q22 | AP1: 4Q22 | AQ1: 1Q23 | AR1: 2Q23 | AS1: 3Q23 | AT1: 4Q23 | AU1: 1Q24 | AV1: 2Q24 | AW1: 3Q24 | AX1: 4Q24 | AY1: 1Q25 | AZ1: 2Q25 | BA1: 3Q25 | BB1: 4Q25 | BC1: 1Q26 | BD1: 6M23 | BE1: 6M24 | BF1: 7M24 | BG1: 8M24 | BH1: 9M24 | BI1: 6M25 | BJ1: 7M25 | BK1: 8M25 | BL1: 9M25 | BP1: 6M26 | BQ1: 2Q26 | CC1: H1/19 | CD1: H1/20 | CE1: H1/21 | CF1: H1/22 | CG1: H1/23 | CH1: 9M23 | CI1: YoY growth | CJ1: H2/19 | CK1: H2/20 | CL1: H2/21 | CM1: H2/22 | CN1: H2/23 | CP1: 8M/2022 | CQ1: 8M/2023
A2: Total net revenue (post-deconsolidation) | B2: =B3-B14 -> 14382.534 | C2: =C3-C14 -> 17318.533 | D2: =D3-D14 -> 18364.247 | E2: =E3-E14 -> 22970.847 | F2: =F3-F14 -> 29279.879 | G2: =G3-G14 -> 36811.901 | H2: =H3-H14 -> 45238.79 | I2: 50605.83 | J2: =J3-J14 -> 57194.607 | K2: =K3-K14 -> 65945.02 | L2: =L3-L14 -> 76536.74 | N2: =N9 -> 0 | O2: =O9 -> 0 | AE2: =PL!BO8 -> 0.0021744814 | AF2: =PL!BP8 -> 0.0024668202 | AG2: =PL!BQ8 -> 0.0033729491 | AH2: =PL!BR8 -> 0.0039105489 | AI2: =PL!BS8 -> 0.0025437597 | AJ2: =PL!BT8 -> -0.0018784805 | AK2: =PL!BU8 -> -0.0043884108 | AL2: =PL!BV8 -> 0.0010001896 | ... BB2: =PL!CL8 -> 0.0016494397 | CD2: =AE2+AF2 -> 0.0046413016 | CP2: 27060 | CQ2: 32827
A3: Total net revenue | B3: =PL!I9 -> 23213.537 | C3: =PL!J9 -> 27716.96 | D3: =PL!K9 -> 29830.401 | E3: =PL!L9 -> 35657.263 | F3: =PL!M9 -> 44009.528 | G3: =PL!N9 -> 52617.901 | H3: =PL!O9 -> 62848.79 | I3: =PL!P9 -> 70207.69 | J3: =J10 -> 78944.912 | K3: =K10 -> 90305.362 | L3: =L10 -> 103820.32 | N3: =N10 -> 66308.23 | O3: =O10 -> 55744.61 | AE3: =PL!BO9 -> 6630.5649 | AF3: =PL!BP9 -> 6980.0025 | AG3: =PL!BQ9 -> 7553.1285 | AH3: =PL!BR9 -> 8666.7046 | AI3: =PL!BS9 -> 7586.3277 | AJ3: =PL!BT9 -> 8641.7073 | AK3: =PL!BU9 -> 8725.172 | AL3: =PL!BV9 -> 10704.056 | ... BB3: =PL!CL9 -> 20225.45 | BC3: 12480 | BD3: =BC3*4 -> 49920 | BP3: 26269 | BQ3: =BP3-BC3 -> 13789 | CD3: =AE3+AF3 -> 13610.567 | CP3: 27060 | CQ3: 32827
A4: % growth | B4: =PL!I10 -> -0.45582999 | C4: =C3/B3-1 -> 0.19399988 | D4: =D3/C3-1 -> 0.0762508 | E4: =E3/D3-1 -> 0.19533301 | F4: =F3/E3-1 -> 0.23423742 | G4: =G3/F3-1 -> 0.19560249 | H4: =H3/G3-1 -> 0.19443743 | I4: =I3/H3-1 -> 0.11708897 | J4: =J3/I3-1 -> 0.12444821 | ... L4: =L3/K3-1 -> 0.14965845 | N4: =N3/H3-1 -> 0.05504386 | O4: =O3/G3-1 -> 0.059422917 | AE4: =AE3/AA3-1 -> #DIV/0! | AF4: =AF3/AB3-1 -> #DIV/0! | AG4: =AG3/AC3-1 -> #DIV/0! | AH4: =AH3/AD3-1 -> #DIV/0! | AI4: =AI3/AE3-1 -> 0.144145 | AJ4: =AJ3/AF3-1 -> 0.2380665 | AK4: =AK3/AG3-1 -> 0.15517324 | AL4: =AL3/AH3-1 -> 0.23507793 | ... BB4: =BB3/AX3-1 -> 0.14866292 | CQ4: =CQ3/CP3-1 -> 0.21311899
A5: Total COGS | B5: =PL!I11 -> 14490.658 | C5: =PL!J11 -> 17004.911 | D5: =PL!K11 -> 18016.743 | E5: =PL!L11 -> 22025.298 | F5: =PL!M11 -> 26842.249 | G5: =PL!N11 -> 32298.347 | H5: =PL!O11 -> 39150.45 | I5: =PL!P11 -> 44217.42 | J5: =J57 -> 37370.882 | K5: =K57 -> 43668.412 | L5: =L57 -> 50958.99 | M5: =J2*66% -> 37748.44 | N5: =N57 -> 41453.585 | O5: =O57 -> 36150.136 | AE5: =PL!BO11 -> 4006.1865 | AF5: =PL!BP11 -> 4258.2478 | AG5: =PL!BQ11 -> 4554.3503 | AH5: =PL!BR11 -> 5195.7837 | AI5: =PL!BS11 -> 4691.8007 | AJ5: =PL!BT11 -> 5201.5261 | AK5: =PL!BU11 -> 5474.2432 | AL5: =PL!BV11 -> 6609.6875 | ... BB5: =PL!CL11 -> 13178.175 | CD5: =AE5+AF5 -> 8264.4344 | CF5: =SUM(AM5:AN5) -> 12030.304
A6: % revenue | B6: =B5/B3 -> 0.62423309 | C6: =C5/C3 -> 0.61352004 | D6: =D5/D3 -> 0.60397255 | E6: =E5/E3 -> 0.61769459 | F6: =F5/F3 -> 0.60991904 | G6: =G5/G3 -> 0.61382812 | H6: =H5/H3 -> 0.62293085 | I6: =I5/I3 -> 0.62980879 | J6: =J5/J2 -> 0.65339871 | K6: =K5/K3 -> 0.48356389 | L6: =L5/L3 -> 0.4908383 | N6: =N5/N3 -> 0.62516501 | O6: =O5/O3 -> 0.64849563 | S6: 7913 | T6: =S6/S8-1 -> 0.22777347 | AE6: =AE5/AA5-1 -> #DIV/0! | AF6: =AF5/AB5-1 -> #DIV/0! | AG6: =AG5/AC5-1 -> #DIV/0! | AH6: =AH5/AD5-1 -> #DIV/0! | AI6: =AI5/AE5-1 -> 0.17113886 | AJ6: =AJ5/AF5-1 -> 0.22151795 | AK6: =AK5/AG5-1 -> 0.20198115 | AL6: =AL5/AH5-1 -> 0.27212522 | ... BB6: =BB5/AX5-1 -> 0.17345338
A7: Total gross profit | B7: =B3-B5 -> 8722.879 | C7: =C3-C5 -> 10712.05 | D7: =D3-D5 -> 11813.657 | E7: =E3-E5 -> 13631.964 | F7: =F3-F5 -> 17167.279 | G7: =G3-G5 -> 20319.553 | H7: =H3-H5 -> 23698.34 | I7: =I3-I5 -> 25990.27 | J7: =J2-J5 -> 19823.725 | K7: =K2-K5 -> 22276.608 | L7: =L2-L5 -> 25577.75 | N7: =N3-N5 -> 24854.645 | O7: =O3-O5 -> 19594.474 | S7: 1038 | T7: =S7/S9-1 -> 0.24759615 | AE7: =PL!BO13 -> 2624.3784 | AF7: =PL!BP13 -> 2721.7547 | AG7: =PL!BQ13 -> 2998.7782 | AH7: =PL!BR13 -> 3470.921 | AI7: =PL!BS13 -> 2894.527 | AJ7: =PL!BT13 -> 3440.1811 | AK7: =PL!BU13 -> 3250.9287 | AL7: =PL!BV13 -> 4094.3682 | ... BB7: =PL!CL13 -> 7047.2751 | CD7: =AE7+AF7 -> 5346.1331
A8: % margin | B8: =B7/B3 -> 0.37576691 | C8: =C7/C3 -> 0.38647996 | D8: =D7/D3 -> 0.39602745 | E8: =E7/E3 -> 0.38230541 | F8: =F7/F3 -> 0.39008096 | G8: =G7/G3 -> 0.38617188 | H8: =H7/H3 -> 0.37706915 | I8: =I7/I2 -> 0.51358253 | J8: =J7/J2 -> 0.34660129 | K8: =K7/K2 -> 0.33780577 | L8: =L7/L2 -> 0.33418917 | N8: =N7/N3 -> 0.37483499 | O8: =O7/O3 -> 0.35150437 | Q8: 56404 | R8: 62849 | S8: =R8-Q8 -> 6445 | AE8: =PL!BO14 -> 0.39580012 | AF8: =PL!BP14 -> 0.38993606 | AG8: =PL!BQ14 -> 0.39702465 | AH8: =PL!BR14 -> 0.40048913 | AI8: =PL!BS14 -> 0.38154521 | AJ8: =PL!BT14 -> 0.39809045 | AK8: =PL!BU14 -> 0.37259194 | AL8: =PL!BV14 -> 0.38250625 | ... BB8: =PL!CL14 -> 0.34843601
Q9: 10239 | R9: 11071 | S9: =R9-Q9 -> 832 | T9: Achieved/Forecast | U9: FPT's 2024 plan | V9: %23/Plan
A10: Net revenue | B10: =SUM(B12:B13,B15:B17) -> 23213.537 | C10: =SUM(C12:C13,C15:C17) -> 27716.96 | D10: =SUM(D12:D13,D15:D17) -> 29830.401 | E10: =SUM(E12:E13,E15:E17) -> 35657.263 | F10: =SUM(F12:F13,F15:F17) -> 44009.528 | G10: =SUM(G12:G13,G15:G17) -> 52618 | H10: =SUM(H12:H13,H15:H17) -> 62850 | I10: =SUM(I12:I13,I15:I17) -> 70114 | J10: =SUM(J11,J14,J17) -> 78944.912 | K10: =SUM(K11,K14,K17) -> 90305.362 | L10: =SUM(L11,L14,L17) -> 103820.32 | N10: =SUM(N11,N14,N17) -> 66308.23 | O10: =SUM(O11,O14,O17) -> 55744.61 | T10: Net revenue | U10: =U11+U12+U13 -> 61850 | AA10: =AA3 -> 0 | AB10: =AB3 -> 0 | AC10: =AC3 -> 0 | AD10: =AD3 -> 0 | AE10: =AE3 -> 6630.5649 | AF10: =AF3 -> 6980.0025 | AG10: =AG3 -> 7553.1285 | AH10: =AH3 -> 8666.7046 | ... AP10: =AP3 -> 13042.426 | AQ10: =SUM(AQ12:AQ13,AQ15:AQ17) -> 11687.891 | AR10: =24166-AQ10 -> 12478.109 | AS10: =37927-AR10-AQ10 -> 13761 | AT10: =52618-AS10-AR10-AQ10 -> 14691 | AU10: =AU11+AU14+AU17 -> 14092 | AV10: =AV11+AV14+AV17 -> 15246 | AW10: =45241-AV10-AU10 -> 15903 | AX10: =62849-AW10-AV10-AU10 -> 17608 | AY10: 16058 | AZ10: =32683-AY10 -> 16625 | BA10: =49887-AZ10-AY10 -> 17204 | BB10: =49887-BA10-AZ10 -> 16058 | BD10: =AQ10+AR10 -> 24166 | BE10: =AU10+AV10 -> 29338 | BI10: =AY10+AZ10 -> 32683 | BL10: =BA10+AZ10+AY10 -> 49887 | BN10: =BI10/N10 -> 0.49289508 | BP10: 26269 | BQ10: =BP10-BC3 -> 13789 | CD10: =AE10+AF10 -> 13610.567 | CE10: =AI10+AJ10 -> 16228.035 | CF10: =AM10+AN10 -> 19826.314 | CG10: =AQ10+AR10 -> 24166
A11: Total IT services | B11: =SUM(B12:B13) -> 13401.574 | C11: =SUM(C12:C13) -> 15783.421 | D11: =SUM(D12:D13) -> 16804.932 | E11: =SUM(E12:E13) -> 20872.244 | F11: =SUM(F12:F13) -> 25762.902 | G11: =31449 -> 31449 | H11: 39110 | I11: 44475 | J11: =SUM(J12,J13) -> 50756.007 | K11: =SUM(K12,K13) -> 58733.788 | L11: =SUM(L12,L13) -> 68460.16 | M11: =J11+J17 -> 57194.607 | N11: =SUM(N12,N13) -> 39843.13 | O11: =SUM(O12,O13) -> 31950.27 | T11: Total IT services | U11: 38150 | AE11: =SUM(AE12:AE13) -> 3594.085 | AF11: =SUM(AF12:AF13) -> 3933.248 | AG11: =SUM(AG12:AG13) -> 4183.63 | AH11: =SUM(AH12:AH13) -> 5093.969 | AI11: =SUM(AI12:AI13) -> 4177.351 | AJ11: =SUM(AJ12:AJ13) -> 4969.317 | AK11: =SUM(AK12:AK13) -> 5237.552 | AL11: =SUM(AL12:AL13) -> 6488.024 | ... AQ11: =SUM(AQ12:AQ13) -> 6844.791 | AR11: =14202-AQ11 -> 7357.209 | AS11: =22517-AR11-AQ11 -> 8315 | AT11: =31449-AS11-AR11-AQ11 -> 8932 | AU11: =AU13+AU12 -> 8471 | AV11: =AV13+AV12 -> 9606 | AW11: =27964-AV11-AU11 -> 9887 | AX11: =39110-AW11-AV11-AU11 -> 11146 | AY11: 9769 | AZ11: =20128-AY11 -> 10359 | BA11: =30949-AZ11-AY11 -> 10821 | BB11: =44475-BA11-AZ11-AY11 -> 13526 | BC11: 10842 | BD11: =AQ11+AR11 -> 14202 | BE11: =AU11+AV11 -> 18077 | BI11: =AY11+AZ11 -> 20128 | BL11: =BA11+AZ11+AY11 -> 30949 | BN11: =BI11/N11 -> 0.50518119 | BP11: 23138 | BQ11: =BP11-BC11 -> 12296 | CD11: =AE11+AF11 -> 7527.333 | CE11: =AI11+AJ11 -> 9146.668 | CF11: =AM11+AN11 -> 11354.504 | CG11: =AQ11+AR11 -> 14202 | CI11: =CG11/CF11-1 -> 0.25078119
A12: Global IT | B12: 8443.472 | C12: 10848.063 | D12: 12000.26 | E12: 14540.801 | F12: 18915.494 | G12: 24288 | H12: 30953 | I12: 35382 | J12: =I12*(1+Scenarios!H9) -> 40571.847 | K12: =J12*(1+Scenarios!I9) -> 47327.529 | L12: =K12*(1+Scenarios!J9) -> 55685.15 | N12: =H12*(1+Scenarios!G9) -> 30952 | O12: =SUM(O159:O162) -> 24288 | T12: Total telecom | U12: 17600 | AE12: 2890.8 | AF12: =5810.278-AE12 -> 2919.478 | AG12: =8778.695-SUM(AE12:AF12) -> 2968.417 | AH12: =12000.26-SUM(AE12:AG12) -> 3221.565 | AI12: 3169.398 | AJ12: 3513.542 | AK12: 3731.633 | AL12: 4126.228 | AM12: 4111.367 | AN12: 4510.72 | AO12: 4857.043 | AP12: 5444.135 | AQ12: 5437.791 | AR12: =11227-AQ12 -> 5789.209 | AS12: =17626-AR12-AQ12 -> 6399 | AT12: =24288-AS12-AR12-AQ12 -> 6662 | AU12: 6999 | AV12: =14573-AU12 -> 7574 | AW12: =22668-AV12-AU12 -> 8095 | AX12: =30953-AW12-AV12-AU12 -> 8285 | AY12: 8186 | AZ12: =16669-AY12 -> 8483 | BA12: =25574-AZ12-AY12 -> 8905 | BB12: =35382-BA12-AZ12-AY12 -> 9808 | BD12: =AQ12+AR12 -> 11227 | BE12: =AU12+AV12 -> 14573 | BI12: =AY12+AZ12 -> 16669 | BL12: =BA12+AZ12+AY12 -> 25574 | BN12: =BI12/N12 -> 0.53854355 | BP12: 18902 | CD12: =AE12+AF12 -> 5810.278 | CE12: =AI12+AJ12 -> 6682.94 | CF12: =AM12+AN12 -> 8622.087 | CG12: =AQ12+AR12 -> 11227 | CI12: =CG12/CF12-1 -> 0.30212094
A13: Domestic IT | B13: 4958.102 | C13: 4935.358 | D13: 4804.672 | E13: 6331.443 | F13: 6847.408 | G13: =G11-G12 -> 7161 | H13: 8157 | I13: 9093 | J13: =I13*(1+Scenarios!H15) -> 10184.16 | K13: =J13*(1+Scenarios!I15) -> 11406.259 | L13: =K13*(1+Scenarios!J15) -> 12775.01 | N13: =H13*(1+Scenarios!G15) -> 8891.13 | O13: =G13*(1+O22) -> 7662.27 | T13: Investment, education & others | U13: 6100 | AE13: 703.285 | AF13: =1717.055-AE13 -> 1013.77 | AG13: =2932.268-SUM(AE13:AF13) -> 1215.213 | AH13: =4804.672-SUM(AE13:AG13) -> 1872.404 | AI13: 1007.953 | AJ13: 1455.775 | AK13: 1505.919 | AL13: 2361.796 | AM13: 1529.745 | AN13: 1202.672 | AO13: 1706.958 | AP13: 2408.033 | AQ13: 1407 | AR13: =2975-AQ13 -> 1568 | AS13: =4891-AR13-AQ13 -> 1916 | AT13: =7161-AS13-AR13-AQ13 -> 2270 | AU13: 1472 | AV13: =3504-AU13 -> 2032 | AW13: =5296-AV13-AU13 -> 1792 | AX13: =8157-AW13-AV13-AU13 -> 2861 | AY13: 1583 | AZ13: =3459-AY13 -> 1876 | BA13: =5376-AZ13-AY13 -> 1917 | BB13: =9093-BA13-AZ13-AY13 -> 3717 | BD13: =AQ13+AR13 -> 2975 | BE13: =AU13+AV13 -> 3504 | BI13: =AY13+AZ13 -> 3459 | BL13: =BA13+AZ13+AY13 -> 5376 | BN13: =BI13/N13 -> 0.38903941 | BP13: 4236 | CD13: =AE13+AF13 -> 1717.055 | CE13: =AI13+AJ13 -> 2463.728 | CF13: =AM13+AN13 -> 2732.417 | CG13: =AQ13+AR13 -> 2975 | CI13: =CG13/CF13-1 -> 0.088779641
A14: Total telecom | B14: =SUM(B15:B16) -> 8831.003 | C14: =SUM(C15:C16) -> 10398.427 | D14: =SUM(D15:D16) -> 11466.154 | E14: =SUM(E15:E16) -> 12686.416 | F14: =SUM(F15:F16) -> 14729.649 | G14: =G15+G16 -> 15806 | H14: 17610 | I14: 19507 | J14: =I14*(1+Scenarios!H24) -> 21750.305 | K14: =J14*(1+Scenarios!I24) -> 24360.342 | L14: =K14*(1+Scenarios!J24) -> 27283.583 | N14: =H14*(1+Scenarios!G24) -> 19723.2 | O14: =SUM(O15:O16) -> 17680.52 | T14: PBT | U14: 10875 | AE14: =SUM(AE15:AE16) -> 2668.02 | AF14: =SUM(AF15:AF16) -> 2770.679 | AG14: =SUM(AG15:AG16) -> 2872.372 | AH14: =SUM(AH15:AH16) -> 3155.083 | AI14: =SUM(AI15:AI16) -> 2925.12 | AJ14: =SUM(AJ15:AJ16) -> 3201.014 | AK14: =SUM(AK15:AK16) -> 3105.698 | AL14: =SUM(AL15:AL16) -> 3454.584 | ... AQ14: =SUM(AQ15:AQ16) -> 3790.224 | AR14: =7682-AQ14 -> 3891.776 | AS14: =11690-AR14-AQ14 -> 4008 | AT14: =15806-AS14-AR14-AQ14 -> 4116 | AU14: =AU15+AU16 -> 4012 | AV14: =AV15+AV16 -> 4232 | AW14: =12800-AV14-AU14 -> 4556 | AX14: =17610-AW14-AV14-AU14 -> 4810 | AY14: 4582 | AZ14: =9357-AY14 -> 4775 | BA14: =14287-AZ14-AY14 -> 4930 | BB14: =19507-AY14-AZ14-BA14 -> 5220 | BD14: =AQ14+AR14 -> 7682 | BE14: =AU14+AV14 -> 8244 | BI14: =AY14+AZ14 -> 9357 | BL14: =BA14+AZ14+AY14 -> 14287 | BN14: =BI14/N14 -> 0.47441592 | CD14: =AE14+AF14 -> 5438.699 | CE14: =AI14+AJ14 -> 6126.134 | CF14: =AM14+AN14 -> 7076.665 | CG14: =AQ14+AR14 -> 7682 | CI14: =CG14/CF14-1 -> 0.085539587
A15: Communication | B15: 8293.162 | C15: 9789.511 | D15: 10867.003 | E15: 12078.678 | F15: 13954.22 | G15: 15186 | H15: 16906 | I15: 18702 | J15: =SUM(J199,J201) -> 20909.325 | K15: =SUM(K199,K201) -> 23355.703 | L15: =SUM(L199,L201) -> 26051.256 | N15: =SUM(N199,N201) -> 19184.84 | O15: =SUM(O199,O201) -> 16998.52 | T15: Total IT services | U15: 5195 | AE15: 2565.155 | AF15: =5217.39-AE15 -> 2652.235 | AG15: =7947.542-SUM(AE15:AF15) -> 2730.152 | AH15: =10867.003-SUM(AE15:AG15) -> 2919.461 | AI15: 2803.634 | AJ15: 3043.648 | AK15: 2974.898 | AL15: 3256.498 | AM15: 3320.123 | AN15: 3406.44 | AO15: 3516.78 | AP15: 3710.877 | AQ15: 3694.996 | AR15: =7423-AQ15 -> 3728.004 | AS15: =11278-AR15-AQ15 -> 3855 | AT15: =15186-AS15-AR15-AQ15 -> 3908 | AU15: 3885 | AV15: =7966-AU15 -> 4081 | AW15: =12320-AV15-AU15 -> 4354 | AX15: =16906-AW15-AV15-AU15 -> 4586 | AY15: 4465 | AZ15: =9030-AY15 -> 4565 | BA15: =13738-AZ15-AY15 -> 4708 | BB15: =18702-AY15-AZ15-BA15 -> 4964 | BD15: =AQ15+AR15 -> 7423 | BE15: =AU15+AV15 -> 7966 | BI15: =AY15+AZ15 -> 9030 | BL15: =BA15+AZ15+AY15 -> 13738 | BN15: =BI15/N15 -> 0.47068414 | CD15: =AE15+AF15 -> 5217.39 | CE15: =AI15+AJ15 -> 5847.282 | CF15: =AM15+AN15 -> 6726.563 | CG15: =AQ15+AR15 -> 7423 | CI15: =CG15/CF15-1 -> 0.10353534
A16: Digital content | B16: 537.841 | C16: 608.916 | D16: 599.151 | E16: 607.738 | F16: 775.429 | G16: 620 | H16: 705 | I16: 805 | J16: =I16*(1+J25) -> 917.7 | K16: =J16*(1+K25) -> 1046.178 | L16: =K16*(1+L25) -> 1192.6429 | N16: =H16*(1+N25) -> 803.7 | O16: =G16*(1+O25) -> 682 | T16: Total telecom | U16: 3508 | AE16: 102.865 | AF16: =221.309-AE16 -> 118.444 | AG16: =363.529-SUM(AE16:AF16) -> 142.22 | AH16: =599.151-SUM(AE16:AG16) -> 235.622 | AI16: 121.486 | AJ16: 157.366 | AK16: 130.8 | AL16: 198.086 | AM16: 151.004 | AN16: 199.098 | AO16: 213.814 | AP16: 211.513 | AQ16: 95.228 | AR16: =259-AQ16 -> 163.772 | AS16: =413-AR16-AQ16 -> 154 | AT16: =620-AS16-AR16-AQ16 -> 207 | AU16: 127 | AV16: =278-AU16 -> 151 | AW16: =480-AV16-AU16 -> 202 | AX16: =705-AW16-AV16-AU16 -> 225 | AY16: 117 | AZ16: =327-AY16 -> 210 | BA16: =549-AZ16-AY16 -> 222 | BB16: =805-AY16-AZ16-BA16 -> 256 | BD16: =AQ16+AR16 -> 259 | BE16: =AU16+AV16 -> 278 | BI16: =AY16+AZ16 -> 327 | BL16: =BA16+AZ16+AY16 -> 549 | BN16: =BI16/N16 -> 0.40686823 | CD16: =AE16+AF16 -> 221.309 | CE16: =AI16+AJ16 -> 278.852 | CF16: =AM16+AN16 -> 350.102 | CG16: =AQ16+AR16 -> 259 | CI16: =CG16/CF16-1 -> -0.26021559
A17: Education, Investments and others | B17: =1375.177-394.217142275 -> 980.95986 | C17: =1792.058-256.945847725005 -> 1535.1122 | D17: =2187.175-627.860473176002 -> 1559.3145 | E17: =3237.52-1138.91745497299 -> 2098.6025 | F17: =5066.948-1549.971319089 -> 3516.9767 | G17: 5363 | H17: 6129 | I17: 6132 | J17: =I17*(1+Scenarios!H28) -> 6438.6 | K17: =J17*(1+Scenarios!I28) -> 7211.232 | L17: =K17*(1+Scenarios!J28) -> 8076.5798 | N17: =H17*(1+Scenarios!G28) -> 6741.9 | O17: =G17*(1+O26) -> 6113.82 | T17: Investment, education & others | U17: 2172 | AE17: =447.489-79.029 -> 368.46 | AF17: =644.537-AE17 -> 276.077 | AG17: =1141.663-SUM(AE17:AF17) -> 497.126 | AH17: =1559.314-SUM(AE17:AG17) -> 417.651 | AI17: =700.646-216.789330046001 -> 483.85667 | AJ17: =690.291-218.914715178998 -> 471.37628 | AK17: =800.72-418.798043028 -> 381.92196 | AL17: =1045.863-284.415366719997 -> 761.44763 | AM17: =1039.158-421.143155609001 -> 618.01484 | AN17: =1047.914-270.783909041 -> 777.13009 | AO17: =1256.65-402.685979647002 -> 853.96402 | AP17: =1723.226-455.357728890998 -> 1267.8683 | AQ17: =1492.142-439.266 -> 1052.876 | AR17: =2281-AQ17 -> 1228.124 | AS17: =3720-AR17-AQ17 -> 1439 | AT17: =5363-AS17-AR17-AQ17 -> 1643 | AU17: 1609 | AV17: =3017-AU17 -> 1408 | AW17: =4477-AV17-AU17 -> 1460 | AX17: =6129-AW17-AV17-AU17 -> 1652 | AY17: 1707 | AZ17: =3198-AY17 -> 1491 | BA17: =4651-AZ17-AY17 -> 1453 | BB17: =6132-AY17-AZ17-BA17 -> 1481 | BC17: 1638 | BD17: =AQ17+AR17 -> 2281 | BE17: =AU17+AV17 -> 3017 | BI17: =AY17+AZ17 -> 3198 | BL17: =BA17+AZ17+AY17 -> 4651 | BN17: =BI17/N17 -> 0.47434699 | BP17: 3131 | BQ17: =BP17-BC17 -> 1493 | CD17: =AE17+AF17 -> 644.537 | CE17: =AI17+AJ17 -> 955.23295 | CF17: =AM17+AN17 -> 1395.1449 | CG17: =AQ17+AR17 -> 2281 | CI17: =CG17/CF17-1 -> 0.63495558
A19: Net revenue growth | B19: Tổng | C19: =C10/B10-1 -> 0.19399988 | D19: =D10/C10-1 -> 0.0762508 | E19: =E10/D10-1 -> 0.19533301 | F19: =F10/E10-1 -> 0.23423742 | G19: =G10/F10-1 -> 0.19560474 | H19: =H10/G10-1 -> 0.19445817 | I19: =I10/H10-1 -> 0.11557677 | J19: =J10/I10-1 -> 0.12595076 | ... L19: =L10/K10-1 -> 0.14965845 | N19: =N10/H10-1 -> 0.055023548 | O19: =O10/G10-1 -> 0.059420921 | AI19: =AI10/AE10-1 -> 0.144145 | AJ19: =AJ10/AF10-1 -> 0.2380665 | AK19: =AK10/AG10-1 -> 0.15517324 | AL19: =AL10/AH10-1 -> 0.23507793 | AM19: =AM10/AI10-1 -> 0.28260395 | AN19: =AN10/AJ10-1 -> 0.16829462 | AO19: =AO10/AK10-1 -> 0.27774662 | AP19: =AP10/AL10-1 -> 0.21845651 | ... BB19: =BB10/AX10-1 -> -0.088028169 | BD19: Net revenue growth | BE19: =BE10/BD10-1 -> 0.2140197 | BI19: =BI10/BE10-1 -> 0.11401595 | BK19: 0.105 | BL19: 0.103
A20: Total IT services | B20: CNTT | C20: =C11/B11-1 -> 0.1777289 | D20: =D11/C11-1 -> 0.064720506 | E20: =E11/D11-1 -> 0.24203085 | F20: =F11/E11-1 -> 0.23431395 | G20: =G11/F11-1 -> 0.22070875 | H20: =H11/G11-1 -> 0.24360075 | I20: =I11/H11-1 -> 0.13717719 | J20: =J11/I11-1 -> 0.14122556 | ... L20: =L11/K11-1 -> 0.16560096 | N20: =N11/H11-1 -> 0.018745334 | O20: =O11/G11-1 -> 0.01593914 | AE20: =AE11/AA11-1 -> #DIV/0! | AF20: =AF11/AB11-1 -> #DIV/0! | AG20: =AG11/AC11-1 -> #DIV/0! | AH20: =AH11/AD11-1 -> #DIV/0! | AI20: =AI11/AE11-1 -> 0.16228498 | AJ20: =AJ11/AF11-1 -> 0.26341309 | AK20: =AK11/AG11-1 -> 0.25191568 | AL20: =AL11/AH11-1 -> 0.27366774 | ... BB20: =BB11/AX11-1 -> 0.21352952 | BD20: Total IT services | BE20: =BE11/BD11-1 -> 0.27284889 | BI20: =BI11/BE11-1 -> 0.11345909 | BK20: 0.106 | BL20: 0.107
A21: Global IT | B21: CNTT nước ngoài | C21: =C12/B12-1 -> 0.28478699 | D21: =D12/C12-1 -> 0.10621223 | E21: =E12/D12-1 -> 0.21170716 | F21: =F12/E12-1 -> 0.3008564 | G21: =G12/F12-1 -> 0.28402673 | H21: =H12/G12-1 -> 0.27441535 | I21: =I12/H12-1 -> 0.14308791 | J21: =J12/I12-1 -> 0.14668042 | ... L21: =L12/K12-1 -> 0.17659111 | N21: =N12/H12-1 -> -3.2307046e-05 | O21: =O12/G12-1 -> 0 | AI21: =AI12/AE12-1 -> 0.096374014 | AJ21: =AJ12/AF12-1 -> 0.20348295 | AK21: =AK12/AG12-1 -> 0.25711212 | AL21: =AL12/AH12-1 -> 0.28081476 | AM21: =AM12/AI12-1 -> 0.29720755 | AN21: =AN12/AJ12-1 -> 0.2838099 | AO21: =AO12/AK12-1 -> 0.30158646 | AP21: =AP12/AL12-1 -> 0.31939752 | ... BB21: =BB12/AX12-1 -> 0.18382619 | BD21: Global IT | BE21: =BE12/BD12-1 -> 0.29803153 | BI21: =BI12/BE12-1 -> 0.14382763 | BK21: 0.126 | BL21: 0.128 | BN21: =27123-22437 -> 4686
A22: Domestic IT | B22: CNTT trong nước | C22: =C13/B13-1 -> -0.0045872392 | D22: =D13/C13-1 -> -0.026479538 | E22: =E13/D13-1 -> 0.317768 | F22: =F13/E13-1 -> 0.081492481 | G22: =G13/F13-1 -> 0.045797183 | H22: =H13/G13-1 -> 0.13908672 | I22: =I13/H13-1 -> 0.11474807 | J22: =J13/I13-1 -> 0.12 | ... L22: =L13/K13-1 -> 0.12 | N22: =N13/H13-1 -> 0.09 | O22: 0.07 | T22: =O12+O13 -> 31950.27 | AI22: =AI13/AE13-1 -> 0.43320702 | AJ22: =AJ13/AF13-1 -> 0.43600126 | AK22: =AK13/AG13-1 -> 0.23922226 | AL22: =AL13/AH13-1 -> 0.26137094 | AM22: =AM13/AI13-1 -> 0.51767493 | AN22: =AN13/AJ13-1 -> -0.17386135 | AO22: =AO13/AK13-1 -> 0.13349921 | AP22: =AP13/AL13-1 -> 0.019577051 | ... BB22: =BB13/AX13-1 -> 0.29919609 | BD22: Domestic IT | BE22: =BE13/BD13-1 -> 0.17781513 | BI22: =BI13/BE13-1 -> -0.012842466 | BK22: 0.02 | BL22: 0.015 | BN22: =24525-19934 -> 4591 | BO22: =BN22/BN21-1 -> -0.020273154
A23: Total telecom | B23: Viễn thông | C23: =C14/B14-1 -> 0.17749105 | D23: =D14/C14-1 -> 0.10268159 | E23: =E14/D14-1 -> 0.10642296 | F23: =F14/E14-1 -> 0.16105676 | G23: =G14/F14-1 -> 0.073073771 | H23: =H14/G14-1 -> 0.11413387 | I23: =I14/H14-1 -> 0.10772288 | J23: =J14/I14-1 -> 0.115 | ... L23: =L14/K14-1 -> 0.12 | N23: =N14/H14-1 -> 0.12 | O23: =O14/G14-1 -> 0.11859547 | V23: =#REF!/F14-1 -> #REF! | W23: =O14/#REF!-1 -> #REF! | AI23: =AI14/AE14-1 -> 0.096363595 | AJ23: =AJ14/AF14-1 -> 0.15531752 | AK23: =AK14/AG14-1 -> 0.081231122 | AL23: =AL14/AH14-1 -> 0.094926504 | AM23: =AM14/AI14-1 -> 0.1866614 | AN23: =AN14/AJ14-1 -> 0.12637371 | AO23: =AO14/AK14-1 -> 0.20120952 | AP23: =AP14/AL14-1 -> 0.13541602 | ... BB23: =BB14/AX14-1 -> 0.085239085 | BD23: Total telecom | BE23: =BE14/BD14-1 -> 0.073158032 | BI23: =BI14/BE14-1 -> 0.13500728 | BK23: 0.123 | BL23: 0.116
A24: Telecom | B24: Viễn thông | C24: =C15/B15-1 -> 0.18043166 | D24: =D15/C15-1 -> 0.11006597 | E24: =E15/D15-1 -> 0.11150038 | F24: =F15/E15-1 -> 0.15527709 | G24: =G15/F15-1 -> 0.088272938 | H24: =H15/G15-1 -> 0.11326222 | I24: =I15/H15-1 -> 0.10623447 | J24: =J15/I15-1 -> 0.11802615 | ... L24: =L15/K15-1 -> 0.11541306 | N24: =N15/H15-1 -> 0.13479475 | O24: =O15/G15-1 -> 0.11935467 | AI24: =AI15/AE15-1 -> 0.092968651 | AJ24: =AJ15/AF15-1 -> 0.14757855 | AK24: =AK15/AG15-1 -> 0.089645558 | AL24: =AL15/AH15-1 -> 0.11544494 | AM24: =AM15/AI15-1 -> 0.18422126 | AN24: =AN15/AJ15-1 -> 0.11919644 | AO24: =AO15/AK15-1 -> 0.18215146 | AP24: =AP15/AL15-1 -> 0.13952995 | ... BB24: =BB15/AX15-1 -> 0.082424771 | BD24: Telecom | BE24: =BE15/BD15-1 -> 0.073151017 | BI24: =BI15/BE15-1 -> 0.13356766 | BL24: 0.115
A25: Digital content | B25: Quảng cáo online | C25: =C16/B16-1 -> 0.13214872 | D25: =D16/C16-1 -> -0.016036695 | E25: =E16/D16-1 -> 0.014331946 | F25: =F16/E16-1 -> 0.27592647 | G25: =G16/F16-1 -> -0.20044259 | H25: =H16/G16-1 -> 0.13709677 | I25: =I16/H16-1 -> 0.14184397 | J25: 0.14 | K25: 0.14 | L25: 0.14 | N25: 0.14 | O25: =Assumptions!AG20 -> 0.1 | AI25: =AI16/AE16-1 -> 0.18102367 | AJ25: =AJ16/AF16-1 -> 0.32861099 | AK25: =AK16/AG16-1 -> -0.08029813 | AL25: =AL16/AH16-1 -> -0.15930601 | AM25: =AM16/AI16-1 -> 0.2429745 | AN25: =AN16/AJ16-1 -> 0.2651907 | AO25: =AO16/AK16-1 -> 0.63466361 | AP25: =AP16/AL16-1 -> 0.06778369 | ... BB25: =BB16/AX16-1 -> 0.13777778 | BD25: Digital content | BE25: =BE16/BD16-1 -> 0.073359073 | BI25: =BI16/BE16-1 -> 0.17625899 | BL25: 0.144
A26: Education & Investments | B26: Giáo dục | C26: =C17/B17-1 -> 0.56490823 | D26: =D17/C17-1 -> 0.015765867 | E26: =E17/D17-1 -> 0.34584942 | F26: =F17/E17-1 -> 0.67586601 | G26: =G17/F17-1 -> 0.52488927 | H26: =H17/G17-1 -> 0.14283051 | I26: =I17/H17-1 -> 0.00048947626 | J26: =J17/I17-1 -> 0.05 | ... L26: =L17/K17-1 -> 0.12 | N26: =N17/H17-1 -> 0.1 | O26: 0.14 | AI26: =AI17/AE17-1 -> 0.31318642 | AJ26: =AJ17/AF17-1 -> 0.70740875 | AK26: =AK17/AG17-1 -> -0.23174013 | AL26: =AL17/AH17-1 -> 0.82316727 | AM26: =AM17/AI17-1 -> 0.27726842 | AN26: =AN17/AJ17-1 -> 0.64864062 | AO26: =AO17/AK17-1 -> 1.2359647 | AP26: =AP17/AL17-1 -> 0.66507612 | ... BB26: =BB17/AX17-1 -> -0.1035109 | BD26: Investment, education & others | BE26: =BE17/BD17-1 -> 0.3226655 | BI26: =BI17/BE17-1 -> 0.059993371 | BK26: 0.044 | BL26: 0.039
A28: % net revenue contribution
A29: Total IT services | B29: =B11/B$3 -> 0.5773172 | C29: =C11/C$3 -> 0.56944993 | D29: =D11/D$3 -> 0.56334919 | E29: =E11/E$3 -> 0.58535744 | F29: =F11/F$3 -> 0.58539374 | G29: =G11/G$3 -> 0.59768633 | H29: =H11/H$3 -> 0.62228724 | I29: =I11/I$3 -> 0.63347761 | ... L29: =L11/L$3 -> 0.65941001 | N29: =N11/N$3 -> 0.6008776 | O29: =O11/O$3 -> 0.57315443 | AI29: =AI11/AI$10 -> 0.55064205 | AJ29: =AJ11/AJ$10 -> 0.5750388 | AK29: =AK11/AK$10 -> 0.60028066 | AL29: =AL11/AL$10 -> 0.60612764 | AM29: =AM11/AM$10 -> 0.57974973 | AN29: =AN11/AN$10 -> 0.56590313 | AO29: =AO11/AO$10 -> 0.58877573 | AP29: =AP11/AP$10 -> 0.6020481 | ... BB29: =BB11/BB$10 -> 0.84232158 | BD29: =BD11/BD$10 -> 0.58768518 | BE29: =BE11/BE$10 -> 0.61616334 | BI29: =BI11/BI$10 -> 0.61585534
A30: Global IT | B30: =B12/B$3 -> 0.36373053 | C30: =C12/C$3 -> 0.39138718 | D30: =D12/D$3 -> 0.4022829 | E30: =E12/E$3 -> 0.40779353 | F30: =F12/F$3 -> 0.42980452 | G30: =G12/G$3 -> 0.46159196 | H30: =H12/H$3 -> 0.49249954 | I30: =I12/I$3 -> 0.50396189 | ... L30: =L12/L$3 -> 0.53636079 | N30: =N12/N$3 -> 0.46678972 | O30: =O12/O$3 -> 0.43570132 | AI30: =AI12/AI$10 -> 0.41777763 | AJ30: =AJ12/AJ$10 -> 0.40657961 | AK30: =AK12/AK$10 -> 0.4276859 | AL30: =AL12/AL$10 -> 0.38548268 | AM30: =AM12/AM$10 -> 0.4225344 | AN30: =AN12/AN$10 -> 0.44678023 | AO30: =AO12/AO$10 -> 0.43566554 | AP30: =AP12/AP$10 -> 0.41741735 | ... BB30: =BB12/BB$10 -> 0.6107859 | BD30: =BD12/BD$10 -> 0.46457833 | BE30: =BE12/BE$10 -> 0.49672779 | BI30: =BI12/BI$10 -> 0.5100205
A31: Domestic IT | B31: =B13/B$3 -> 0.21358667 | C31: =C13/C$3 -> 0.17806274 | D31: =D13/D$3 -> 0.16106629 | E31: =E13/E$3 -> 0.17756391 | F31: =F13/F$3 -> 0.15558922 | G31: =G13/G$3 -> 0.13609437 | H31: =H13/H$3 -> 0.1297877 | I31: =I13/I$3 -> 0.12951573 | ... L31: =L13/L$3 -> 0.12304923 | N31: =N13/N$3 -> 0.13408788 | O31: =O13/O$3 -> 0.13745311 | AI31: =AI13/AI$10 -> 0.13286442 | AJ31: =AJ13/AJ$10 -> 0.16845919 | AK31: =AK13/AK$10 -> 0.17259476 | AL31: =AL13/AL$10 -> 0.22064497 | AM31: =AM13/AM$10 -> 0.15721532 | AN31: =AN13/AN$10 -> 0.1191229 | AO31: =AO13/AO$10 -> 0.15311019 | AP31: =AP13/AP$10 -> 0.18463075 | ... BB31: =BB13/BB$10 -> 0.23147341 | BD31: =BD13/BD$10 -> 0.12310684 | BE31: =BE13/BE$10 -> 0.11943554 | BI31: =BI13/BI$10 -> 0.10583484
A32: Total telecom | B32: =B14/B$3 -> 0.38042471 | C32: =C14/C$3 -> 0.37516477 | D32: =D14/D$3 -> 0.38437814 | E32: =E14/E$3 -> 0.35578772 | F32: =F14/F$3 -> 0.33469228 | G32: =G14/G$3 -> 0.30039207 | H32: =H14/H$3 -> 0.28019633 | I32: =I14/I$3 -> 0.27784706 | ... L32: =L14/L$3 -> 0.26279617 | N32: =N14/N$3 -> 0.29744724 | O32: =O14/O$3 -> 0.31717004 | AI32: =AI14/AI$10 -> 0.38557786 | AJ32: =AJ14/AJ$10 -> 0.37041454 | AK32: =AK14/AK$10 -> 0.35594691 | AL32: =AL14/AL$10 -> 0.32273599 | AM32: =AM14/AM$10 -> 0.3567355 | AN32: =AN14/AN$10 -> 0.35712327 | AO32: =AO14/AO$10 -> 0.33462567 | AP32: =AP14/AP$10 -> 0.30074082 | ... BB32: =BB14/BB$10 -> 0.32507162 | BD32: =BD14/BD$10 -> 0.31788463 | BE32: =BE14/BE$10 -> 0.28100075 | BI32: =BI14/BI$10 -> 0.28629563
A33: Telecom | B33: =B15/B$3 -> 0.35725543 | C33: =C15/C$3 -> 0.35319569 | D33: =D15/D$3 -> 0.3642929 | E33: =E15/E$3 -> 0.33874384 | F33: =F15/F$3 -> 0.31707271 | G33: =G15/G$3 -> 0.288609 | H33: =H15/H$3 -> 0.26899484 | I33: =I15/I$3 -> 0.26638108 | ... L33: =L15/L$3 -> 0.25092637 | N33: =N15/N$3 -> 0.28932819 | O33: =O15/O$3 -> 0.30493567 | AI33: =AI15/AI$10 -> 0.36956405 | AJ33: =AJ15/AJ$10 -> 0.35220448 | AK33: =AK15/AK$10 -> 0.3409558 | AL33: =AL15/AL$10 -> 0.30423029 | AM33: =AM15/AM$10 -> 0.34121648 | AN33: =AN15/AN$10 -> 0.3374029 | AO33: =AO15/AO$10 -> 0.31544705 | AP33: =AP15/AP$10 -> 0.28452352 | ... BB33: =BB15/BB$10 -> 0.30912941 | BD33: =BD15/BD$10 -> 0.30716709 | BE33: =BE15/BE$10 -> 0.27152498 | BI33: =BI15/BI$10 -> 0.27629043
A34: Digital content | B34: =B16/B$3 -> 0.023169283 | C34: =C16/C$3 -> 0.021969076 | D34: =D16/D$3 -> 0.020085248 | E34: =E16/E$3 -> 0.017043877 | F34: =F16/F$3 -> 0.017619571 | G34: =G16/G$3 -> 0.011783062 | H34: =H16/H$3 -> 0.0112174 | I34: =I16/I$3 -> 0.01146598 | ... L34: =L16/L$3 -> 0.011487567 | N34: =N16/N$3 -> 0.012120667 | O34: =O16/O$3 -> 0.012234367 | AI34: =AI16/AI$10 -> 0.016013809 | AJ34: =AJ16/AJ$10 -> 0.018210059 | AK34: =AK16/AK$10 -> 0.014991109 | AL34: =AL16/AL$10 -> 0.018505696 | AM34: =AM16/AM$10 -> 0.01551902 | AN34: =AN16/AN$10 -> 0.019720366 | AO34: =AO16/AO$10 -> 0.019178622 | AP34: =AP16/AP$10 -> 0.016217305 | ... BB34: =BB16/BB$10 -> 0.015942209 | BD34: =BD16/BD$10 -> 0.010717537 | BE34: =BE16/BE$10 -> 0.0094757652 | BI34: =BI16/BI$10 -> 0.010005201
A35: Investment, education & others | B35: =B17/B$3 -> 0.042258096 | C35: =C17/C$3 -> 0.0553853 | D35: =D17/D$3 -> 0.052272665 | E35: =E17/E$3 -> 0.058854842 | F35: =F17/F$3 -> 0.079913984 | G35: =G17/G$3 -> 0.10192349 | H35: =H17/H$3 -> 0.097519777 | I35: =I17/I$3 -> 0.08734086 | ... L35: =L17/L$3 -> 0.077793823 | N35: =N17/N$3 -> 0.10167516 | O35: =O17/O$3 -> 0.10967554 | AI35: =AI17/AI$10 -> 0.063780091 | AJ35: =AJ17/AJ$10 -> 0.054546662 | AK35: =AK17/AK$10 -> 0.043772428 | AL35: =AL17/AL$10 -> 0.071136367 | AM35: =AM17/AM$10 -> 0.063514771 | AN35: =AN17/AN$10 -> 0.0769736 | AO35: =AO17/AO$10 -> 0.076598601 | AP35: =AP17/AP$10 -> 0.097211074 | ... BB35: =BB17/BB$10 -> 0.092228173 | BD35: =BD17/BD$10 -> 0.094388811 | BE35: =BE17/BE$10 -> 0.10283591 | BI35: =BI17/BI$10 -> 0.097849035
A37: Production costs by factors | B37: =SUM(B38:B39,B53:B55) -> 20176.807 | C37: =SUM(C38:C39,C53:C55) -> 23714.657 | D37: =SUM(D38:D39,D53:D55) -> 25248.395 | E37: =SUM(E38:E39,E53:E55) -> 30325.982 | F37: =SUM(F38:F39,F53:F55) -> 37206.167 | G37: =SUM(G38:G39,G53:G55) -> 44119.808 | H37: =SUM(H38:H39,H53:H55) -> 52322.78 | I37: =SUM(I38:I39,I53:I55) -> 62507.503
A38: Raw materials | B38: 3565.6454 | C38: 4163.1202 | D38: 3526.4899 | E38: 5172.5485 | F38: 5295.4224 | G38: =Data!AX300 -> 5506.3275 | H38: =Data!AY300 -> 6642.59 | I38: =Data!AZ300 -> 8013.3269
A39: Labour costs | B39: 7707.9083 | C39: 10267.171 | D39: 12390.314 | E39: 15080.424 | F39: 18798.003 | G39: =Data!AX301 -> 22824.862 | H39: =Data!AY301 -> 26455.12 | I39: =Data!AZ301 -> 30662.765 | J39: =J40*J45 -> 30690 | K39: =K40*K45 -> 37510 | L39: =L40*L45 -> 44561.88 | N39: =N40*N45 -> 33542 | O39: =O40*O45 -> 25781.165 | T39: [3.COGs Assumption]
A40: # employees | B40: =16940+9531+1372 -> 27843 | C40: =17628+9361+1792 -> 28781 | D40: =18728+9803+2120 -> 30651 | E40: =24068+10346+2766 -> 37180 | F40: =28533+9478+4397 -> 42408 | G40: 48162 | I40: 54100 | J40: 45000 | K40: 50000 | L40: 55000 | N40: 54100 | O40: =Assumptions!AG30 -> 50000
A41: % growth | C41: =C40/B40-1 -> 0.033688898 | D41: =D40/C40-1 -> 0.06497342 | E41: =E40/D40-1 -> 0.21301099 | F41: =F40/E40-1 -> 0.14061323 | G41: =G40/F40-1 -> 0.13568195 | I41: =I40/C40-1 -> 0.87971231 | J41: =J40/N40-1 -> -0.16820702 | K41: =K40/J40-1 -> 0.11111111 | L41: =L40/K40-1 -> 0.1 | N41: =N40/H40-1 -> #DIV/0! | O41: =O40/G40-1 -> 0.038162867
A42: technology | B42: 16940 | C42: 17628 | D42: 18728 | E42: 24068 | F42: 28533
A43: telecommunications | B43: 9531 | C43: 9355 | D43: 9803 | E43: 10346 | F43: 9478
A44: education & investment | B44: 1372 | C44: 1972 | D44: 2120 | E44: 2766 | F44: 4397
A45: Average annual salary (VNDbn) | B45: =B39/B40 -> 0.27683469 | C45: =C39/C40 -> 0.35673434 | D45: =D39/D40 -> 0.40423849 | E45: =E39/E40 -> 0.40560581 | F45: =F39/F40 -> 0.44326549 | G45: =G39/G40 -> 0.47391848 | I45: 0.62 | J45: =I45*(1+J46) -> 0.682 | K45: =J45*(1+K46) -> 0.7502 | L45: =K45*(1+L46) -> 0.810216 | N45: 0.62 | O45: =G45*(1+O46) -> 0.51562331
A46: % growth | C46: =C45/B45-1 -> 0.28861862 | D46: =D45/C45-1 -> 0.13316394 | E46: =E45/D45-1 -> 0.0033824633 | F46: =F45/E45-1 -> 0.092847966 | G46: =G45/F45-1 -> 0.069152675 | I46: 0.088 | J46: 0.1 | K46: 0.1 | L46: 0.08 | N46: 0.088 | O46: 0.088 | T46: =570/12 -> 47.5
A47: # Global IT services employees | E47: 18214 | F47: 22089 | G47: 25213
A48: % growth | F48: =(F47/E47)-1 -> 0.21274844 | G48: =(G47/F47)-1 -> 0.14142786 | H48: =(H47/G47)-1 -> -1 | I48: =(I47/H47)-1 -> #DIV/0!
A49: # Revenue per employee (VNDmn) | B49: =(B10/B40) -> 0.83372973 | C49: =(C10/C40) -> 0.96302978 | D49: =(D10/D40) -> 0.97322764 | E49: =(E10/E40) -> 0.95904418 | F49: =(F10/F40) -> 1.0377648 | G49: =(G10/G40) -> 1.0925211 | H49: =(H10/H40) -> #DIV/0! | I49: =(I10/I40) -> 1.2960074 | ... L49: =(L10/L40) -> 1.8876422 | N49: =(N10/H40) -> #DIV/0! | O49: =(O10/O40) -> 1.1148922
A50: % growth | C50: =C49/B49-1 -> 0.15508629 | D50: =D49/C49-1 -> 0.010589353 | E50: =E49/D49-1 -> -0.014573637 | F50: =F49/E49-1 -> 0.082082325 | G50: =G49/F49-1 -> 0.052763712 | H50: =H49/G49-1 -> #DIV/0! | I50: =I49/H49-1 -> #DIV/0! | J50: =J49/I49-1 -> 0.35364303 | ... L50: =L49/K49-1 -> 0.045144047 | N50: =N49/H49-1 -> #DIV/0!
A51: # Total production employees | E51: 16787 | F51: 20527 | G51: 23434 | H51: 23434 | I51: 23435
A52: % growth | F52: =(F51/E51)-1 -> 0.22279145 | G52: =(G51/F51)-1 -> 0.14161836 | H52: =(H51/G51)-1 -> 0 | I52: =(I51/H51)-1 -> 4.2673039e-05
A53: Depreciation expense | B53: 1872.6636 | C53: 2447.4293 | D53: 1490.6075 | E53: 1643.9157 | F53: 1833.0645 | G53: =Data!AX302 -> 2286.5142 | H53: =Data!AY302 -> 2531.21 | I53: =Data!AZ302 -> 2802.0925 | J53: =BS!Q230 -> 2697.8567 | K53: =BS!R230 -> 2700.7971 | L53: =BS!S230 -> 2734.974 | N53: =BS!Z230 -> 0 | O53: =BS!Y230 -> 2197.6753
A54: Outside service expenses | B54: 5700.5573 | C54: 5577.6488 | D54: 6459.2496 | E54: 7102.0209 | F54: 9678.384 | G54: =Data!AX303 -> 10497.59 | H54: =Data!AY303 -> 13932.61 | I54: =Data!AZ303 -> 18491.638
A55: Other cash expenses | B55: 1330.0327 | C55: 1259.2878 | D55: 1381.7339 | E55: 1327.0732 | F55: 1601.2936 | G55: =Data!AX304 -> 3004.5151 | H55: =Data!AY304 -> 2761.25 | I55: =Data!AZ304 -> 2537.6812
T56: Achieved/Forecast | U56: 2Q2023 | V56: %23/Forecast
A57: COGS by factors | B57: =B5 -> 14490.658 | C57: =C5 -> 17004.911 | D57: =D5 -> 18016.743 | E57: =E5 -> 22025.298 | F57: =F5 -> 26842.249 | G57: =G5 -> 32298.347 | H57: =H5 -> 39150.45 | I57: =I5 -> 44217.42 | J57: =SUM(J59:J63) -> 37370.882 | K57: =SUM(K59:K63) -> 43668.412 | L57: =SUM(L59:L63) -> 50958.99 | N57: =SUM(N59:N63) -> 41453.585 | O57: =SUM(O59:O63) -> 36150.136 | T57: COGs | U57: 14964.039 | V57: =U57/#REF! -> #REF! | AI57: =PL!BS11 -> 4691.8007 | AJ57: =PL!BT11 -> 5201.5261 | AK57: =PL!BU11 -> 5474.2432 | AL57: =PL!BV11 -> 6609.6875 | AM57: =PL!BW11 -> 5776.9326 | AN57: =PL!BX11 -> 6253.3717 | AO57: =PL!BY11 -> 6789.0733 | AP57: =PL!BZ11 -> 7801.1525
A58: % production costs | B58: =B57/B37 -> 0.71818388 | C58: =C57/C37 -> 0.71706331 | D58: =D57/D37 -> 0.71357974 | E58: =E57/E37 -> 0.72628474 | F58: =F57/F37 -> 0.72144623 | G58: =G57/G37 -> 0.73206001 | H58: =H57/H37 -> 0.74824866 | I58: =I57/I37 -> 0.7073938 | J58: 0.625 | K58: 0.615 | L58: 0.615 | N58: 0.712 | O58: 0.735
A59: Raw materials | B59: =B38*B$58 -> 2560.7891 | C59: =C38*C$58 -> 2985.2208 | D59: =D38*D$58 -> 2516.4318 | E59: =E38*E$58 -> 3756.7431 | F59: =F38*F$58 -> 3820.3625 | G59: =G38*G$58 -> 4030.9622 | H59: =H38*H$58 -> 4970.3091 | I59: =I38*I$58 -> 5668.5777 | J59: =J2*J66 -> 4461.1793 | K59: =K2*K66 -> 5077.7666 | L59: =L2*L66 -> 5816.7922 | N59: =N10*N66 -> 5238.3502 | O59: =O10*O66 -> 4994.2124
A60: Labour costs | B60: =B39*B$58 -> 5535.6955 | C60: =C39*C$58 -> 7362.2117 | D60: =D39*D$58 -> 8841.477 | E60: =E39*E$58 -> 10952.682 | F60: =F39*F$58 -> 13561.748 | G60: =G39*G$58 -> 16709.169 | H60: =H39*H$58 -> 19795.008 | I60: =I39*I$58 -> 21690.65 | J60: =J39*J58 -> 19181.25 | K60: =K39*K58 -> 23068.65 | L60: =L39*L58 -> 27405.556 | N60: =N39*N58 -> 23881.904 | O60: =O39*O58 -> 18949.156
A61: Depreciation expense | B61: =B53*B$58 -> 1344.9168 | C61: =C53*C$58 -> 1754.9617 | D61: =D53*D$58 -> 1063.6673 | E61: =E53*E$58 -> 1193.9509 | F61: =F53*F$58 -> 1322.4575 | G61: =G53*G$58 -> 1673.8656 | H61: =H53*H$58 -> 1893.9745 | I61: =I53*I$58 -> 1982.1828 | J61: =J53*J58 -> 1686.1604 | K61: =K53*K58 -> 1660.9902 | L61: =L53*L58 -> 1682.009 | N61: =N53*N58 -> 0 | O61: =O53*O58 -> 1615.2913
A62: Outside service expenses | B62: =B54*B$58 -> 4094.0484 | C62: =C54*C$58 -> 3999.5273 | D62: =D54*D$58 -> 4609.1897 | E62: =E54*E$58 -> 5158.0894 | F62: =F54*F$58 -> 6982.4336 | G62: =G54*G$58 -> 7684.8656 | H62: =H54*H$58 -> 10425.057 | I62: =I54*I$58 -> 13080.87 | J62: =J$2*J69 -> 9437.1101 | K62: =K$2*K69 -> 10880.928 | L62: =L$2*L69 -> 12628.562 | N62: =N$10*N69 -> 10145.159 | O62: =O$10*O69 -> 8361.6915
A63: Other cash expenses | B63: =B55*B$58 -> 955.20805 | C63: =C55*C$58 -> 902.98907 | D63: =D55*D$58 -> 985.97729 | E63: =E55*E$58 -> 963.83299 | F63: =F55*F$58 -> 1155.2472 | G63: =G55*G$58 -> 2199.4854 | H63: =H55*H$58 -> 2066.1016 | I63: =I55*I$58 -> 1795.1399 | J63: =J$10*J70 -> 2605.1821 | K63: =K$10*K70 -> 2980.0769 | L63: =L$10*L70 -> 3426.0706 | N63: =N$10*N70 -> 2188.1716 | O63: =O$10*O70 -> 2229.7844
A65: COGS as % revenue | B65: =B57/B$3 -> 0.62423309 | C65: =C57/C$3 -> 0.61352004 | D65: =D57/D$3 -> 0.60397255 | E65: =E57/E$3 -> 0.61769459 | F65: =F57/F$3 -> 0.60991904 | G65: =G57/G$3 -> 0.61382812 | H65: =H57/H$3 -> 0.62293085 | I65: =I57/I$3 -> 0.62980879 | J65: =J57/J10 -> 0.47337924 | K65: =K57/K10 -> 0.48356389 | L65: =L57/L10 -> 0.4908383 | N65: =N57/N10 -> 0.62516501 | O65: =O57/O10 -> 0.64849563
A66: Raw materials | B66: =B59/B$3 -> 0.11031447 | C66: =C59/C$3 -> 0.10770376 | D66: =D59/D$3 -> 0.084357961 | E66: =E59/E$3 -> 0.10535702 | F66: =F59/F$3 -> 0.086807624 | G66: =G59/G$3 -> 0.07660819 | H66: =H59/H$3 -> 0.079083608 | I66: =I59/I$3 -> 0.080740126 | J66: 0.078 | K66: 0.077 | L66: 0.076 | N66: 0.079 | O66: =AVERAGE(E66:G66) -> 0.089590946
A67: Labour costs | B67: =B60/B$3 -> 0.23846842 | C67: =C60/C$3 -> 0.26562118 | D67: =D60/D$3 -> 0.2963915 | E67: =E60/E$3 -> 0.30716553 | F67: =F60/F$3 -> 0.30815482 | G67: =G60/G$3 -> 0.31755673 | H67: =H60/H$3 -> 0.31496244 | I67: =I60/I$3 -> 0.30894977 | J67: 0.308 | K67: 0.308 | L67: 0.307 | N67: 0.311 | O67: 0.318
A68: Depreciation expense | B68: =B61/B$3 -> 0.057936748 | C68: =C61/C$3 -> 0.063317251 | D68: =D61/D$3 -> 0.035657158 | E68: =E61/E$3 -> 0.033484087 | F68: =F61/F$3 -> 0.030049345 | G68: =G61/G$3 -> 0.031811714 | H68: =H61/H$3 -> 0.030135417 | I68: =I61/I$3 -> 0.02823313 | J68: 0.03 | K68: 0.03 | L68: 0.03 | N68: 0.03 | O68: =Assumptions!AG32 -> 0.035
A69: Outside service expenses | B69: =B62/B$3 -> 0.1763647 | C69: =C62/C$3 -> 0.14429892 | D69: =D62/D$3 -> 0.15451317 | E69: =E62/E$3 -> 0.14465747 | F69: =F62/F$3 -> 0.15865732 | G69: =G62/G$3 -> 0.1460504 | H69: =H62/H$3 -> 0.16587522 | I69: =I62/I$3 -> 0.18631677 | J69: 0.165 | K69: =J69 -> 0.165 | L69: =K69 -> 0.165 | N69: 0.153 | O69: =Assumptions!AG33 -> 0.15
A70: Other cash expenses | B70: =B63/B$3 -> 0.041148751 | C70: =C63/C$3 -> 0.032578936 | D70: =D63/D$3 -> 0.033052767 | E70: =E63/E$3 -> 0.027030482 | F70: =F63/F$3 -> 0.026249935 | G70: =G63/G$3 -> 0.041801086 | H70: =H63/H$3 -> 0.032874167 | I70: =I63/I$3 -> 0.025568993 | J70: 0.033 | K70: =J70 -> 0.033 | L70: =K70 -> 0.033 | N70: =Assumptions!P34 -> 0.033 | O70: 0.04
A72: COGS growth | C72: =C57/B57-1 -> 0.17350852 | D72: =D57/C57-1 -> 0.059502373 | E72: =E57/D57-1 -> 0.22249056 | F72: =F57/E57-1 -> 0.21870082 | G72: =G57/F57-1 -> 0.20326532 | H72: =H57/G57-1 -> 0.21215025 | I72: =I57/H57-1 -> 0.12942303 | J72: =J57/I57-1 -> -0.15483803 | ... L72: =L57/K57-1 -> 0.16695313 | N72: =N57/H57-1 -> 0.058827803 | O72: =O57/G57-1 -> 0.11925653 | AI72: =AI57 -> 4691.8007 | AJ72: =AJ57 -> 5201.5261 | AK72: =AK57 -> 5474.2432 | AL72: =AL57 -> 6609.6875 | AM72: =AM57 -> 5776.9326 | AN72: =AN57 -> 6253.3717 | AO72: =AO57 -> 6789.0733 | AP72: =AP57 -> 7801.1525
A73: Raw materials | C73: =C59/B59-1 -> 0.16574255 | D73: =D59/C59-1 -> -0.15703662 | E73: =E59/D59-1 -> 0.49288494 | F73: =F59/E59-1 -> 0.016934735 | G73: =G59/F59-1 -> 0.055125559 | H73: =H59/G59-1 -> 0.23303292 | I73: =I59/H59-1 -> 0.14048798 | J73: =J59/I59-1 -> -0.21299848 | ... L73: =L59/K59-1 -> 0.14554148 | N73: =N59/H59-1 -> 0.053928459 | O73: =O59/G59-1 -> 0.23896285
A74: Labour costs | C74: =C60/B60-1 -> 0.32995242 | D74: =D60/C60-1 -> 0.20092677 | E74: =E60/D60-1 -> 0.23878419 | F74: =F60/E60-1 -> 0.23821254 | G74: =G60/F60-1 -> 0.23208074 | H74: =H60/G60-1 -> 0.18467941 | I74: =I60/H60-1 -> 0.095763625 | J74: =J60/I60-1 -> -0.11569039 | ... L74: =L60/K60-1 -> 0.188 | N74: =N60/H60-1 -> 0.20646094 | O74: =O60/G60-1 -> 0.13405741
A75: Depreciation expense | C75: =C61/B61-1 -> 0.30488495 | D75: =D61/C61-1 -> -0.39390855 | E75: =E61/D61-1 -> 0.12248528 | F75: =F61/E61-1 -> 0.10763138 | G75: =G61/F61-1 -> 0.26572357 | H75: =H61/G61-1 -> 0.13149736 | I75: =I61/H61-1 -> 0.046573137 | J75: =J61/I61-1 -> -0.14934161 | ... L75: =L61/K61-1 -> 0.01265438 | N75: =N61/H61-1 -> -1 | O75: =O61/G61-1 -> -0.034993402
A76: Outside service expenses | C76: =C62/B62-1 -> -0.023087436 | D76: =D62/C62-1 -> 0.1524336 | E76: =E62/D62-1 -> 0.11908812 | F76: =F62/E62-1 -> 0.35368604 | G76: =G62/F62-1 -> 0.10059987 | H76: =H62/G62-1 -> 0.35656982 | I76: =I62/H62-1 -> 0.25475285 | J76: =J62/I62-1 -> -0.27855637 | ... L76: =L62/K62-1 -> 0.1606144 | N76: =N62/H62-1 -> -0.026848541 | O76: =O62/G62-1 -> 0.088072577
A77: Other cash expenses | C77: =C63/B63-1 -> -0.054667653 | D77: =D63/C63-1 -> 0.091903906 | E77: =E63/D63-1 -> -0.022459243 | F77: =F63/E63-1 -> 0.19859689 | G77: =G63/F63-1 -> 0.90390883 | H77: =H63/G63-1 -> -0.060643177 | I77: =I63/H63-1 -> -0.13114634 | J77: =J63/I63-1 -> 0.45124178 | ... L77: =L63/K63-1 -> 0.14965845 | N77: =N63/H63-1 -> 0.059082273 | O77: =O63/G63-1 -> 0.013775499
A79: Gross profit | B79: =B7 -> 8722.879 | C79: =C7 -> 10712.05 | D79: =D7 -> 11813.657 | E79: =E7 -> 13631.964 | F79: =F7 -> 17167.279 | G79: =G7 -> 20319.553 | H79: =H7 -> 23698.34 | I79: =I7 -> 25990.27 | J79: =J10-J57 -> 41574.03 | K79: =K10-K57 -> 46636.95 | L79: =L10-L57 -> 52861.332 | N79: =N10-N57 -> 24854.645 | O79: =O10-O57 -> 19594.474
A80: Gross profit margin | B80: =B8 -> 0.37576691 | C80: =C8 -> 0.38647996 | D80: =D8 -> 0.39602745 | E80: =E8 -> 0.38230541 | F80: =F8 -> 0.39008096 | G80: =G8 -> 0.38617188 | H80: =H8 -> 0.37706915 | I80: =I8 -> 0.51358253 | ... L80: =L8 -> 0.33418917 | N80: =N8 -> 0.37483499 | O80: =O8 -> 0.35150437
A82: SG&A & other costs | B82: =B37-B57 -> 5686.1495 | C82: =C37-C57 -> 6709.7465 | D82: =D37-D57 -> 7231.6517 | E82: =E37-E57 -> 8300.684 | F82: =F37-F57 -> 10363.918 | G82: =G37-G57 -> 11821.461 | H82: =H37-H57 -> 13172.33 | I82: =I37-I57 -> 18290.083
A83: Selling expenses | B83: =PL!I17 -> 2047.8336 | C83: =PL!J17 -> 2345.9576 | D83: =PL!K17 -> 2713.5613 | E83: =PL!L17 -> 3604.6108 | F83: =PL!M17 -> 4526.4407 | G83: =PL!N17 -> 5242.5519 | H83: =PL!O17 -> 6115.96 | I83: =PL!P17 -> 7580.84
A84: Administration expenses | B84: =PL!I20 -> 3553.2881 | C84: =PL!J20 -> 4219.2548 | D84: =PL!K20 -> 4495.3665 | E84: =PL!L20 -> 4612.3259 | F84: =PL!M20 -> 5846.2807 | G84: =PL!N20 -> 6625.3736 | H84: =PL!O20 -> 7074.04 | I84: =PL!P20 -> 7330.79
A88: Depreciation breakdown
A89: Total IT
A90: Global IT | B90: 199 | C90: 252 | D90: 278 | E90: 346 | F90: 354.7 | G90: 448.139 | J90: =J12*J99 -> 0 | K90: =K12*K99 -> 0 | L90: =L12*L99 -> 0 | N90: =N12*N99 -> 0 | O90: =O12*O99 -> 448.139
A91: Domestic IT | B91: 25 | C91: 40 | D91: 29 | E91: 34 | F91: 63.5 | G91: 134.623 | J91: =J13*J100 -> 0 | K91: =K13*K100 -> 0 | L91: =L13*L100 -> 0 | N91: =N13*N100 -> 0 | O91: =O13*O100 -> 144.04661
A92: Total communication
A93: Communication | B93: 876 | C93: 984 | D93: 1079 | E93: 1128 | F93: 1169.2 | G93: 1329.413 | J93: =J15*J102 -> 0 | K93: =K15*K102 -> 0 | L93: =L15*L102 -> 0 | N93: =N15*N102 -> 0 | O93: =O15*O102 -> 1488.0846
A94: Digital content | B94: 5 | C94: 4 | D94: 3 | E94: 3 | F94: 4.5 | G94: 3.902 | J94: =J16*J103 -> 0 | K94: =K16*K103 -> 0 | L94: =L16*L103 -> 0 | N94: =N16*N103 -> 0 | O94: =O16*O103 -> 4.2922
A95: Investment, education & others | B95: 40 | C95: 63 | D95: 102 | E95: =143.2-9.4 -> 133.8 | F95: =276.4-35.1 -> 241.3 | G95: 396.525 | J95: =J17*J104 -> 0 | K95: =K17*K104 -> 0 | L95: =L17*L104 -> 0 | N95: =N17*N104 -> 0 | O95: =O17*O104 -> 452.0385
A97: Depreciation breakdown (% revenue)
A98: Total IT
A99: Global IT | B99: =B90/B12 -> 0.023568504 | C99: =C90/C12 -> 0.023229954 | D99: =D90/D12 -> 0.023166165 | E99: =E90/E12 -> 0.023795113 | F99: =F90/F12 -> 0.018751823 | G99: =G90/G12 -> 0.018451046 | H99: =H90/H12 -> 0 | I99: =I90/I12 -> 0 | J99: =I99 -> 0 | K99: =J99 -> 0 | L99: =K99 -> 0 | N99: =H99 -> 0 | O99: =G99 -> 0.018451046
A100: Domestic IT | B100: =B91/B13 -> 0.0050422521 | C100: =C91/C13 -> 0.0081047819 | D100: =D91/D13 -> 0.0060357918 | E100: =E91/E13 -> 0.0053700239 | F100: =F91/F13 -> 0.0092735821 | G100: =G91/G13 -> 0.018799469 | H100: =H91/H13 -> 0 | I100: =I91/I13 -> 0 | J100: =I100 -> 0 | K100: =J100 -> 0 | L100: =K100 -> 0 | N100: =H100 -> 0 | O100: =G100 -> 0.018799469
A101: Total communication
A102: Communication | B102: =B93/B15 -> 0.10562919 | C102: =C93/C15 -> 0.10051575 | D102: =D93/D15 -> 0.099291405 | E102: =E93/E15 -> 0.093387704 | F102: =F93/F15 -> 0.083788273 | G102: =G93/G15 -> 0.087542012 | H102: =H93/H15 -> 0 | I102: =I93/I15 -> 0 | J102: =I102 -> 0 | K102: =J102 -> 0 | L102: =K102 -> 0 | N102: =H102 -> 0 | O102: =G102 -> 0.087542012
A103: Digital content | B103: =B94/B16 -> 0.0092964278 | C103: =C94/C16 -> 0.0065690506 | D103: =D94/D16 -> 0.005007085 | E103: =E94/E16 -> 0.0049363377 | F103: =F94/F16 -> 0.0058032392 | G103: =G94/G16 -> 0.0062935484 | H103: =H94/H16 -> 0 | I103: =I94/I16 -> 0 | J103: =I103 -> 0 | K103: =J103 -> 0 | L103: =K103 -> 0 | N103: =H103 -> 0 | O103: =G103 -> 0.0062935484
A104: Investment, education & others | B104: =B95/B17 -> 0.040776388 | C104: =C95/C17 -> 0.041039347 | D104: =D95/D17 -> 0.065413358 | E104: =E95/E17 -> 0.063756713 | F104: =F95/F17 -> 0.068610065 | G104: =G95/G17 -> 0.073937162 | H104: =H95/H17 -> 0 | I104: =I95/I17 -> 0 | J104: =I104 -> 0 | K104: =J104 -> 0 | L104: =K104 -> 0 | N104: =H104 -> 0 | O104: =G104 -> 0.073937162
A106: Depreciation growth breakdown
A107: Total IT
A108: Global IT | C108: =C90/B90-1 -> 0.26633166 | D108: =D90/C90-1 -> 0.1031746 | E108: =E90/D90-1 -> 0.24460432 | F108: =F90/E90-1 -> 0.025144509 | G108: =G90/F90-1 -> 0.26343107 | H108: =H90/G90-1 -> -1 | I108: =I90/H90-1 -> #DIV/0!
A109: Domestic IT | C109: =C91/B91-1 -> 0.6 | D109: =D91/C91-1 -> -0.275 | E109: =E91/D91-1 -> 0.17241379 | F109: =F91/E91-1 -> 0.86764706 | G109: =G91/F91-1 -> 1.1200472 | H109: =H91/G91-1 -> -1 | I109: =I91/H91-1 -> #DIV/0!
A110: Total communication
A111: Communication | C111: =C93/B93-1 -> 0.12328767 | D111: =D93/C93-1 -> 0.096544715 | E111: =E93/D93-1 -> 0.045412419 | F111: =F93/E93-1 -> 0.036524823 | G111: =G93/F93-1 -> 0.13702788 | H111: =H93/G93-1 -> -1 | I111: =I93/H93-1 -> #DIV/0!
A112: Digital content | C112: =C94/B94-1 -> -0.2 | D112: =D94/C94-1 -> -0.25 | E112: =E94/D94-1 -> 0 | F112: =F94/E94-1 -> 0.5 | G112: =G94/F94-1 -> -0.13288889 | H112: =H94/G94-1 -> -1 | I112: =I94/H94-1 -> #DIV/0!
...

Sheet Valuation
B3: DISCOUNTED FCFF MODEL | J3: 2026 | R3: 2023
B5: Assumption | F5: Present Value | N5: Present Value
B6: Net sales growth rate in long-term | F6: Present value of first stage (2025-2028 FCFF) | J6: =D36 -> 29669.934 | N6: Present value of next 4-year cash flow | R6: =P36 -> #REF!
B7: terminal g | C7: 0.025 | F7: WACC | J7: =C27 -> 0.099249688 | N7: WACC | R7: =C27 -> 0.099249688
F8: Growth rate to perpeptuity | J8: =C7 -> 0.025 | N8: Growth rate to perpeptuity | R8: =C6 -> 0
F9: Terminal value (2028 onwards) | J9: =G36 -> 135886.66 | N9: Terminal value | R9: =S36 -> 116282.71
B10: WACC | F10: Terminal value/ Total company value | J10: =J9/(J9+J6) -> 0.82078676 | N10: Terminal value/ Total company value | R10: =R9/(R9+R6) -> #REF!
B12: Equity | C12: =BS!Q76 -> 42945.223 | F12: Intrinsic Value | N12: Intrinsic Value
B13: Debt | C13: =BS!Q50+BS!Q53 -> 21486.007 | F13: Total company's PV | J13: =J6+J9 -> 165556.59 | N13: Total company present value | R13: =R6+R9 -> #REF!
F14: - Debt | J14: =BS!O50+BS!O53 -> 14947.36 | N14: - Debt | R14: =BS!V50+BS!V53 -> 13146.554
B15: E/(D+E) | C15: =C12/($C$12+$C$13) -> 0.66652806 | F15: + Cash and cash equivalent | J15: =BS!O6+BS!O7 -> 31100.65 | N15: + Cash and cash equivalent | R15: =BS!V6+BS!V7 -> #REF!
B16: D/(D+E) | C16: =1-C15 -> 0.33347194 | F16: Net debt | J16: =J14-J15 -> -16153.29 | N16: Net debt | R16: =R14-R15 -> #REF!
F17: Present value of Equity YE | J17: =J13-J16 -> 181709.88 | N17: Present value of Equity | R17: =R13-R16 -> #REF!
B18: Cost of debt | C18: 0.115
B19: Tax rate | C19: =PL!W51 -> 0.15 | F19: Outstanding number of shares | J19: =PL!Q90 -> 1703507121 | N19: Outstanding number of shares | R19: =PL!J90 -> 613636772
B20: After tax cost of debt | C20: =C18*(1-C19) -> 0.09775 | AA20: ==((CF!$M$23*(1+Valuation!G$33))/(Valuation!$C36-Valuation!G$33))/((1+Valuation!$C36)^CF!$M$37)
F21: Present value per share | J21: =J17*10^9/$J$19 -> 106668.11 | N21: Present value per share | R21: =R17*10^9/R19 -> #REF!
B22: Risk free rate | C22: 0.043 | M22: CF!M23 | AA22: Free Cash Flow to Firm (FCFF) | AB22: 6046.6051
B23: Beta | C23: 1 | F23: Current stock price | J23: 72200 | M23: V!G33 | AA23: Terminal value | AB23: 0.04
B24: Expected market return | C24: =C22+5.7% -> 0.1 | F24: Premium | J24: =J21/J23-1 -> 0.47739761 | M24: V!C36 | AA24: WACC | AB24: 0.0882
B25: Cost of equity | C25: =C22+C23*(C24-C22) -> 0.1 | M25: CF!M37 | AA25: Terrminal value | AB25: 0.04
AA26: Discount number of year 2027 | AB26: 4.425
B27: WACC | C27: =C15*C25+C16*C20 -> 0.099249688
AB29: =((AB22*(1+AB23))/(AB24-AB25))/(1+AB24)^AB26 -> 89755.654
B30: Sensitivity Analysis | N30: Sensitivity Analysis
D32: Present Value | F32: Terminal Value | J32: Company Value | P32: Present Value | R32: Terminal Value | V32: Company Value
C33: WACC | D33: (3-year CF) | F33: =G33-1% -> 0.015 | G33: =C7 -> 0.025 | H33: =G33+1% -> 0.035 | J33: =F33 -> 0.015 | K33: =G33 -> 0.025 | L33: =H33 -> 0.035 | O33: WACC | P33: (4-year CF) | R33: =F33 -> 0.015 | S33: =G33 -> 0.025 | T33: =H33 -> 0.035 | V33: =R33 -> 0.015 | W33: =S33 -> 0.025 | X33: =T33 -> 0.035
C34: =C35-0.5% -> 0.089249688 | D34: =SUM(CF!Q44:U44) -> 0 | F34: =((CF!$M$23*(1+Valuation!F$33))/(Valuation!$C34-Valuation!F$33))/((1+Valuation!$C34)^CF!$M$37) -> 111009.69 | G34: =((CF!$M$23*(1+Valuation!G$33))/(Valuation!$C34-Valuation!G$33))/((1+Valuation!$C34)^CF!$M$37) -> 129551.47 | H34: =((CF!$M$23*(1+Valuation!H$33))/(Valuation!$C34-Valuation!H$33))/((1+Valuation!$C34)^CF!$M$37) -> 154928.96 | J34: =F34+$D34 -> 111009.69 | K34: =G34+$D34 -> 129551.47 | L34: =H34+$D34 -> 154928.96 | O34: =C34 -> 0.089249688 | P34: =SUM(CF!Q44:T44) -> 0 | R34: =((CF!$L$23*(1+Valuation!R$33))/(Valuation!$C34-Valuation!R$33))/((1+Valuation!$C34)^4) -> 119435.36 | S34: =((CF!$L$23*(1+Valuation!S$33))/(Valuation!$C34-Valuation!S$33))/((1+Valuation!$C34)^4) -> 139384.46 | T34: =((CF!$L$23*(1+Valuation!T$33))/(Valuation!$C34-Valuation!T$33))/((1+Valuation!$C34)^4) -> 166688.11 | V34: =R34+$P34 -> 119435.36 | W34: =S34+$P34 -> 139384.46 | X34: =T34+$P34 -> 166688.11
C35: =C36-0.5% -> 0.094249688 | D35: =SUM(CF!Q45:U45) -> 0 | F35: =((CF!$M$23*(1+Valuation!F$33))/(Valuation!$C35-Valuation!F$33))/((1+Valuation!$C35)^CF!$M$37) -> 103328.03 | G35: =((CF!$M$23*(1+Valuation!G$33))/(Valuation!$C35-Valuation!G$33))/((1+Valuation!$C35)^CF!$M$37) -> 119414.13 | H35: =((CF!$M$23*(1+Valuation!H$33))/(Valuation!$C35-Valuation!H$33))/((1+Valuation!$C35)^CF!$M$37) -> 140930.16 | J35: =F35+$D35 -> 103328.03 | K35: =G35+$D35 -> 119414.13 | L35: =H35+$D35 -> 140930.16 | O35: =C35 -> 0.094249688 | P35: =NPV($C35,CF!$Q$23:$T$23) -> #REF! | R35: =((CF!$L$23*(1+Valuation!R$33))/(Valuation!$C35-Valuation!R$33))/((1+Valuation!$C35)^4) -> 109868.72 | S35: =((CF!$L$23*(1+Valuation!S$33))/(Valuation!$C35-Valuation!S$33))/((1+Valuation!$C35)^4) -> 126973.07 | T35: =((CF!$L$23*(1+Valuation!T$33))/(Valuation!$C35-Valuation!T$33))/((1+Valuation!$C35)^4) -> 149851.07 | V35: =R35+$P35 -> #REF! | W35: =S35+$P35 -> #REF! | X35: =T35+$P35 -> #REF!
C36: =C27 -> 0.099249688 | D36: =SUM(CF!L$38:N$38) -> 29669.934 | E36: + | F36: =((CF!$M$23*(1+Valuation!F$33))/(Valuation!$C36-Valuation!F$33))/((1+Valuation!$C36)^CF!$M$37) -> 96565.171 | G36: =((CF!$N$23*(1+Valuation!G$33))/(Valuation!$C36-Valuation!G$33))/((1+Valuation!$C36)^CF!$N$37) -> 135886.66 | H36: =((CF!$M$23*(1+Valuation!H$33))/(Valuation!$C36-Valuation!H$33))/((1+Valuation!$C36)^CF!$M$37) -> 129119.58 | I36: = | J36: =F36+$D36 -> 126235.1 | K36: =G36+$D36 -> 165556.59 | L36: =H36+$D36 -> 158789.51 | O36: =C36 -> 0.099249688 | P36: =NPV($C36,CF!$Q$23:$T$23) -> #REF! | Q36: + | R36: =((CF!$L$23*(1+Valuation!R$33))/(Valuation!$C36-Valuation!R$33))/((1+Valuation!$C36)^4) -> 101480.74 | S36: =((CF!$L$23*(1+Valuation!S$33))/(Valuation!$C36-Valuation!S$33))/((1+Valuation!$C36)^4) -> 116282.71 | T36: =((CF!$L$23*(1+Valuation!T$33))/(Valuation!$C36-Valuation!T$33))/((1+Valuation!$C36)^4) -> 135692.31 | U36: = | V36: =R36+$P36 -> #REF! | W36: =S36+$P36 -> #REF! | X36: =T36+$P36 -> #REF!
C37: =C36+0.5% -> 0.10424969 | D37: =SUM(CF!Q47:U47) -> 0 | F37: =((CF!$M$23*(1+Valuation!F$33))/(Valuation!$C37-Valuation!F$33))/((1+Valuation!$C37)^CF!$M$37) -> 90566.597 | G37: =((CF!$M$23*(1+Valuation!G$33))/(Valuation!$C37-Valuation!G$33))/((1+Valuation!$C37)^CF!$M$37) -> 102999.48 | H37: =((CF!$M$23*(1+Valuation!H$33))/(Valuation!$C37-Valuation!H$33))/((1+Valuation!$C37)^CF!$M$37) -> 119023.1 | J37: =F37+$D37 -> 90566.597 | K37: =G37+$D37 -> 102999.48 | L37: =H37+$D37 -> 119023.1 | O37: =C37 -> 0.10424969 | P37: =NPV($C37,CF!$Q$23:$T$23) -> #REF! | R37: =((CF!$L$23*(1+Valuation!R$33))/(Valuation!$C37-Valuation!R$33))/((1+Valuation!$C37)^4) -> 94072.242 | S37: =((CF!$L$23*(1+Valuation!S$33))/(Valuation!$C37-Valuation!S$33))/((1+Valuation!$C37)^4) -> 106986.37 | T37: =((CF!$L$23*(1+Valuation!T$33))/(Valuation!$C37-Valuation!T$33))/((1+Valuation!$C37)^4) -> 123630.23 | V37: =R37+$P37 -> #REF! | W37: =S37+$P37 -> #REF! | X37: =T37+$P37 -> #REF!
C38: =C37+0.5% -> 0.10924969 | D38: =SUM(CF!Q48:U48) -> 0 | F38: =((CF!$M$23*(1+Valuation!F$33))/(Valuation!$C38-Valuation!F$33))/((1+Valuation!$C38)^CF!$M$37) -> 85210.575 | G38: =((CF!$M$23*(1+Valuation!G$33))/(Valuation!$C38-Valuation!G$33))/((1+Valuation!$C38)^CF!$M$37) -> 96263.786 | H38: =((CF!$M$23*(1+Valuation!H$33))/(Valuation!$C38-Valuation!H$33))/((1+Valuation!$C38)^CF!$M$37) -> 110294.31 | J38: =F38+$D38 -> 85210.575 | K38: =G38+$D38 -> 96263.786 | L38: =H38+$D38 -> 110294.31 | O38: =C38 -> 0.10924969 | P38: =NPV($C38,CF!$Q$23:$T$23) -> #REF! | R38: =((CF!$L$23*(1+Valuation!R$33))/(Valuation!$C38-Valuation!R$33))/((1+Valuation!$C38)^4) -> 87486.322 | S38: =((CF!$L$23*(1+Valuation!S$33))/(Valuation!$C38-Valuation!S$33))/((1+Valuation!$C38)^4) -> 98834.735 | T38: =((CF!$L$23*(1+Valuation!T$33))/(Valuation!$C38-Valuation!T$33))/((1+Valuation!$C38)^4) -> 113239.97 | V38: =R38+$P38 -> #REF! | W38: =S38+$P38 -> #REF! | X38: =T38+$P38 -> #REF!
C39: =C38+0.5% -> 0.11424969 | D39: =SUM(CF!Q49:U49) -> 0 | F39: =((CF!$M$23*(1+Valuation!F$33))/(Valuation!$C39-Valuation!F$33))/((1+Valuation!$C39)^CF!$M$37) -> 80399.902 | G39: =((CF!$M$23*(1+Valuation!G$33))/(Valuation!$C39-Valuation!G$33))/((1+Valuation!$C39)^CF!$M$37) -> 90289.196 | H39: =((CF!$M$23*(1+Valuation!H$33))/(Valuation!$C39-Valuation!H$33))/((1+Valuation!$C39)^CF!$M$37) -> 102674.22 | J39: =F39+$D39 -> 80399.902 | K39: =G39+$D39 -> 90289.196 | L39: =H39+$D39 -> 102674.22 | O39: =C39 -> 0.11424969 | P39: =NPV($C39,CF!$Q$23:$T$23) -> #REF! | R39: =((CF!$L$23*(1+Valuation!R$33))/(Valuation!$C39-Valuation!R$33))/((1+Valuation!$C39)^4) -> 81597.736 | S39: =((CF!$L$23*(1+Valuation!S$33))/(Valuation!$C39-Valuation!S$33))/((1+Valuation!$C39)^4) -> 91634.365 | T39: =((CF!$L$23*(1+Valuation!T$33))/(Valuation!$C39-Valuation!T$33))/((1+Valuation!$C39)^4) -> 104203.91 | V39: =R39+$P39 -> #REF! | W39: =S39+$P39 -> #REF! | X39: =T39+$P39 -> #REF!
D41: Equity Value (EV-Net Debt) | H41: Value per share | P41: Equity Value | T41: Value per share
C42: WACC | D42: =F33 -> 0.015 | E42: =G33 -> 0.025 | F42: =H33 -> 0.035 | H42: =J33 -> 0.015 | I42: =K33 -> 0.025 | J42: =L33 -> 0.035 | O42: WACC | P42: =R33 -> 0.015 | Q42: =S33 -> 0.025 | R42: =T33 -> 0.035 | T42: =V33 -> 0.015 | U42: =W33 -> 0.025 | V42: =X33 -> 0.035
C43: =C34 -> 0.089249688 | D43: =J34-$J$16 -> 127162.98 | E43: =K34-$J$16 -> 145704.76 | F43: =L34-$J$16 -> 171082.25 | H43: =D43*10^9/$J$19 -> 74647.755 | I43: =E43*10^9/$J$19 -> 85532.226 | J43: =F43*10^9/$J$19 -> 100429.43 | O43: =O34 -> 0.089249688 | P43: =V34-$R$16 -> #REF! | Q43: =W34-$R$16 -> #REF! | R43: =X34-$R$16 -> #REF! | T43: =P43*1000000/$J$19 -> #REF! | U43: =Q43*1000000/$J$19 -> #REF! | V43: =R43*1000000/$J$19 -> #REF!
C44: =C35 -> 0.094249688 | D44: =J35-$J$16 -> 119481.32 | E44: =K35-$J$16 -> 135567.42 | F44: =L35-$J$16 -> 157083.45 | H44: =D44*10^9/$J$19 -> 70138.431 | I44: =E44*10^9/$J$19 -> 79581.361 | J44: =F44*10^9/$J$19 -> 92211.794 | O44: =O35 -> 0.094249688 | P44: =V35-$R$16 -> #REF! | Q44: =W35-$R$16 -> #REF! | R44: =X35-$R$16 -> #REF! | T44: =P44*1000000/$J$19 -> #REF! | U44: =Q44*1000000/$J$19 -> #REF! | V44: =R44*1000000/$J$19 -> #REF!
C45: =C36 -> 0.099249688 | D45: =J36-$J$16 -> 142388.39 | E45: =K36-$J$16 -> 181709.88 | F45: =L36-$J$16 -> 174942.8 | G45: = | H45: =D45*10^9/$J$19 -> 83585.441 | I45: =E45*10^9/$J$19 -> 106668.11 | J45: =F45*10^9/$J$19 -> 102695.67 | O45: =O36 -> 0.099249688 | P45: =V36-$R$16 -> #REF! | Q45: =W36-$R$16 -> #REF! | R45: =X36-$R$16 -> #REF! | S45: = | T45: =P45*1000000/$J$19 -> #REF! | U45: =Q45*1000000/$J$19 -> #REF! | V45: =R45*1000000/$J$19 -> #REF!
C46: =C37 -> 0.10424969 | D46: =J37-$J$16 -> 106719.89 | E46: =K37-$J$16 -> 119152.77 | F46: =L37-$J$16 -> 135176.39 | H46: =D46*10^9/$J$19 -> 62647.162 | I46: =E46*10^9/$J$19 -> 69945.564 | J46: =F46*10^9/$J$19 -> 79351.818 | O46: =O37 -> 0.10424969 | P46: =V37-$R$16 -> #REF! | Q46: =W37-$R$16 -> #REF! | R46: =X37-$R$16 -> #REF! | T46: =P46*1000000/$J$19 -> #REF! | U46: =Q46*1000000/$J$19 -> #REF! | V46: =R46*1000000/$J$19 -> #REF!
C47: =C38 -> 0.10924969 | D47: =J38-$J$16 -> 101363.86 | E47: =K38-$J$16 -> 112417.08 | F47: =L38-$J$16 -> 126447.6 | H47: =D47*10^9/$J$19 -> 59503.047 | I47: =E47*10^9/$J$19 -> 65991.55 | J47: =F47*10^9/$J$19 -> 74227.805 | O47: =O38 -> 0.10924969 | P47: =V38-$R$16 -> #REF! | Q47: =W38-$R$16 -> #REF! | R47: =X38-$R$16 -> #REF! | T47: =P47*1000000/$J$19 -> #REF! | U47: =Q47*1000000/$J$19 -> #REF! | V47: =R47*1000000/$J$19 -> #REF!
C48: =C39 -> 0.11424969 | D48: =J39-$J$16 -> 96553.192 | E48: =K39-$J$16 -> 106442.49 | F48: =L39-$J$16 -> 118827.51 | H48: =D48*10^9/$J$19 -> 56679.066 | I48: =E48*10^9/$J$19 -> 62484.321 | J48: =F48*10^9/$J$19 -> 69754.631 | O48: =O39 -> 0.11424969 | P48: =V39-$R$16 -> #REF! | Q48: =W39-$R$16 -> #REF! | R48: =X39-$R$16 -> #REF! | T48: =P48*1000000/$J$19 -> #REF! | U48: =Q48*1000000/$J$19 -> #REF! | V48: =R48*1000000/$J$19 -> #REF!
B50: EVPS
B51: DISCOUNTED FCFE MODEL
B53: Assumption | E53: =F5 -> Present Value | J53: =F12 -> Intrinsic Value
B54: =B6 -> Net sales growth rate in long-term | C54: =C6 -> 0 | E54: =F6 -> Present value of first stage (2025-2028 FCFF) | H54: =D67 -> #REF! | J54: =F17 -> Present value of Equity YE | L54: =H54+H57 -> #REF!
B55: =B7 -> terminal g | C55: =C7 -> 0.025 | E55: =B56 -> Cost of equity | H55: =C56 -> 0.1 | J55: Cash | L55: =J15 -> 31100.65
B56: =B25 -> Cost of equity | C56: =C25 -> 0.1 | E56: =F8 -> Growth rate to perpeptuity | H56: =C55 -> 0.025 | J56: =F19 -> Outstanding number of shares | L56: =J19 -> 1703507121
E57: =F9 -> Terminal value (2028 onwards) | H57: =G67 -> #REF!
E58: =F10 -> Terminal value/ Total company value | H58: =H57/(H57+H54) -> #REF! | J58: =F21 -> Present value per share | L58: =(L54+L55)*1000000/L56 -> #REF!
B61: =B30 -> Sensitivity Analysis
D63: =D32 -> Present Value | F63: =F32 -> Terminal Value | J63: =J32 -> Company Value
C64: Cost of equity | D64: =D33 -> (3-year CF) | F64: =G64-1% -> 0.015 | G64: =C55 -> 0.025 | H64: =G64+1% -> 0.035 | J64: =F64 -> 0.015 | K64: =G64 -> 0.025 | L64: =H64 -> 0.035
C65: =C66-0.5% -> 0.09 | D65: =NPV($C65,CF!#REF!)+CF!#REF! -> #REF! | F65: =((CF!#REF!*(1+Valuation!F$64))/(Valuation!$C65-F$64))/((1+Valuation!$C65)^3) -> #REF! | G65: =((CF!#REF!*(1+Valuation!G$64))/(Valuation!$C65-G$64))/((1+Valuation!$C65)^3) -> #REF! | H65: =((CF!#REF!*(1+Valuation!H$64))/(Valuation!$C65-H$64))/((1+Valuation!$C65)^3) -> #REF! | J65: =$D65+F65 -> #REF! | K65: =$D65+G65 -> #REF! | L65: =$D65+H65 -> #REF!
C66: =C67-0.5% -> 0.095 | D66: =NPV($C66,CF!#REF!)+CF!#REF! -> #REF! | F66: =((CF!#REF!*(1+Valuation!F$64))/(Valuation!$C66-F$64))/((1+Valuation!$C66)^3) -> #REF! | G66: =((CF!#REF!*(1+Valuation!G$64))/(Valuation!$C66-G$64))/((1+Valuation!$C66)^3) -> #REF! | H66: =((CF!#REF!*(1+Valuation!H$64))/(Valuation!$C66-H$64))/((1+Valuation!$C66)^3) -> #REF! | J66: =$D66+F66 -> #REF! | K66: =$D66+G66 -> #REF! | L66: =$D66+H66 -> #REF!
C67: =C56 -> 0.1 | D67: =NPV($C67,CF!#REF!)+CF!#REF! -> #REF! | E67: + | F67: =((CF!#REF!*(1+Valuation!F$64))/(Valuation!$C67-F$64))/((1+Valuation!$C67)^3) -> #REF! | G67: =((CF!#REF!*(1+Valuation!G$64))/(Valuation!$C67-G$64))/((1+Valuation!$C67)^3) -> #REF! | H67: =((CF!#REF!*(1+Valuation!H$64))/(Valuation!$C67-H$64))/((1+Valuation!$C67)^3) -> #REF! | I67: = | J67: =$D67+F67 -> #REF! | K67: =$D67+G67 -> #REF! | L67: =$D67+H67 -> #REF!
C68: =C67+0.5% -> 0.105 | D68: =NPV($C68,CF!#REF!)+CF!#REF! -> #REF! | F68: =((CF!#REF!*(1+Valuation!F$64))/(Valuation!$C68-F$64))/((1+Valuation!$C68)^3) -> #REF! | G68: =((CF!#REF!*(1+Valuation!G$64))/(Valuation!$C68-G$64))/((1+Valuation!$C68)^3) -> #REF! | H68: =((CF!#REF!*(1+Valuation!H$64))/(Valuation!$C68-H$64))/((1+Valuation!$C68)^3) -> #REF! | J68: =$D68+F68 -> #REF! | K68: =$D68+G68 -> #REF! | L68: =$D68+H68 -> #REF!
C69: =C68+0.5% -> 0.11 | D69: =NPV($C69,CF!#REF!)+CF!#REF! -> #REF! | F69: =((CF!#REF!*(1+Valuation!F$64))/(Valuation!$C69-F$64))/((1+Valuation!$C69)^3) -> #REF! | G69: =((CF!#REF!*(1+Valuation!G$64))/(Valuation!$C69-G$64))/((1+Valuation!$C69)^3) -> #REF! | H69: =((CF!#REF!*(1+Valuation!H$64))/(Valuation!$C69-H$64))/((1+Valuation!$C69)^3) -> #REF! | J69: =$D69+F69 -> #REF! | K69: =$D69+G69 -> #REF! | L69: =$D69+H69 -> #REF!
C70: =C69+0.5% -> 0.115 | D70: =NPV($C70,CF!#REF!)+CF!#REF! -> #REF! | F70: =((CF!#REF!*(1+Valuation!F$64))/(Valuation!$C70-F$64))/((1+Valuation!$C70)^3) -> #REF! | G70: =((CF!#REF!*(1+Valuation!G$64))/(Valuation!$C70-G$64))/((1+Valuation!$C70)^3) -> #REF! | H70: =((CF!#REF!*(1+Valuation!H$64))/(Valuation!$C70-H$64))/((1+Valuation!$C70)^3) -> #REF! | J70: =$D70+F70 -> #REF! | K70: =$D70+G70 -> #REF! | L70: =$D70+H70 -> #REF!
D72: =H41 -> Value per share
C73: =C64 -> Cost of equity | D73: =F64 -> 0.015 | E73: =G64 -> 0.025 | F73: =H64 -> 0.035
C74: =C65 -> 0.09 | D74: =J65*1000000/$L$56 -> #REF! | E74: =K65*1000000/$L$56 -> #REF! | F74: =L65*1000000/$L$56 -> #REF!
C75: =C66 -> 0.095 | D75: =J66*1000000/$L$56 -> #REF! | E75: =K66*1000000/$L$56 -> #REF! | F75: =L66*1000000/$L$56 -> #REF!
C76: =C67 -> 0.1 | D76: =J67*1000000/$L$56 -> #REF! | E76: =K67*1000000/$L$56 -> #REF! | F76: =L67*1000000/$L$56 -> #REF!
C77: =C68 -> 0.105 | D77: =J68*1000000/$L$56 -> #REF! | E77: =K68*1000000/$L$56 -> #REF! | F77: =L68*1000000/$L$56 -> #REF!
C78: =C69 -> 0.11 | D78: =J69*1000000/$L$56 -> #REF! | E78: =K69*1000000/$L$56 -> #REF! | F78: =L69*1000000/$L$56 -> #REF!
C79: =C70 -> 0.115 | D79: =J70*1000000/$L$56 -> #REF! | E79: =K70*1000000/$L$56 -> #REF! | F79: =L70*1000000/$L$56 -> #REF!
F81: Terminal growth rate
C82: =I45 -> 106668.11 | D82: =E82-0.1% -> 0.027 | E82: =F82-0.1% -> 0.028 | F82: =G82-0.1% -> 0.029 | G82: 0.03 | H82: =G82+0.1% -> 0.031 | I82: =H82+0.1% -> 0.032 | J82: =I82+0.1% -> 0.033
C83: =C84-0.2% -> 0.093249688 | D83: 117673.25 | E83: 119154.17 | F83: 120681.19 | G83: 122256.49 | H83: 123882.41 | I83: 125561.42 | J83: 127296.16
C84: =C85-0.2% -> 0.095249688 | D84: 114623.07 | E84: 116014.21 | F84: 117447.34 | G84: 118924.4 | H84: 120447.44 | I84: 122018.64 | J84: 123640.32
C85: =C86-0.2% -> 0.097249688 | D85: 111748.94 | E85: 113058.02 | F85: 114405.46 | G85: 115792.98 | H85: 117222.38 | I85: 118695.6 | J85: 120214.68
B86: WACC | C86: =C27 -> 0.099249688 | D86: 109036.2 | E86: 110270.11 | F86: 111539.14 | G86: 112844.82 | H86: 114188.77 | I86: 115572.68 | J86: 116998.37
C87: =C86+0.2% -> 0.10124969 | D87: 106471.81 | E87: 107636.67 | F87: 108833.77 | G87: 110064.48 | H87: 111330.22 | I87: 112632.52 | J87: 113972.98
C88: =C87+0.2% -> 0.10324969 | D88: 104044.08 | E88: 105145.37 | F88: 106276.34 | G88: 107438.18 | H88: 108632.18 | I88: 109859.7 | J88: 111122.17
C89: =C88+0.2% -> 0.10524969 | D89: 101742.5 | E89: 102785.16 | F89: 103855.18 | G89: 104953.63 | H89: 106081.67 | I89: 107240.51 | J89: 108431.44
B91: Equity value
F92: Terminal growth rate
B97: WACC
B102: Equity value per share
F103: Terminal growth rate
D104: =E104-0.25% -> 0.0325 | E104: =F104-0.25% -> 0.035 | F104: =G104-0.25% -> 0.0375 | G104: 0.04 | H104: =G104+0.25% -> 0.0425 | I104: =H104+0.25% -> 0.045 | J104: =I104+0.25% -> 0.0475
C105: 0.084933992
C106: 0.086933992
C107: 0.088933992
B108: WACC | C108: 0.090933992
C109: 0.092933992
C110: 0.094933992
C111: 0.096933992
B113: Premium to Stock Price
F114: Terminal growth rate
C115: =J24 -> 0.47739761 | D115: 0.0325 | E115: 0.035 | F115: 0.0375 | G115: 0.04 | H115: =G115+0.25% -> 0.0425 | I115: 0.045 | J115: 0.0475
C116: 0.084933992 | D116: 1.0038418 | E116: 1.0894316 | F116: 1.1840434 | G116: 1.289183 | H116: 1.4067113 | I116: 1.5389548 | J116: 1.688862
C117: 0.086933992 | D117: 0.93645552 | E117: 1.0155174 | F117: 1.102576 | G117: 1.1989092 | H117: 1.3060825 | I117: 1.4260345 | J117: 1.5611958
C118: 0.088933992 | D118: 0.87384734 | E118: 0.94708693 | F118: 1.0274463 | G118: 1.1160166 | H118: 1.2141242 | I118: 1.3233972 | J118: 1.4458565
B119: WACC | C119: 0.090933992 | D119: 0.81552664 | E119: 0.88355188 | F119: 0.95794246 | G119: 1.0396357 | H119: 1.1297624 | I119: 1.2296995 | J119: 1.3411412
C120: 0.092933992 | D120: 0.76106773 | E120: 0.82440523 | F120: 0.89345561 | G120: 0.96902831 | H120: 1.0520932 | I120: 1.1438227 | J120: 1.2456469
C121: 0.094933992 | D121: 0.71009946 | E121: 0.76920766 | F121: 0.83346161 | G121: 0.90356385 | H121: 0.98035089 | I121: 1.0648268 | J121: 1.1582073
C122: 0.096933992 | D122: 0.66229679 | E122: 0.71757657 | F122: 0.77750687 | G122: 0.84270031 | H122: 0.91388205 | I122: 0.99191689 | J122: 1.0778446
B127: P/E, P/BV MODELS
C128: Historical
...

Sheet PL
B1: 89600 | D1: =HYPERLINK("#PL!B486","▼ 1H26 Tracker: actual vs plan vs forecast (row 486)") | V1: =5198/10966 -> 0.47401058
BG2: 1Q18 | BH2: 2Q18 | BI2: 3Q18 | BJ2: 4Q18 | BK2: 1Q19 | BL2: 2Q19 | BM2: 3Q19 | BN2: 4Q19 | BO2: 1Q20 | BP2: 2Q20 | BQ2: 3Q20 | BR2: 4Q20 | BS2: 1Q21 | BT2: 2Q21 | BU2: 3Q21 | BV2: 4Q21 | BW2: 1Q22 | BX2: 2Q22 | BY2: 3Q22 | BZ2: 4Q22 | CA2: 1Q23 | CB2: 2Q23 | CC2: 3Q23 | CD2: 4Q23 | CE2: 1Q24 | CF2: 2Q24 | CG2: 3Q24 | CH2: 4Q24 | CI2: 1Q25 | CJ2: 2Q25 | CK2: 3Q25 | CL2: 4Q25 | CM2: 1Q26
B3: INCOME STATEMENTS | P3: Historical | W3: Projection | AA3: 2010 | AE3: 2011 | AI3: 2012 | AM3: 2013 | AQ3: 2014 | AU3: 2015 | AY3: 2016 | BC3: 2017 | BG3: 2018 | BK3: 2019 | BO3: 2020 | BS3: 2021 | BW3: 2022 | CA3: 2023 | CR3: INCOME STATEMENTS | CS3: 6M2022 | CT3: 6M2023 | CU3: 9M25 | CV3: 9M24 | CW3: 6M2025 | CX3: 6M2024 | CY3: YoY | CZ3: =CJ2 -> 2Q25 | DA3: =CF2 -> 2Q24 | DB3: YoY | DC3: YoY | DE3: Q1 2022 | DF3: Q1 2023 | DG3: SOQ/YP | DH3: 2022 Plan | DI3: 2023 Plan
B4: =BS!B4 -> VND bn | C4: 2012 | D4: 2013 | E4: 2014 | F4: 2015 | G4: 2016 | H4: 2017 | I4: 2018 | J4: 2019 | K4: 2020 | L4: 2021 | M4: 2022 | N4: 2023 | O4: 2024 | P4: 2025 | Q4: 2026F | R4: 2027 | S4: 2028 | V4: 2024 | W4: 2025F | AA4: Q1 10 | AB4: Q2 10 | AC4: Q3 10 | AD4: Q4 10 | AE4: Q1 11 | AF4: Q2 11 | AG4: Q3 11 | AH4: Q4 11 | AI4: Q1 12 | AJ4: Q2 12 | AK4: Q3 12 | AL4: Q4 12 | AM4: Q1 13 | AN4: Q2 13 | AO4: Q3 13 | AP4: Q4 13 | AQ4: Q1 14 | AR4: Q2 14 | AS4: Q3 14 | AT4: Q4 14 | AU4: Q1 15 | AV4: Q2 15 | AW4: Q3 15 | AX4: Q4 15 | AY4: Q1 | AZ4: Q2 | BA4: Q3 | BB4: Q4 | BC4: Q1 | BD4: Q2 | BE4: Q3 | BF4: Q4 | BG4: Q1 | BH4: Q2 | BI4: Q3 | BJ4: Q4 | BK4: Q1 | BL4: Q2 | BM4: Q3 | BN4: Q4 | BO4: Q1 | BP4: Q2 | BQ4: Q3 | BR4: Q4 | BS4: Q1 | BT4: Q2 | BU4: Q3 | BV4: Q4 | BW4: Q1 | BX4: Q2 | BY4: Q3 | BZ4: Q4 | CA4: Q1 | CB4: Q2 | CC4: Q3 | CD4: Q4 | CE4: Q1 | CF4: Q2 | CG4: Q3 | CH4: Q4 | CI4: Q1 | CJ4: Q2 | CK4: Q3 | CL4: Q4 | CM4: Q1 | CR4: =BS!CM4 -> 0 | CS4: 6M2022 | CT4: 6M2023 | DO4: Table 1. 1Q24 results | DX4: 6M/2022 | DY4: 6M/2023 | DZ4: YoY | EA4: 2023P | EB4: 2023F | EC4: % 2023F | EE4: 6M/2022 | EF4: 2022 | EG4: % 2022 | EI4: Q1/2022 | EJ4: Q1/2023 | EK4: YoY | EL4: 2020 | EN4: YoY | EO4: YoY | EP4: % 2022
DO5: (VNDbn) | DP5: 1Q23 | DQ5: 1Q24 | DR5: YoY | DS5: 4Q23 | DT5: QoQ | DU5: % 2024P | DX5: =CS9 -> 19826.314 | DY5: =CT9 -> 24165.743 | DZ5: =(DY5/DX5-1) -> 0.21887221 | EA5: 52289 | EB5: =#REF! -> #REF! | EC5: =DY5/EB5 -> #REF! | EE5: =DX5 -> 19826.314 | EF5: =M9 -> 44009.528 | EG5: =EE5/EF5 -> 0.45050049 | EI5: =DE9 -> 9730.2538 | EJ5: =DF9 -> 11681.379 | EK5: =(EJ5/EI5-1) -> 0.20052149 | EL5: =K9 -> 29830.401 | EN5: =(EF5/EL5-1) -> 0.47532473 | EO5: =(EB5/EF5-1) -> #REF! | EP5: =EI5/EF5 -> 0.22109426 | ER5: Multiples | ET5: 45153 | EV5: Q2/2025 | FA5: D/A | FB5: D/E
B6: Gross Sales | C6: =Data!L333 -> 24624.085 | D6: =Data!M333 -> 27114.702 | E6: =Data!N333 -> 32873.027 | F6: =Data!O333 -> 38707.143 | G6: =Data!P333 -> 40447.138 | H6: =Data!Q333 -> 43298.396 | I6: =Data!R333 -> 23259.126 | J6: =Data!S333 -> 27791.982 | ... P6: =Data!Y333 -> 70207.69 | Q6: =(1+Q8)*Q9 -> 57271.884 | R6: =(1+R8)*R9 -> 66034.121 | S6: =(1+S8)*S9 -> 76640.151 | U6: =CM6*4 -> 49943.347 | V6: =(1+V8)*V9 -> 55752.315 | W6: =(1+W8)*W9 -> 66428.14 | BC6: =#REF! -> #REF! | BD6: =#REF! -> #REF! | BE6: =#REF! -> #REF! | BF6: =#REF! -> #REF! | BG6: =Data!BA473 -> 4756.9653 | BH6: =Data!BB473 -> 5479.3493 | BI6: =Data!BC473 -> 6047.7296 | BJ6: =Data!BD473 -> 6975.082 | BK6: =Data!BE473 -> 5672.1264 | BL6: =Data!BF473 -> 6834.1814 | BM6: =Data!BG473 -> 7138.8048 | BN6: =Data!BH473 -> 8146.8696 | ... CM6: =Data!CG473 -> 12485.837 | CN6: =CM6*4 -> 49943.347 | CO6: =Q6/CN6 -> 1.146737 | CR6: Gross Sales | CS6: =BW6+BX6 -> 19828.54 | CT6: =CA6+CB6 -> 24167.536 | CW6: =CI6+CJ6 -> 32723.316 | CX6: =CE6+CF6 -> 29339.19 | CY6: =CW6/CX6-1 -> 0.11534492 | CZ6: =CJ6 -> 16658.336 | DA6: =CF6 -> 15245.892 | DB6: =CZ6/DA6-1 -> 0.092644199 | DE6: =SUM(BW6) -> 9731.8324 | DF6: =SUM(CA6) -> 11683.021 | DG6: =DF6/DE6-1 -> 0.20049552 | DO6: Net revenue | DP6: =Data!BU475 -> 11681.379 | DQ6: =Data!BY475 -> 14092.928 | DR6: =DQ6/DP6-1 -> 0.20644391 | DS6: =Data!BX475 -> 14690.413 | DT6: =DQ6/DS6-1 -> -0.040671716 | DU6: =DQ6/V292 -> 0.22785656 | DX6: =CS11 -> 12030.304 | DY6: =CT11 -> 14964.04 | DZ6: =(DY6/DX6-1) -> 0.24386212 | EB6: =#REF! -> #REF! | EC6: =DY6/EB6 -> #REF! | EE6: =DX6 -> 12030.304 | EF6: =M11 -> 26842.249 | EG6: =EE6/EF6 -> 0.44818541 | EI6: =DE11 -> 5776.9326 | EJ6: =DF11 -> 7113.4999 | EK6: =(EJ6/EI6-1) -> 0.23136281 | EO6: =EB6/EF6-1 -> #REF! | EP6: =EI6/EF6 -> 0.2152179 | ER6: Price | ET6: =Valuation!J21 -> 106668.11 | EV6: LT & ST interest bearing debts | EY6: 15804 | FA6: =EY6/EY10 -> 0.16169098 | FB6: =EY6/EY11 -> 0.46879449
B7: Discount | C7: =-Data!L334 -> 29.781279 | D7: =-Data!M334 -> 86.812894 | E7: =-Data!N334 -> 228.37033 | F7: =-Data!O334 -> 747.44451 | G7: =-Data!P334 -> 915.66927 | H7: =-Data!Q334 -> 639.78546 | I7: =-Data!R334 -> 45.58942 | J7: =-Data!S334 -> 75.022025 | ... P7: =-Data!Y334 -> 94.86 | Q7: =Q6*Q8 -> 77.381992 | R7: =R6*R8 -> 89.220949 | S7: =S6*S8 -> 103.55112 | V7: =V6*V8 -> 7.7062781 | W7: =W6*W8 -> 120.1269 | BC7: =-#REF! -> #REF! | BD7: =-#REF! -> #REF! | BE7: =-#REF! -> #REF! | BF7: =-#REF! -> #REF! | BG7: =-Data!BA474 -> 6.1967292 | BH7: =-Data!BB474 -> 5.0866045 | BI7: =-Data!BC474 -> 11.670624 | BJ7: =-Data!BD474 -> 22.635461 | BK7: =-Data!BE474 -> 5.6467473 | BL7: =-Data!BF474 -> 8.2628592 | BM7: =-Data!BG474 -> 34.430711 | BN7: =-Data!BH474 -> 26.681707 | ... CM7: =-Data!CG474 -> 5.8394976 | CN7: =CM7*4 -> 23.35799 | CO7: =Q7/CN7 -> 3.3128703 | CR7: Discount | CS7: =BW7+BX7 -> 2.2261443 | CT7: =CA7+CB7 -> 1.7932434 | CW7: =CI7+CJ7 -> 40.462169 | CX7: =CE7+CF7 -> 1.0348563 | CY7: =CW7/CX7-1 -> 38.099313 | CZ7: =CJ7 -> 33.622721 | DA7: =CF7 -> 0.6658725 | DB7: =CZ7/DA7-1 -> 49.494232 | DO7: Technology | DX7: =CS13 -> 7796.0096 | DY7: =CT13 -> 9201.7033 | DZ7: =(DY7/DX7-1) -> 0.18030938 | EB7: =#REF! -> #REF! | EC7: =DY7/EB7 -> #REF! | EE7: =DX7 -> 7796.0096 | EF7: =M13 -> 17167.279 | EG7: =EE7/EF7 -> 0.4541203 | EI7: =DE13 -> 3953.3213 | EJ7: =DF13 -> 4567.879 | EK7: =(EJ7/EI7-1) -> 0.15545352 | EL7: =K13 -> 11813.657 | EN7: =(EF7/EL7-1) -> 0.4531722 | EO7: =(EB7/EF7-1) -> #REF! | EP7: =EI7/EF7 -> 0.23028235 | ER7: Outstanding no. of shares | ET7: 1471321000 | EU7: MC (US$bn) | EV7: Minorities Interest | EY7: 5070 | FA7: (Cash+ST inv.)/A
B8: Discount/Gross sales (%) | C8: =C7/C6 -> 0.001209437 | D8: =D7/D6 -> 0.0032016909 | E8: =E7/E6 -> 0.006947043 | F8: =F7/F6 -> 0.019310247 | G8: =G7/G6 -> 0.022638666 | H8: =H7/H6 -> 0.014776193 | I8: =I7/I6 -> 0.0019600659 | J8: =J7/J6 -> 0.0026994125 | ... P8: =P7/P6 -> 0.001351134 | Q8: =P8 -> 0.001351134 | R8: =Q8 -> 0.001351134 | S8: =R8 -> 0.001351134 | V8: =N8 -> 0.00013822346 | W8: =O8 -> 0.0018083737 | BC8: =BC7/BC6 -> #REF! | BD8: =BD7/BD6 -> #REF! | BE8: =BE7/BE6 -> #REF! | BF8: =BF7/BF6 -> #REF! | BG8: =BG7/BG6 -> 0.0013026644 | BH8: =BH7/BH6 -> 0.00092832273 | BI8: =BI7/BI6 -> 0.001929753 | BJ8: =BJ7/BJ6 -> 0.0032451893 | ... CM8: =CM7/CM6 -> 0.00046768973 | CN8: =CM8*4 -> 0.0018707589 | CO8: =Q8/CN8 -> 0.72223846 | CR8: Discount/Gross sales (%) | CS8: =CS7/CS6 -> 0.0001122697 | CT8: =CT7/CT6 -> 7.4200506e-05 | CW8: =CW7/CW6 -> 0.0012364936 | CX8: =CX7/CX6 -> 3.5272149e-05 | CY8: =CW8/CX8-1 -> 34.055804 | CZ8: =CJ8 -> 0.0020183721 | DA8: =CF8 -> 4.3675535e-05 | DB8: =CZ8/DA8-1 -> 45.212877 | DO8: Global IT | DP8: =5435 -> 5435 | DQ8: =6999 -> 6999 | DR8: =DQ8/DP8-1 -> 0.28776449 | DX8: =DX7/DX5 -> 0.39321528 | DY8: =DY7/DY5 -> 0.38077469 | EB8: =EB7/EB5 -> #REF! | EE8: =DX8 -> 0.39321528 | EF8: =EF7/EF5 -> 0.39008096 | EI8: =EI7/EI5 -> 0.40629169 | EJ8: =EJ7/EJ5 -> 0.39103937 | EL8: =EL7/EL5 -> 0.39602745 | ER8: Market Cap (VND bn) | ET8: =ET7*ET6/10^9 -> 156943.03 | EU8: =ET8/ET10 -> 6.5887081 | EV8: Cash and equivalent | EY8: 23728 | FA8: =(EY8+EY9)/EY10 -> 0.38241493
B9: Net sales | C9: =C6-C7 -> 24594.304 | D9: =D6-D7 -> 27027.889 | E9: =E6-E7 -> 32644.656 | F9: =F6-F7 -> 37959.699 | G9: =G6-G7 -> 39531.469 | H9: =H6-H7 -> 42658.611 | I9: =I6-I7 -> 23213.537 | J9: =J6-J7 -> 27716.96 | ... O9: =O6-O7 -> 62848.79 | P9: =P6 -> 70207.69 | Q9: =Revenue!J2 -> 57194.607 | R9: =Revenue!K2 -> 65945.02 | S9: =Revenue!L2 -> 76536.74 | V9: =Revenue!O3 -> 55744.61 | W9: =Revenue!N3 -> 66308.23 | BC9: =BC6-BC7 -> #REF! | BD9: =BD6-BD7 -> #REF! | BE9: =BE6-BE7 -> #REF! | BF9: =BF6-BF7 -> #REF! | BG9: =BG6-BG7 -> 4750.7686 | BH9: =BH6-BH7 -> 5474.2627 | BI9: =BI6-BI7 -> 6036.0589 | BJ9: =BJ6-BJ7 -> 6952.4466 | ... CM9: =CM6-CM7 -> 12479.997 | CN9: =CM9*4 -> 49919.989 | CO9: =Q9/CN9 -> 1.1457256 | CR9: Net sales | CS9: =BW9+BX9 -> 19826.314 | CT9: =CA9+CB9 -> 24165.743 | CU9: =CK9+CJ9+CI9 -> 49887.375 | CV9: =CG9+CF9+CE9 -> 45240.977 | CW9: =CI9+CJ9 -> 32682.854 | CX9: =CE9+CF9 -> 29338.155 | CY9: =CW9/CX9-1 -> 0.1140051 | CZ9: =CJ9 -> 16624.713 | DA9: =CF9 -> 15245.226 | DB9: =CZ9/DA9-1 -> 0.090486464 | DD9: =CT9/CS9-1 -> 0.21887221 | DE9: =SUM(BW9) -> 9730.2538 | DF9: =SUM(CA9) -> 11681.379 | DG9: =DF9/DE9-1 -> 0.20052149 | DH9: 42420 | DI9: 52289 | DJ9: =DF9/DI9 -> 0.22340031 | DO9: Domestic IT | DP9: 1407 | DQ9: =1472 -> 1472 | DR9: =DQ9/DP9-1 -> 0.046197584 | DX9: =CS17 -> 2020.9156 | DY9: =CT17 -> 2340.1681 | DZ9: =(DY9/DX9-1) -> 0.1579742 | EB9: =#REF! -> #REF! | EC9: =DY9/EB9 -> #REF! | EE9: =DX9 -> 2020.9156 | EF9: =M17 -> 4526.4407 | EG9: =EE9/EF9 -> 0.44646902 | EI9: =DE17 -> 1007.0925 | EJ9: =DF17 -> 1101.8715 | EK9: =(EJ9/EI9-1) -> 0.094111551 | EL9: =K17 -> 2713.5613 | EN9: =IFERROR((EF9/EL9-1)*100,0) -> 66.808121 | EO9: =IFERROR((EB9/EF9-1),0) -> 0 | EP9: =EI9/EF9 -> 0.22249104 | ER9: EV (VND bn) | ET9: =ET8+EY6+EY7-EY8-EY9 -> 140439.03 | EV9: ST investment | EY9: 13650 | FA9: =EY9+EY8 -> 37378
B10: Growth (%) | C10: =C9/B9-1 -> #VALUE! | D10: =D9/C9-1 -> 0.098949129 | E10: =E9/D9-1 -> 0.20781378 | F10: =F9/E9-1 -> 0.16281508 | G10: =G9/F9-1 -> 0.04140628 | H10: =H9/G9-1 -> 0.079105135 | I10: =I9/H9-1 -> -0.45582999 | J10: =J9/I9-1 -> 0.19399988 | ... S10: =S9/R9-1 -> 0.1606144 | V10: =V9/N9-1 -> 0.059422917 | W10: =W9/O9-1 -> 0.05504386 | BK10: =BK9/BG9-1 -> 0.19275007 | BL10: =BL9/BH9-1 -> 0.24691102 | BM10: =BM9/BI9-1 -> 0.17698886 | BN10: =BN9/BJ9-1 -> 0.1679612 | BO10: =BO9/BK9-1 -> 0.17013832 | BP10: =BP9/BL9-1 -> 0.022573368 | BQ10: =BQ9/BM9-1 -> 0.063165925 | BR10: =BR9/BN9-1 -> 0.06730346 | ... CC10: =CC9/BY9-1 -> 0.23439675 | CD10: =CD9/CA9-1 -> 0.25759235 | CE10: =CE9/CA9-1 -> 0.20644391 | CF10: =CF9/CB9-1 -> 0.22114559 | CG10: =CG9/CC9-1 -> 0.15558178 | CH10: =CH9/CD9-1 -> 0.1985926 | CI10: =CI9/CE9-1 -> 0.13944671 | CJ10: =CJ9/CF9-1 -> 0.090486464 | CK10: =CK9/CG9-1 -> 0.081853367 | CL10: =CL9/CH9-1 -> 0.14866292 | CM10: =CM9/CI9-1 -> -0.22282428 | CN10: =CM10*4 -> -0.89129713 | CO10: =Q10/CN10 -> 0.20795675 | CR10: Growth (%) | CY10: =CW10/CX10-1 -> #DIV/0! | CZ10: =CJ10 -> 0.090486464 | DA10: =CF10 -> 0.22114559 | DB10: =CZ10/DA10-1 -> -0.59082855 | DO10: Telecommunications | DP10: =3695+95 -> 3790 | DQ10: =3885+127 -> 4012 | DR10: =DQ10/DP10-1 -> 0.058575198 | DX10: =CS20 -> 2778.7325 | DY10: =CT20 -> 3068.0512 | DZ10: =(DY10/DX10-1) -> 0.10411897 | EB10: =#REF! -> #REF! | EC10: =DY10/EB10 -> #REF! | EE10: =DX10 -> 2778.7325 | EF10: =M20 -> 5846.2807 | EG10: =EE10/EF10 -> 0.47529919 | EI10: =DE20 -> 1530.5722 | EJ10: =DF20 -> 1592.4925 | EK10: =(EJ10/EI10-1) -> 0.040455608 | EL10: =K20 -> 4495.3665 | EN10: =(EF10/EL10-1) -> 0.30051259 | EO10: =(EB10/EF10-1) -> #REF! | EP10: =EI10/EF10 -> 0.26180273 | ER10: USDVND | ET10: 23820 | EV10: Total Assets | EY10: 97742
B11: COGS | C11: =-Data!L336 -> 19902.159 | D11: =-Data!M336 -> 21488.736 | E11: =-Data!N336 -> 26456.135 | F11: =-Data!O336 -> 30465.879 | G11: =-Data!P336 -> 31093.334 | H11: =-Data!Q336 -> 32976.206 | I11: =-Data!R336 -> 14490.658 | J11: =-Data!S336 -> 17004.911 | ... P11: =-Data!Y336 -> 44217.42 | Q11: =Revenue!J5 -> 37370.882 | R11: =Revenue!K5 -> 43668.412 | S11: =Revenue!L5 -> 50958.99 | V11: =Revenue!O5 -> 36150.136 | W11: =Revenue!N5 -> 41453.585 | BC11: =-#REF! -> #REF! | BD11: =-#REF! -> #REF! | BE11: =-#REF! -> #REF! | BF11: =-#REF! -> #REF! | BG11: =-Data!BA476 -> 2895.2083 | BH11: =-Data!BB476 -> 3473.5901 | BI11: =-Data!BC476 -> 3740.3887 | BJ11: =-Data!BD476 -> 4381.2358 | BK11: =-Data!BE476 -> 3387.1493 | BL11: =-Data!BF476 -> 4247.789 | BM11: =-Data!BG476 -> 4321.6489 | BN11: =-Data!BH476 -> 5049.1596 | ... CM11: =-Data!CG476 -> 8235.1073 | CN11: =CM11*4 -> 32940.429 | CO11: =Q11/CN11 -> 1.1344989 | CR11: COGS | CS11: =BW11+BX11 -> 12030.304 | CT11: =CA11+CB11 -> 14964.04 | CU11: =CK11+CJ11+CI11 -> 31046.121 | CV11: =CG11+CF11+CE11 -> 27920.198 | CW11: =CI11+CJ11 -> 20360.466 | CX11: =CE11+CF11 -> 18176.332 | CY11: =CW11/CX11-1 -> 0.12016364 | CZ11: =CJ11 -> 10603.673 | DA11: =CF11 -> 9593.8691 | DB11: =CZ11/DA11-1 -> 0.10525513 | DD11: =CT11/CS11-1 -> 0.24386212 | DE11: =SUM(BW11) -> 5776.9326 | DF11: =SUM(CA11) -> 7113.4999 | DG11: =DF11/DE11-1 -> 0.23136281 | DO11: Investment, education & others | DP11: 1048 | DQ11: 1609 | DR11: =DQ11/DP11-1 -> 0.53530534 | DX11: =(DX9+DX10)/DX5 -> 0.24208474 | DY11: =(DY9+DY10)/DY5 -> 0.22379694 | EB11: =(EB9+EB10)/EB5 -> #REF! | EE11: =DX11 -> 0.24208474 | EF11: =(EF9+EF10)/EF5 -> 0.23569263 | EI11: =(EI9+EI10)/EI5 -> 0.26080149 | EJ11: =(EJ9+EJ10)/EJ5 -> 0.23065462 | EL11: =(EL9+EL10)/EL5 -> 0.24166379 | EV11: Equity | EY11: 33712
B12: Growth (%) | D12: =D11/C11-1 -> 0.079718847 | E12: =E11/D11-1 -> 0.23116292 | F12: =F11/E11-1 -> 0.15156197 | G12: =G11/F11-1 -> 0.020595326 | H12: =H11/G11-1 -> 0.060555507 | I12: =I11/H11-1 -> -0.56057232 | J12: =J11/I11-1 -> 0.17350852 | K12: =K11/J11-1 -> 0.059502373 | ... S12: =S11/R11-1 -> 0.16695313 | V12: =V11/N11-1 -> 0.11925653 | W12: =W11/O11-1 -> 0.058827803 | BK12: =BK11/BG11-1 -> 0.16991559 | BL12: =BL11/BH11-1 -> 0.22288146 | BM12: =BM11/BI11-1 -> 0.15540101 | BN12: =BN11/BJ11-1 -> 0.15245099 | BO12: =BO11/BK11-1 -> 0.18276053 | BP12: =BP11/BL11-1 -> 0.0024621849 | BQ12: =BQ11/BM11-1 -> 0.053845523 | BR12: =BR11/BN11-1 -> 0.029039301 | ... CC12: =CC11/BY11-1 -> 0.21745275 | CD12: =CD11/CA11-1 -> 0.2734307 | CE12: =CE11/CA11-1 -> 0.20650353 | CF12: =CF11/CB11-1 -> 0.22206487 | CG12: =CG11/CC11-1 -> 0.17887753 | CH12: =CH11/CD11-1 -> 0.23974047 | CI12: =CI11/CE11-1 -> 0.13682906 | CJ12: =CJ11/CF11-1 -> 0.10525513 | CK12: =CK11/CG11-1 -> 0.09665452 | CL12: =CL11/CH11-1 -> 0.17345338 | CM12: =CM11/CI11-1 -> -0.15596167 | CN12: =CM12*4 -> -0.62384667 | CO12: =Q12/CN12 -> 0.24819885 | CR12: Growth (%) | CY12: =CW12/CX12-1 -> #DIV/0! | CZ12: =CJ12 -> 0.10525513 | DA12: =CF12 -> 0.22206487 | DB12: =CZ12/DA12-1 -> -0.52601631 | DO12: COGS | DP12: =-Data!BU476 -> 7113.4999 | DQ12: =-Data!BY476 -> 8582.4627 | DR12: =DQ12/DP12-1 -> 0.20650353 | DS12: =-Data!BX476 -> 9058.5491 | DT12: =DQ12/DS12-1 -> -0.052556585 | EE12: =DX12 -> 0
B13: Gross Profit | C13: =C9-C11 -> 4692.145 | D13: =D9-D11 -> 5539.1527 | E13: =E9-E11 -> 6188.5213 | F13: =F9-F11 -> 7493.8199 | G13: =G9-G11 -> 8438.1351 | H13: =H9-H11 -> 9682.4047 | I13: =I9-I11 -> 8722.879 | J13: =J9-J11 -> 10712.05 | ... S13: =S9-S11 -> 25577.75 | V13: =V9-V11 -> 19594.474 | W13: =W9-W11 -> 24854.645 | BC13: =#REF! -> #REF! | BD13: =#REF! -> #REF! | BE13: =#REF! -> #REF! | BF13: =#REF! -> #REF! | BG13: =Data!BA477 -> 1855.5603 | BH13: =Data!BB477 -> 2000.6726 | BI13: =Data!BC477 -> 2295.6702 | BJ13: =Data!BD477 -> 2571.2107 | BK13: =Data!BE477 -> 2279.3303 | BL13: =Data!BF477 -> 2578.1295 | BM13: =Data!BG477 -> 2782.7253 | BN13: =Data!BH477 -> 3071.0283 | ... CM13: =Data!CG477 -> 4244.8899 | CN13: =CM13*4 -> 16979.56 | CO13: =Q13/CN13 -> 1.1675052 | CR13: Gross Profit | CS13: =BW13+BX13 -> 7796.0096 | CT13: =CA13+CB13 -> 9201.7033 | CU13: =CK13+CJ13+CI13 -> 18841.254 | CV13: =CG13+CF13+CE13 -> 17320.779 | CW13: =CI13+CJ13 -> 12322.388 | CX13: =CE13+CF13 -> 11161.823 | CY13: =CW13/CX13-1 -> 0.10397629 | CZ13: =CJ13 -> 6021.04 | DA13: =CF13 -> 5651.3573 | DB13: =CZ13/DA13-1 -> 0.065414855 | DE13: =SUM(BW13) -> 3953.3213 | DF13: =SUM(CA13) -> 4567.879 | DG13: =DF13/DE13-1 -> 0.15545352 | DO13: Gross profit | DP13: =Data!BU477 -> 4567.879 | DQ13: =Data!BY477 -> 5510.4657 | DR13: =DQ13/DP13-1 -> 0.20635106 | DS13: =Data!BX477 -> 5631.8636 | DT13: =DQ13/DS13-1 -> -0.021555544 | DX13: =DX7-DX9-DX10 -> 2996.3616 | DY13: =DY7-DY9-DY10 -> 3793.484 | DZ13: =(DY13/DX13-1) -> 0.2660301 | EB13: =EB7-EB9-EB10 -> #REF! | EC13: =DY13/EB13 -> #REF! | EE13: =DX13 -> 2996.3616 | EF13: =EF7-EF9-EF10 -> 6794.5573 | EG13: =EE13/EF13 -> 0.44099439 | EI13: =EI7-EI9-EI10 -> 1415.6566 | EJ13: =EJ7-EJ9-EJ10 -> 1873.515 | EK13: =(EJ13/EI13-1) -> 0.3234248 | EL13: =EL7-EL9-EL10 -> 4604.7297 | EN13: =(EF13/EL13-1) -> 0.47556051 | EO13: =(EB13/EF13-1) -> #REF! | EP13: =EI13/EF13 -> 0.20835155
B14: Gross Profit margin (%) | C14: =C13/C9 -> 0.19078178 | D14: =D13/D9 -> 0.20494212 | E14: =E13/E9 -> 0.18957226 | F14: =F13/F9 -> 0.19741516 | G14: =G13/G9 -> 0.21345362 | H14: =H13/H9 -> 0.22697421 | I14: =I13/I9 -> 0.37576691 | J14: =J13/J9 -> 0.38647996 | ... S14: =S13/S9 -> 0.33418917 | V14: =V13/V9 -> 0.35150437 | W14: =W13/W9 -> 0.37483499 | BC14: =BC13/BC9 -> #REF! | BD14: =BD13/BD9 -> #REF! | BE14: =BE13/BE9 -> #REF! | BF14: =BF13/BF9 -> #REF! | BG14: =BG13/BG9 -> 0.39058108 | BH14: =BH13/BH9 -> 0.36546887 | BI14: =BI13/BI9 -> 0.38032602 | BJ14: =BJ13/BJ9 -> 0.36982819 | ... CM14: =CM13/CM9 -> 0.34013548 | CN14: =CM14*4 -> 1.3605419 | CO14: =Q14/CN14 -> 0.25475238 | CR14: Gross Profit margin (%) | CS14: =CS13/CS9 -> 0.39321528 | CT14: =CT13/CT9 -> 0.38077469 | CW14: =CW13/CW9 -> 0.37702913 | CX14: =CX13/CX9 -> 0.38045416 | CY14: =CW14/CX14-1 -> -0.0090024776 | CZ14: =CJ14 -> 0.36217407 | DA14: =CF14 -> 0.37069684 | DB14: =CZ14/DA14-1 -> -0.022991215 | DE14: =DE13/DE9 -> 0.40629169 | DF14: =DF13/DF9 -> 0.39103937 | DO14: Gross margin | DP14: =DP13/DP6 -> 0.39103937 | DQ14: =DQ13/DQ6 -> 0.39100927 | DS14: =DS13/DS6 -> 0.38337 | DX14: =DX13/DX5 -> 0.15113055 | DY14: =DY13/DY5 -> 0.15697775 | EB14: =EB13/EB5 -> #REF! | EE14: =DX14 -> 0.15113055 | EF14: =EF13/EF5 -> 0.15438833 | EI14: =EI13/EI5 -> 0.1454902 | EJ14: =EJ13/EJ5 -> 0.16038475 | EL14: =EL13/EL5 -> 0.15436366 | ER14: Price | ET14: 100500 | EU14: # of shares | EV14: =ET7 -> 1471321000
CN15: =CM15*4 -> 0 | CO15: =Q15/CN15 -> #DIV/0! | CY15: =CW15/CX15-1 -> #DIV/0! | CZ15: =CJ15 -> 0 | DA15: =CF15 -> 0 | DB15: =CZ15/DA15-1 -> #DIV/0! | DO15: Selling expenses | DP15: =-Data!BU482 -> 1101.8715 | DQ15: =-Data!BY482 -> 1368.9486 | DR15: =DQ15/DP15-1 -> 0.24238496 | DS15: =-Data!BX482 -> 1316.1563 | DT15: =DQ15/DS15-1 -> 0.040110997 | EE15: =DX15 -> 0
B16: Operating Expenses | CN16: =CM16*4 -> 0 | CO16: =Q16/CN16 -> #DIV/0! | CR16: Operating Expenses | CY16: =CW16/CX16-1 -> #DIV/0! | CZ16: =CJ16 -> 0 | DA16: =CF16 -> 0 | DB16: =CZ16/DA16-1 -> #DIV/0! | DO16: Admin expenses | DP16: =-Data!BU483 -> 1592.4925 | DQ16: =-Data!BY483 -> 1823.4718 | DR16: =DQ16/DP16-1 -> 0.14504264 | DS16: =-Data!BX483 -> 1979.9444 | DT16: =DQ16/DS16-1 -> -0.079028784 | DX16: =CS29 -> 3874.3534 | DY16: =CT29 -> 4813.518 | DZ16: =(DY16/DX16-1) -> 0.24240551 | EB16: =#REF! -> #REF! | EC16: =DY16/EB16 -> #REF! | EE16: =DX16 -> 3874.3534 | EF16: =M29 -> 8627.6218 | EG16: =EE16/EF16 -> 0.44906389 | EI16: =DE29 -> 1845.6918 | EJ16: =DF29 -> 2383.532 | EK16: =(EJ16/EI16-1) -> 0.29140307 | EL16: =K29 -> 6095.3372 | EN16: =(EF16/EL16-1) -> 0.4154462 | EO16: =(EB16/EF16-1) -> #REF! | EP16: =EI16/EF16 -> 0.21392822 | ER16: Market Cap (VND mn) | ET16: =ET8 -> 156943.03 | EU16: EV (VND mn) | EV16: =ET9 -> 140439.03
B17: Selling expenses | C17: =-Data!L342 -> 857.89299 | D17: =-Data!M342 -> 1356.6074 | E17: =-Data!N342 -> 1617.819 | F17: =-Data!O342 -> 2226.8708 | G17: =-Data!P342 -> 2638.4545 | H17: =-Data!Q342 -> 3074.6374 | I17: =-Data!R342 -> 2047.8336 | J17: =-Data!S342 -> 2345.9576 | ... P17: =-Data!Y342 -> 7580.84 | Q17: =Q9*Q19 -> 4575.5685 | R17: =R9*R19 -> 5209.6566 | S17: =S9*S19 -> 6046.4024 | V17: =V9*Assumptions!AG42 -> 5574.461 | W17: =W9*W19 -> 7028.6724 | BC17: =-#REF! -> #REF! | BD17: =-#REF! -> #REF! | BE17: =-#REF! -> #REF! | BF17: =-#REF! -> #REF! | BG17: =-Data!BA482 -> 422.70741 | BH17: =-Data!BB482 -> 451.95925 | BI17: =-Data!BC482 -> 507.53496 | BJ17: =-Data!BD482 -> 665.49633 | BK17: =-Data!BE482 -> 488.58605 | BL17: =-Data!BF482 -> 566.4555 | BM17: =-Data!BG482 -> 559.02314 | BN17: =-Data!BH482 -> 727.16923 | ... CM17: =-Data!CG482 -> 1002.3372 | CN17: =CM17*4 -> 4009.3486 | CO17: =Q17/CN17 -> 1.1412249 | CR17: Selling expenses | CS17: =BW17+BX17 -> 2020.9156 | CT17: =CA17+CB17 -> 2340.1681 | CU17: =CK17+CJ17+CI17 -> 5535.6647 | CV17: =CG17+CF17+CE17 -> 4521.0239 | CW17: =CI17+CJ17 -> 3619.0818 | CX17: =CE17+CF17 -> 2957.161 | CY17: =CW17/CX17-1 -> 0.22383661 | CZ17: =CJ17 -> 1790.2959 | DA17: =CF17 -> 1588.2123 | DB17: =CZ17/DA17-1 -> 0.12723964 | DE17: =SUM(BW17) -> 1007.0925 | DF17: =SUM(CA17) -> 1101.8715 | DG17: =DF17/DE17-1 -> 0.094111551 | DO17: SG&A as % of sales | DP17: =CA23 -> 0.23065462 | DQ17: =CE23 -> 0.2265264 | DS17: =CD23 -> 0.22437087 | DX17: =DX16/DX5 -> 0.19541471 | DY17: =DY16/DY5 -> 0.19918767 | EB17: =EB16/EB5 -> #REF! | EE17: =DX17 -> 0.19541471 | EF17: =EF16/EF5 -> 0.19603986 | EI17: =EI16/EI5 -> 0.18968588 | EJ17: =EJ16/EJ5 -> 0.20404543 | EL17: =EL16/EL5 -> 0.20433306 | ES17: 2020 | ET17: 2021 | EU17: 2022 | EV17: 2023 | EW17: 2024 | EX17: 2025 | EY17: 2026F | EZ17: 2027F | FA17: 2028F | FB17: 2028F
B18: Growth (%) | J18: =J17/I17-1 -> 0.14558022 | K18: =K17/J17-1 -> 0.15669664 | L18: =L17/K17-1 -> 0.32836901 | M18: =M17/L17-1 -> 0.25573632 | N18: =N17/M17-1 -> 0.15820625 | O18: =O17/N17-1 -> 0.1665998 | P18: =P17/O17-1 -> 0.23951759 | Q18: =Q17/P17-1 -> -0.39642988 | ... S18: =S17/R17-1 -> 0.1606144 | V18: =V17/N17-1 -> 0.063310597 | W18: =W17/O17-1 -> 0.14923452 | BK18: =BK17/BG17-1 -> 0.15584928 | BL18: =BL17/BH17-1 -> 0.25333311 | BM18: =BM17/BI17-1 -> 0.10144756 | BN18: =BN17/BJ17-1 -> 0.092672035 | BO18: =BO17/BK17-1 -> 0.2694193 | BP18: =BP17/BL17-1 -> 0.20605015 | BQ18: =BQ17/BM17-1 -> 0.12240733 | BR18: =BR17/BN17-1 -> 0.18071931 | ... CC18: =CC17/BY17-1 -> 0.2676077 | CD18: =CD17/CA17-1 -> 0.19447344 | CE18: =CE17/CA17-1 -> 0.24238496 | CF18: =CF17/CB17-1 -> 0.28257835 | CG18: =CG17/CC17-1 -> 0.090427352 | CH18: =CH17/CD17-1 -> 0.21181657 | CI18: =CI17/CE17-1 -> 0.33590545 | CJ18: =CJ17/CF17-1 -> 0.12723964 | CK18: =CK17/CG17-1 -> 0.22554399 | CL18: =CL17/CH17-1 -> 0.27089168 | CM18: =CM17/CI17-1 -> -0.45191116 | CN18: =CM18*4 -> -1.8076446 | CO18: =Q18/CN18 -> 0.21930742 | CR18: Growth (%) | CY18: =CW18/CX18-1 -> #DIV/0! | CZ18: =CJ18 -> 0.12723964 | DA18: =CF18 -> 0.28257835 | DB18: =CZ18/DA18-1 -> -0.54971908 | DO18: Net financial income | DP18: =Data!BU478+Data!BU479 -> 179.66121 | DQ18: =Data!BY478+Data!BY479 -> 123.02771 | DR18: =DQ18/DP18-1 -> -0.31522386 | DS18: =Data!BX478+Data!BX479 -> -7.2109139 | DT18: =DQ18/DS18-1 -> -18.06132 | DX18: =CS39 -> 317.52603 | DY18: =CT39 -> 515.20687 | DZ18: =DY18/DX18-1 -> 0.62256577 | EB18: =#REF! -> #REF! | EC18: =DY18/EB18 -> #REF! | EE18: =DX18 -> 317.52603 | EF18: =M39 -> 311.13428 | EI18: =DE39 -> 148.21378 | EJ18: =DF39 -> 179.66121 | EK18: =EJ18/EI18-1 -> 0.21217616 | EL18: =K39 -> 273.73121 | EO18: =(EB18/EF18-1) -> #REF! | EP18: =EI18/EF18 -> 0.47636595 | ER18: EPS (VND) | ES18: =K94 -> 4114.9824 | ET18: =L94 -> 4341.5676 | EU18: =M94 -> 4419.7695 | EV18: =N94 -> 4648.3799 | EW18: =O94 -> 4876.6812 | EX18: =P94 -> 5072.8438 | EY18: =Q94 -> 6139.6016 | EZ18: =R94 -> 6936.1467 | ... FB18: =T94 -> 0
B19: Selling expenses/Net sales (%) | C19: =C17/C9 -> 0.034881776 | D19: =D17/D9 -> 0.050192872 | E19: =E17/E9 -> 0.049558462 | F19: =F17/F9 -> 0.05866408 | G19: =G17/G9 -> 0.066743144 | H19: =H17/H9 -> 0.072075423 | I19: =I17/I9 -> 0.088217215 | J19: =J17/J9 -> 0.084639789 | ... P19: =P17/P9 -> 0.10797735 | Q19: 0.08 | R19: 0.079 | S19: 0.079 | V19: =V17/V9 -> 0.1 | W19: 0.106 | BC19: =BC17/BC9 -> #REF! | BD19: =BD17/BD9 -> #REF! | BE19: =BE17/BE9 -> #REF! | BF19: =BF17/BF9 -> #REF! | BG19: =BG17/BG9 -> 0.088976635 | BH19: =BH17/BH9 -> 0.082560753 | BI19: =BI17/BI9 -> 0.084083831 | BJ19: =BJ17/BJ9 -> 0.095721172 | ... CM19: =CM17/CM9 -> 0.080315495 | CN19: =CM19*4 -> 0.32126198 | CO19: =Q19/CN19 -> 0.24901795 | CR19: Selling expenses/Net sales (%) | CS19: =CS17/CS9 -> 0.10193098 | CT19: =CT17/CT9 -> 0.096838241 | CW19: =CW17/CW9 -> 0.11073335 | CX19: =CX17/CX9 -> 0.10079574 | CY19: =CW19/CX19-1 -> 0.098591569 | CZ19: =CJ19 -> 0.10768883 | DA19: =CF19 -> 0.10417768 | DB19: =CZ19/DA19-1 -> 0.03370347 | DE19: =DE17/DE9 -> 0.10350115 | DF19: =DF17/DF9 -> 0.09432718 | DO19: Operating profit*(before interest income) | DP19: =Data!BU484 -> 2096.9333 | DQ19: =Data!BY484 -> 2515.5271 | DR19: =DQ19/DP19-1 -> 0.19962192 | DS19: =Data!BX484 -> 2386.6983 | DT19: =DQ19/DS19-1 -> 0.053977846 | DX19: =CS44 -> 28.021778 | DY19: =CT44 -> 52.076627 | DZ19: =DY19/DX19-1 -> 0.85843406 | EB19: =#REF! -> #REF! | EC19: =DY19/EB19 -> #REF! | EE19: =DX19 -> 28.021778 | EF19: =M44 -> 72.993338 | EI19: =DE44 -> 6.3472676 | EJ19: =DF44 -> 23.710365 | EK19: =EJ19/EI19-1 -> 2.7355231 | EL19: =K44 -> 72.802166 | EO19: =(EB19/EF19-1) -> #REF! | EP19: =EI19/EF19 -> 0.086956807 | ER19: BVPS (VND) | ES19: =K122 -> 20083.96 | ET19: =L122 -> 19768.51 | EU19: =M122 -> 19185.012 | EV19: =N122 -> 19665.172 | EW19: =O122 -> 20253.448 | EX19: =P122 -> 21418.383 | EY19: =Q122 -> 25209.888 | EZ19: =R122 -> 29797.937 | FA19: =S122 -> 35309.016 | FB19: =U122 -> 0
B20: Administration expenses | C20: =-Data!L343 -> 1602.6764 | D20: =-Data!M343 -> 1846.4737 | E20: =-Data!N343 -> 2236.0336 | F20: =-Data!O343 -> 2331.7895 | G20: =-Data!P343 -> 2751.1585 | H20: =-Data!Q343 -> 3441.1287 | I20: =-Data!R343 -> 3553.2881 | J20: =-Data!S343 -> 4219.2548 | ... P20: =-Data!Y343 -> 7330.79 | Q20: =Q9*9.6% -> 5490.6822 | R20: =R9*9.5% -> 6264.7769 | S20: =S9*9.5% -> 7270.9903 | V20: =V9*Assumptions!AG43 -> 7135.3101 | W20: =W9*11.4% -> 7559.1382 | BC20: =-#REF! -> #REF! | BD20: =-#REF! -> #REF! | BE20: =-#REF! -> #REF! | BF20: =-#REF! -> #REF! | BG20: =-Data!BA483 -> 770.42648 | BH20: =-Data!BB483 -> 829.76604 | BI20: =-Data!BC483 -> 900.92744 | BJ20: =-Data!BD483 -> 1057.6961 | BK20: =-Data!BE483 -> 980.58876 | BL20: =-Data!BF483 -> 931.28081 | BM20: =-Data!BG483 -> 1031.0847 | BN20: =-Data!BH483 -> 1309.1446 | ... CM20: =-Data!CG483 -> 1210.2827 | CN20: =CM20*4 -> 4841.1307 | CO20: =Q20/CN20 -> 1.1341735 | CR20: Administration expenses | CS20: =BW20+BX20 -> 2778.7325 | CT20: =CA20+CB20 -> 3068.0512 | CU20: =CK20+CJ20+CI20 -> 5438.4204 | CV20: =CG20+CF20+CE20 -> 5344.0877 | CW20: =CI20+CJ20 -> 3791.1437 | CX20: =CE20+CF20 -> 3536.1299 | CY20: =CW20/CX20-1 -> 0.072116644 | CZ20: =CJ20 -> 1913.7066 | DA20: =CF20 -> 1712.6581 | DB20: =CZ20/DA20-1 -> 0.11738977 | DE20: =SUM(BW20) -> 1530.5722 | DF20: =SUM(CA20) -> 1592.4925 | DG20: =DF20/DE20-1 -> 0.040455608 | DO20: Operating margin | DP20: =DP19/DP6 -> 0.17951077 | DQ20: =DQ19/DQ6 -> 0.1784957 | DS20: =DS19/DS6 -> 0.16246639 | DX20: =CS47 -> 3636.8925 | DY20: =CT47 -> 4338.7763 | DZ20: =(DY20/DX20-1) -> 0.19298998 | EA20: 9055 | EB20: =#REF! -> #REF! | EC20: =DY20/EB20 -> #REF! | ED20: =DY20/EA20 -> 0.47915807 | EE20: =DX20 -> 3636.8925 | EF20: =M47 -> 7662.283 | EG20: =EE20/EF20 -> 0.47464868 | EI20: =DE47 -> 1779.0478 | EJ20: =DF47 -> 2120.6436 | EK20: =(EJ20/EI20-1) -> 0.19201046 | EL20: =K47 -> 5263.4566 | EN20: =(EF20/EL20-1) -> 0.45575113 | EO20: =(EB20/EF20-1) -> #REF! | EP20: =EI20/EF20 -> 0.23218248 | ER20: P/E (x) | ES20: =$ET$6/ES18 -> 25.921886 | ET20: =$ET$6/ET18 -> 24.56903 | EU20: =$ET$6/EU18 -> 24.134315 | EV20: =$ET$6/EV18 -> 22.947373 | EW20: =$ET$6/EW18 -> 21.873094 | EX20: =$ET$6/EX18 -> 21.02728 | EY20: =$ET$6/EY18 -> 17.373783 | EZ20: =$ET$6/EZ18 -> 15.378583 | FA20: =$ET$6/FA18 -> 13.57243 | FB20: =$ET$14/FB18 -> #DIV/0!
B21: Growth (%) | J21: =J20/I20-1 -> 0.18742265 | K21: =K20/J20-1 -> 0.065440866 | L21: =L20/K20-1 -> 0.026017785 | M21: =M20/L20-1 -> 0.26753415 | N21: =N20/M20-1 -> 0.13326301 | O21: =O20/N20-1 -> 0.067719405 | P21: =P20/O20-1 -> 0.036294677 | Q21: =Q20/P20-1 -> -0.25101084 | ... S21: =S20/R20-1 -> 0.1606144 | V21: =V20/N20-1 -> 0.076967198 | W21: =W20/O20-1 -> 0.068574424 | BK21: =BK20/BG20-1 -> 0.27278694 | BL21: =BL20/BH20-1 -> 0.12234144 | BM21: =BM20/BI20-1 -> 0.1444703 | BN21: =BN20/BJ20-1 -> 0.23773228 | BO21: =BO20/BK20-1 -> -0.027075034 | BP21: =BP20/BL20-1 -> 0.0050642886 | BQ21: =BQ20/BM20-1 -> 0.14344716 | BR21: =BR20/BN20-1 -> 0.03511954 | ... CC21: =CC20/BY20-1 -> 0.21354974 | CD21: =CD20/CA20-1 -> 0.24329905 | CE21: =CE20/CB20-1 -> 0.23578391 | CF21: =CF20/CC20-1 -> -0.034308543 | CG21: =CG20/CD20-1 -> -0.086864312 | CH21: =CH20/CE20-1 -> -0.051287756 | CI21: =CI20/CF20-1 -> 0.096212409 | CJ21: =CJ20/CG20-1 -> 0.058490727 | CK21: =CK20/CH20-1 -> -0.047789397 | ... CM21: =CM20/CJ20-1 -> -0.36757148 | CN21: =CM21*4 -> -1.4702859 | CO21: =Q21/CN21 -> 0.17072247 | CR21: Growth (%) | CY21: =CW21/CX21-1 -> #DIV/0! | CZ21: =CJ21 -> 0.058490727 | DA21: =CF21 -> -0.034308543 | DB21: =CZ21/DA21-1 -> -2.7048444 | DO21: Net income from other activities | DP21: =Data!BU485+Data!BU486 -> 23.710365 | DQ21: =Data!BY485+Data!BY486 -> 18.054932 | DR21: =DQ21/DP21-1 -> -0.23852157 | DS21: =Data!BX485+Data!BX486 -> 112.91308 | DT21: =DQ21/DS21-1 -> -0.84009885 | DX21: =CS53 -> 3111.6437 | DY21: =CT53 -> 3638.2226 | DZ21: =(DY21/DX21-1) -> 0.16922854 | EB21: =#REF! -> #REF! | EC21: =DY21/EB21 -> #REF! | EE21: =DX21 -> 3111.6437 | EF21: =M53 -> 6491.3435 | EG21: =EE21/EF21 -> 0.47935281 | EI21: =DE53 -> 1562.2197 | EJ21: =DF53 -> 1807.2854 | EK21: =(EJ21/EI21-1) -> 0.15687018 | EL21: =K53 -> 4423.7452 | EO21: =EB21/EF21-1 -> #REF! | EP21: =EI21/EF21 -> 0.240662 | ER21: P/B (x) | ES21: =$ET$6/ES19 -> 5.3111093 | ET21: =$ET$6/ET19 -> 5.3958597 | EU21: =$ET$6/EU19 -> 5.5599707 | EV21: =$ET$6/EV19 -> 5.4242143 | EW21: =$ET$6/EW19 -> 5.266664 | EX21: =$ET$6/EX19 -> 4.9802129 | EY21: =$ET$6/EY19 -> 4.2312012 | EZ21: =$ET$6/EZ19 -> 3.5797145 | FA21: =$ET$6/FA19 -> 3.0209879 | FB21: =$ET$14/FB19 -> #DIV/0!
B22: Administration /Net sales (%) | C22: =C20/C9 -> 0.065164534 | D22: =D20/D9 -> 0.068317348 | E22: =E20/E9 -> 0.06849616 | F22: =F20/F9 -> 0.06142803 | G22: =G20/G9 -> 0.069594138 | H22: =H20/H9 -> 0.080666685 | I22: =I20/I9 -> 0.15306966 | J22: =J20/J9 -> 0.15222646 | ... S22: =S20/S9 -> 0.095 | V22: =V20/V9 -> 0.128 | W22: =W20/W9 -> 0.114 | BC22: =BC20/BC9 -> #REF! | BD22: =BD20/BD9 -> #REF! | BE22: =BE20/BE9 -> #REF! | BF22: =BF20/BF9 -> #REF! | BG22: =BG20/BG9 -> 0.16216881 | BH22: =BH20/BH9 -> 0.15157585 | BI22: =BI20/BI9 -> 0.14925756 | BJ22: =BJ20/BJ9 -> 0.15213294 | ... CM22: =CM20/CM9 -> 0.096977799 | CN22: =CM22*4 -> 0.3879112 | CO22: =Q22/CN22 -> 0.24747932 | CR22: Administration /Net sales (%) | CS22: =CS20/CS9 -> 0.14015376 | CT22: =CT20/CT9 -> 0.1269587 | CW22: =CW20/CW9 -> 0.11599794 | CX22: =CX20/CX9 -> 0.12053007 | CY22: =CW22/CX22-1 -> -0.03760167 | CZ22: =CJ22 -> 0.11511216 | DA22: =CF22 -> 0.11234061 | DB22: =CZ22/DA22-1 -> 0.024670921 | DE22: =DE20/DE9 -> 0.15730034 | DF22: =DF20/DF9 -> 0.13632744 | DO22: Net income from Joint Venture | DP22: =CA45 -> 43.757074 | DQ22: =CE45 -> 74.454138 | DR22: =DQ22/DP22-1 -> 0.70153375 | DS22: =CD45 -> 58.146301 | DT22: =DQ22/DS22-1 -> 0.28046215 | DX22: =CS55 -> 2501.2112 | DY22: =CT55 -> 2975.623 | DZ22: =DY22/DX22-1 -> 0.18967283 | EB22: =#REF! -> #REF! | EC22: =DY22/EB22 -> #REF! | EE22: =DX22 -> 2501.2112 | EF22: =M55 -> 5310.1086 | EG22: =EE22/EF22 -> 0.47102826 | EI22: =DE55 -> 1262.541 | EJ22: =DF55 -> 1491.0485 | EK22: =EJ22/EI22-1 -> 0.18099016 | EL22: =K55 -> 3538.0077 | EO22: =EB22/EF22-1 -> #REF! | EP22: =EI22/EF22 -> 0.23776181 | ER22: EV/EBITDA (x) | ES22: =$EV$16/K29 -> 23.040403 | ET22: =$EV$16/L29 -> 19.895191 | EU22: =$EV$16/M29 -> 16.277838 | EV22: =$EV$16/N29 -> 13.078522 | EW22: =$EV$16/V29 -> 15.462803 | EX22: =$EV$16/W29 -> 13.678902 | EY22: =$EV$16/Q29 -> 11.275415 | EZ22: =$EV$16/R29 -> 10.400601 | FA22: =$EV$16/S29 -> 9.3655169 | FB22: =$EV$16/U29 -> #DIV/0!
B23: SG&A/Net sales (%) | I23: =(I17+I20)/I9 -> 0.24128687 | J23: =(J17+J20)/J9 -> 0.23686625 | K23: =(K17+K20)/K9 -> 0.24166379 | L23: =(L17+L20)/L9 -> 0.23044216 | M23: =(M17+M20)/M9 -> 0.23569263 | N23: =(N17+N20)/N9 -> 0.2255492 | O23: =(O17+O20)/O9 -> 0.2098688 | P23: =(P17+P20)/P9 -> 0.21239312 | ... S23: =(S17+S20)/S9 -> 0.174 | V23: =(V17+V20)/V9 -> 0.228 | W23: =(W17+W20)/W9 -> 0.22 | BG23: =(BG17+BG20)/BG9 -> 0.25114544 | BH23: =(BH17+BH20)/BH9 -> 0.23413661 | BI23: =(BI17+BI20)/BI9 -> 0.23334139 | BJ23: =(BJ17+BJ20)/BJ9 -> 0.24785411 | BK23: =(BK17+BK20)/BK9 -> 0.2592747 | BL23: =(BL17+BL20)/BL9 -> 0.21941901 | BM23: =(BM17+BM20)/BM9 -> 0.22382096 | BN23: =(BN17+BN20)/BN9 -> 0.25077177 | ... CM23: =(CM17+CM20)/CM9 -> 0.17729329 | CN23: =CM23*4 -> 0.70917318 | CO23: =Q23/CN23 -> 0.24817633 | CR23: SG&A/Net sales (%) | CS23: =(CS17+CS20)/CS9 -> 0.24208474 | CT23: =(CT17+CT20)/CT9 -> 0.22379694 | CW23: =(CW17+CW20)/CW9 -> 0.22673129 | CX23: =(CX17+CX20)/CX9 -> 0.22132581 | CY23: =CW23/CX23-1 -> 0.024423171 | CZ23: =CJ23 -> 0.22280099 | DA23: =CF23 -> 0.21651829 | DB23: =CZ23/DA23-1 -> 0.029016928 | DO23: Profit before tax | DP23: =Data!BU489 -> 2120.6436 | DQ23: =Data!BY489 -> 2533.5821 | DR23: =DQ23/DP23-1 -> 0.19472315 | DS23: =Data!BX489 -> 2435.0928 | DT23: =DQ23/DS23-1 -> 0.040445791 | DU23: =DQ23/V295 -> 0.23297306 | DX23: =DX21/DX5 -> 0.15694514 | DY23: =DY21/DY5 -> 0.1505529 | EB23: =EB21/EB5 -> #REF! | EE23: =DX23 -> 0.15694514 | EF23: =EF21/EF5 -> 0.14749859 | EI23: =EI21/EI5 -> 0.16055282 | EJ23: =EJ21/EJ5 -> 0.15471507 | EL23: =EL21/EL5 -> 0.14829654 | ER23: Dividend yield (%) | ES23: =K120/$ET$14*100 -> 1.9900498 | ET23: =L120/$ET$14*100 -> 1.9900498 | EU23: =M120/$ET$14*100 -> 1.9900498 | EV23: =N120/$ET$14*100 -> 1.9900498 | EW23: =V120/$ET$14*100 -> 1.8192614 | EX23: =W120/$ET$14*100 -> 2.0209272 | EY23: =Q120/$ET$14*100 -> 1.9900498 | EZ23: =R120/$ET$14*100 -> 1.9900498 | FA23: =S120/$ET$14*100 -> 1.9900498 | FB23: =U120/$ET$14*100 -> 0
B24: Operating Profit (EBIT) | C24: =C13-C17-C20 -> 2231.5756 | D24: =D13-D17-D20 -> 2336.0717 | E24: =E13-E17-E20 -> 2334.6688 | F24: =F13-F17-F20 -> 2935.1596 | G24: =G13-G17-G20 -> 3048.5221 | H24: =H13-H17-H20 -> 3166.6386 | I24: =I13-I17-I20 -> 3121.7573 | J24: =J13-J17-J20 -> 4146.8372 | ... S24: =S13-S17-S20 -> 12260.357 | V24: =V13-V17-V20 -> 6884.7028 | W24: =W13-W17-W20 -> 10266.834 | BC24: =BC13-BC17-BC20 -> #REF! | BD24: =BD13-BD17-BD20 -> #REF! | BE24: =BE13-BE17-BE20 -> #REF! | BF24: =BF13-BF17-BF20 -> #REF! | BG24: =BG13-BG17-BG20 -> 662.42644 | BH24: =BH13-BH17-BH20 -> 718.94731 | BI24: =BI13-BI17-BI20 -> 887.20785 | BJ24: =BJ13-BJ17-BJ20 -> 848.01828 | ... CM24: =CM13-CM17-CM20 -> 2032.2701 | CN24: =CM24*4 -> 8129.0803 | CO24: =Q24/CN24 -> 1.2003171 | CR24: Operating Profit (EBIT) | CS24: =BW24+BX24 -> 2996.3616 | CT24: =CA24+CB24 -> 3793.484 | CU24: =CK24+CJ24+CI24 -> 7867.1693 | CV24: =CG24+CF24+CE24 -> 7455.667 | CW24: =CI24+CJ24 -> 4912.1624 | CX24: =CE24+CF24 -> 4668.5322 | CY24: =CW24/CX24-1 -> 0.052185622 | CZ24: =CJ24 -> 2317.0375 | DA24: =CF24 -> 2350.4869 | DB24: =CZ24/DA24-1 -> -0.014230833 | DE24: =SUM(BW24) -> 1415.6566 | DF24: =SUM(CA24) -> 1873.515 | DG24: =DF24/DE24-1 -> 0.3234248 | DO24: Net profit | DP24: =Data!BU493 -> 1809.7995 | DQ24: =Data!BY493 -> 2160.2653 | DR24: =DQ24/DP24-1 -> 0.19364899 | DS24: =Data!BX493 -> 2051.2408 | DT24: =DQ24/DS24-1 -> 0.053150522 | EB24: =M94 -> 4419.7695 | EF24: =L94 -> 4341.5676 | EL24: =K94 -> 4114.9824 | EN24: =(EF24/EL24-1) -> 0.055063469 | EO24: =(EB24/EF24-1) -> 0.018012355
B25: Growth (%) | C25: =C24/B24-1 -> #VALUE! | D25: =D24/C24-1 -> 0.046826137 | E25: =E24/D24-1 -> -0.00060053955 | F25: =F24/E24-1 -> 0.257206 | G25: =G24/F24-1 -> 0.038622265 | H25: =H24/G24-1 -> 0.038745489 | I25: =I24/H24-1 -> -0.014173158 | J25: =J24/I24-1 -> 0.32836631 | ... S25: =S24/R24-1 -> 0.1349897 | V25: =V24/N24-1 -> -0.1853992 | W25: =W24/O24-1 -> -0.022982274 | BG25: =BG24/BC24-1 -> #REF! | BH25: =BH24/BD24-1 -> #REF! | BI25: =BI24/BE24-1 -> #REF! | BJ25: =BJ24/BF24-1 -> #REF! | BK25: =BK24/BG24-1 -> 0.223012 | BL25: =BL24/BH24-1 -> 0.50274329 | BM25: =BM24/BI24-1 -> 0.3442368 | BN25: =BN24/BJ24-1 -> 0.22015577 | ... CM25: =CM24/CI24-1 -> -0.21688931 | CN25: =CM25*4 -> -0.86755723 | CO25: =Q25/CN25 -> 0.13745889 | CR25: Growth (%) | CY25: =CW25/CX25-1 -> #DIV/0! | CZ25: =CJ25 -> -0.014230833 | DA25: =CF25 -> 0.22423168 | DB25: =CZ25/DA25-1 -> -1.0634649 | DO25: NPATMI | DP25: =Data!BU495 -> 1493.5626 | DQ25: =Data!BY495 -> 1798.0309 | DR25: =DQ25/DP25-1 -> 0.20385372 | DS25: =Data!BX495 -> 1728.4 | DT25: =DQ25/DS25-1 -> 0.040286336
B26: EBIT margin (%) | C26: =C24/C9 -> 0.090735466 | D26: =D24/D9 -> 0.086431896 | E26: =E24/E9 -> 0.07151764 | F26: =F24/F9 -> 0.077323047 | G26: =G24/G9 -> 0.077116338 | H26: =H24/H9 -> 0.074232107 | I26: =I24/I9 -> 0.13448004 | J26: =J24/J9 -> 0.14961371 | ... S26: =S24/S9 -> 0.16018917 | V26: =V24/V9 -> 0.12350437 | W26: =W24/W9 -> 0.15483499 | BC26: =BC24/BC9 -> #REF! | BD26: =BD24/BD9 -> #REF! | BE26: =BE24/BE9 -> #REF! | BF26: =BF24/BF9 -> #REF! | BG26: =BG24/BG9 -> 0.13943564 | BH26: =BH24/BH9 -> 0.13133226 | BI26: =BI24/BI9 -> 0.14698462 | BJ26: =BJ24/BJ9 -> 0.12197408 | ... CM26: =CM24/CM9 -> 0.16284219 | CN26: =CM26*4 -> 0.65136876 | CO26: =Q26/CN26 -> 0.261912 | CR26: EBIT margin (%) | CS26: =CS24/CS9 -> 0.15113055 | CT26: =CT24/CT9 -> 0.15697775 | CU26: =CK26+CJ26+CI26 -> 0.47273872 | CV26: =CG26+CF26+CE26 -> 0.49392181 | CW26: =CW24/CW9 -> 0.15029784 | CX26: =CX24/CX9 -> 0.15912835 | CY26: =CW26/CX26-1 -> -0.055492991 | CZ26: =CJ26 -> 0.13937308 | DA26: =CF26 -> 0.15417855 | DB26: =CZ26/DA26-1 -> -0.096028057 | DE26: =DE24/DE9 -> 0.1454902 | DF26: =DF24/DF9 -> 0.16038475 | DO26: Net margin | DP26: =DP25/DP6 -> 0.12785841 | DQ26: =DQ25/DQ6 -> 0.12758391 | DS26: =DS25/DS6 -> 0.11765496
CN27: =CM27*4 -> 0 | CO27: =Q27/CN27 -> #DIV/0! | CZ27: =CJ27 -> 0 | DA27: =CF27 -> 0 | DX27: =1/DX28 -> 2.239797
B28: Total depreciation expenses | C28: =Data!L396 -> 399.55979 | D28: =Data!M396 -> 442.98595 | E28: =Data!N396 -> 547.27365 | F28: =Data!O396 -> 732.88012 | G28: =Data!P396 -> 933.43968 | H28: =Data!Q396 -> 1039.4168 | I28: =Data!R396 -> 1164.692 | J28: =Data!S396 -> 1354.6135 | ... P28: =Data!Y396 -> 2899.52 | Q28: =BS!Q230 -> 2697.8567 | R28: =BS!R230 -> 2700.7971 | S28: =BS!S230 -> 2734.974 | V28: =BS!Y230 -> 2197.6753 | W28: =BS!Z230 -> 0 | BC28: 311.24389 | BD28: 314.28838 | BE28: 313.04175 | BF28: 361.29613 | BG28: 274.12091 | BH28: 286.03137 | BI28: 310.65005 | BJ28: 293.88968 | BK28: 318.4079 | BL28: 332.98602 | BM28: 346.54962 | BN28: 346.04622 | BO28: 361.7549 | BP28: 368.90914 | BQ28: 372.22176 | BR28: 388.29767 | BS28: 386.34369 | BT28: 386.72979 | BU28: 412.6777 | BV28: 458.15801 | BW28: 430.0352 | BX28: 447.95658 | BY28: 455.11219 | BZ28: 500.02983 | CA28: 510.017 | CB28: 510.017 | CC28: 511.017 | CD28: 513.017 | CE28: 514.017 | CF28: 515.017 | CG28: 516.017 | CH28: 517.017 | CI28: 518.017 | CJ28: 519.017 | CK28: 520.017 | CL28: 521.017 | CM28: 522.017 | CN28: =CM28*4 -> 2088.068 | CO28: =Q28/CN28 -> 1.2920349 | CR28: Total depreciation expenses | CS28: =BW28+BX28 -> 877.99177 | CT28: =CA28+CB28 -> 1020.034 | CU28: =CK28+CJ28+CI28 -> 1557.051 | CV28: =CG28+CF28+CE28 -> 1545.051 | CW28: =CI28+CJ28 -> 1037.034 | CX28: =CE28+CF28 -> 1029.034 | CY28: =CW28/CX28-1 -> 0.0077742815 | CZ28: =CJ28 -> 519.017 | DA28: =CF28 -> 515.017 | DB28: =CZ28/DA28-1 -> 0.0077667339 | DE28: =SUM(BW28) -> 430.0352 | DF28: =SUM(CA28) -> 510.017 | DG28: =DF28/DE28-1 -> 0.18598897 | DX28: =DX9/M17 -> 0.44646902 | DY28: =DY9*DX27 -> 5241.5015 | EB28: =EB22/EF22-1 -> #REF!
B29: EBITDA | C29: =C24+C28 -> 2631.1354 | D29: =D24+D28 -> 2779.0576 | E29: =E24+E28 -> 2881.9424 | F29: =F24+F28 -> 3668.0397 | G29: =G24+G28 -> 3981.9618 | H29: =H24+H28 -> 4206.0553 | I29: =I24+I28 -> 4286.4493 | J29: =J24+J28 -> 5501.4507 | ... S29: =S24+S28 -> 14995.331 | V29: =V24+V28 -> 9082.3781 | W29: =W24+W28 -> 10266.834 | BC29: =BC24+BC28 -> #REF! | BD29: =BD24+BD28 -> #REF! | BE29: =BE24+BE28 -> #REF! | BF29: =BF24+BF28 -> #REF! | BG29: =BG24+BG28 -> 936.54735 | BH29: =BH24+BH28 -> 1004.9787 | BI29: =BI24+BI28 -> 1197.8579 | BJ29: =BJ24+BJ28 -> 1141.908 | ... CM29: =CM24+CM28 -> 2554.2871 | CN29: =CM29*4 -> 10217.148 | CO29: =Q29/CN29 -> 1.2190614 | CR29: EBITDA | CS29: =BW29+BX29 -> 3874.3534 | CT29: =CA29+CB29 -> 4813.518 | CU29: =CK29+CJ29+CI29 -> 9424.2203 | CV29: =CG29+CF29+CE29 -> 9000.718 | CW29: =CI29+CJ29 -> 5949.1964 | CX29: =CE29+CF29 -> 5697.5662 | CY29: =CW29/CX29-1 -> 0.044164516 | CZ29: =CJ29 -> 2836.0545 | DA29: =CF29 -> 2865.5039 | DB29: =CZ29/DA29-1 -> -0.01027721 | DE29: =SUM(BW29) -> 1845.6918 | DF29: =SUM(CA29) -> 2383.532 | DG29: =DF29/DE29-1 -> 0.29140307 | DX29: =DX10/M20 -> 0.47529919 | DY29: =DY10*DX30 -> 6454.9894
B30: EBITDA margin (%) | C30: =C29/C9 -> 0.1069815 | D30: =D29/D9 -> 0.10282185 | E30: =E29/E9 -> 0.08828221 | F30: =F29/F9 -> 0.096629842 | G30: =G29/G9 -> 0.10072891 | H30: =H29/H9 -> 0.098598038 | I30: =I29/I9 -> 0.184653 | J30: =J29/J9 -> 0.1984868 | ... S30: =S29/S9 -> 0.1959233 | V30: =V29/V9 -> 0.16292836 | W30: =W29/W9 -> 0.15483499 | BC30: =BC29/BC9 -> #REF! | BD30: =BD29/BD9 -> #REF! | BE30: =BE29/BE9 -> #REF! | BF30: =BF29/BF9 -> #REF! | BG30: =BG29/BG9 -> 0.19713596 | BH30: =BH29/BH9 -> 0.18358247 | BI30: =BI29/BI9 -> 0.19845033 | BJ30: =BJ29/BJ9 -> 0.16424548 | ... CM30: =CM29/CM9 -> 0.20467048 | CN30: =CM30*4 -> 0.81868194 | CO30: =Q30/CN30 -> 0.26600204 | CR30: EBITDA margin (%) | CS30: =CS29/CS9 -> 0.19541471 | CT30: =CT29/CT9 -> 0.19918767 | CU30: =CK30+CJ30+CI30 -> 0.56644276 | CV30: =CG30+CF30+CE30 -> 0.59662554 | CW30: =CW29/CW9 -> 0.18202806 | CX30: =CX29/CX9 -> 0.19420329 | CY30: =CW30/CX30-1 -> -0.062693232 | CZ30: =CJ30 -> 0.17059269 | DA30: =CF30 -> 0.18796073 | DB30: =CZ30/DA30-1 -> -0.092402499 | DE30: =DE29/DE9 -> 0.18968588 | DF30: =DF29/DF9 -> 0.20404543 | DX30: =1/DX29 -> 2.1039379
CN31: =CM31*4 -> 0 | CO31: =Q31/CN31 -> #DIV/0! | CZ31: =CJ31 -> 0 | DA31: =CF31 -> 0 | DB31: =CZ31/DA31-1 -> #DIV/0!
B32: Income from financial activities | C32: =Data!L338 -> 636.51802 | D32: =Data!M338 -> 385.72136 | E32: =Data!N338 -> 367.64457 | F32: =Data!O338 -> 452.54669 | G32: =Data!P338 -> 574.75971 | H32: =Data!Q338 -> 1583.1 | I32: =Data!R338 -> 600.09331 | J32: =Data!S338 -> 650.49454 | ... P32: =Data!Y338 -> 2977.16 | Q32: =PL!K390 -> 1882.0366 | R32: =PL!L390 -> 2443.6028 | S32: =PL!M390 -> 2553.6584 | V32: =PL!I390 -> 1935.75 | W32: =PL!Q390 -> 0 | Z32: =M32/L32-1 -> 0.57264768 | BC32: =#REF! -> #REF! | BD32: =#REF! -> #REF! | BE32: =#REF! -> #REF! | BF32: =#REF! -> #REF! | BG32: =Data!BA478 -> 153.49256 | BH32: =Data!BB478 -> 112.69987 | BI32: =Data!BC478 -> 124.07638 | BJ32: =Data!BD478 -> 216.86628 | BK32: =Data!BE478 -> 153.5777 | BL32: =Data!BF478 -> 164.11506 | BM32: =Data!BG478 -> 165.79391 | BN32: =Data!BH478 -> 206.12338 | ... CM32: =Data!CG478 -> 415.86387 | CN32: =CM32*4 -> 1663.4555 | CO32: =Q32/CN32 -> 1.1314018 | CR32: Income from financial activities | CS32: =BW32+BX32 -> 921.9399 | CT32: =CA32+CB32 -> 1299.5207 | CU32: =CK32+CJ32+CI32 -> 2423.4354 | CV32: =CG32+CF32+CE32 -> 1353.0745 | CW32: =CI32+CJ32 -> 1810.3249 | CX32: =CE32+CF32 -> 1026.3855 | CY32: =CW32/CX32-1 -> 0.76378649 | CZ32: =CJ32 -> 1236.993 | DA32: =CF32 -> 569.29254 | DB32: =CZ32/DA32-1 -> 1.1728601 | DE32: =SUM(BW32) -> 415.7863 | DF32: =SUM(CA32) -> 676.47655 | DG32: =DF32/DE32-1 -> 0.62698132 | DO32: Business lines
B33: Interest income (%) | C33: =C32/(BS!C7+BS!C6) -> 0.21241749 | D33: =D32/(BS!D7+BS!D6) -> 0.091754835 | E33: =E32/(BS!E7+BS!E6) -> 0.063774462 | F33: =F32/(BS!F7+BS!F6) -> 0.072966086 | G33: =G32/(BS!G7+BS!G6) -> 0.060593835 | H33: =H32/(BS!H7+BS!H6) -> 0.2014095 | I33: =I32/(BS!I7+BS!I6) -> 0.063205301 | J33: =J32/(BS!J7+BS!J6) -> 0.064010142 | ... S33: =S32/(BS!S7+BS!S6) -> 0.048945915 | V33: =V32/(BS!W7+BS!W6) -> 0.07938815 | W33: =W32/(BS!X7+BS!X6) -> #DIV/0! | BW33: =83.763/BW9 -> 0.0086085113 | CA33: =74.302/CA9 -> 0.0063607217 | CB33: =74.302/CB9 -> 0.0059516046 | CC33: =74.302/CC9 -> 0.00539917 | CD33: =74.302/CD9 -> 0.0050578565 | CE33: =74.302/CE9 -> 0.0052722896 | CF33: =74.302/CF9 -> 0.0048737879 | CG33: =74.302/CG9 -> 0.0046722526 | CH33: =74.302/CH9 -> 0.0042198296 | ... CM33: =74.302/CM9 -> 0.0059536872 | CN33: =CM33*4 -> 0.023814749 | CO33: =Q33/CN33 -> 1.6664495 | CR33: Interest income (%) | DB33: =CZ33/DA33-1 -> #DIV/0! | DO33: (VNDbn) | DP33: 1Q23 | DQ33: 1Q24 | DR33: YoY | DS33: 4Q23 | DT33: QoQ
B34: Expenses of financial activities | C34: =-Data!L339 -> 549.88837 | D34: =-Data!M339 -> 270.55557 | E34: =-Data!N339 -> 354.07632 | F34: =-Data!O339 -> 620.41157 | G34: =-Data!P339 -> 694.21396 | H34: =-Data!Q339 -> 600.87183 | I34: =-Data!R339 -> 361.04657 | J34: =-Data!S339 -> 592.38605 | ... P34: =-Data!Y339 -> 1672.05 | Q34: =PL!K420 -> 1324.2606 | R34: =PL!L420 -> 1439.2749 | S34: =PL!M420 -> 1524.2064 | V34: =PL!I420 -> 1811.55 | W34: =PL!Q420 -> 0 | Z34: =M34/L34-1 -> 0.47473188 | BC34: =-#REF! -> #REF! | BD34: =-#REF! -> #REF! | BE34: =-#REF! -> #REF! | BF34: =-#REF! -> #REF! | BG34: =-Data!BA479 -> 142.2954 | BH34: =-Data!BB479 -> 70.016555 | BI34: =-Data!BC479 -> 66.603047 | BJ34: =-Data!BD479 -> 89.173349 | BK34: =-Data!BE479 -> 121.30312 | BL34: =-Data!BF479 -> 204.22533 | BM34: =-Data!BG479 -> 130.42236 | BN34: =-Data!BH479 -> 171.72022 | ... CM34: =-Data!CG479 -> 367.21138 | CN34: =CM34*4 -> 1468.8455 | CO34: =Q34/CN34 -> 0.90156557 | CR34: Expenses of financial activities | CS34: =BW34+BX34 -> 604.41387 | CT34: =CA34+CB34 -> 784.31379 | CU34: =CK34+CJ34+CI34 -> 1195.2851 | CV34: =CG34+CF34+CE34 -> 980.17199 | CW34: =CI34+CJ34 -> 842.70998 | CX34: =CE34+CF34 -> 671.99318 | CY34: =CW34/CX34-1 -> 0.25404544 | CZ34: =CJ34 -> 531.36622 | DA34: =CF34 -> 337.92791 | DB34: =CZ34/DA34-1 -> 0.57242478 | DE34: =SUM(BW34) -> 267.57253 | DF34: =SUM(CA34) -> 496.81534 | DG34: =DF34/DE34-1 -> 0.8567502 | DJ34: =0.2*0.3 -> 0.06 | DO34: Net revenue | DP34: =Data!BU503 -> 0 | DQ34: =Data!BY503 -> 0 | DS34: =Data!BX503 -> 0 | DT34: =DQ34/DS34-1 -> #DIV/0!
B35: Interest expense | C35: =-Data!L340 -> 228.65864 | D35: =-Data!M340 -> 132.49117 | E35: =-Data!N340 -> 166.16529 | F35: =-Data!O340 -> 262.50233 | G35: =-Data!P340 -> 374.18608 | H35: =-Data!Q340 -> 368.54568 | I35: =-Data!R340 -> 238.34443 | J35: =-Data!S340 -> 358.98754 | ... P35: =-Data!Y340 -> 809.76 | Q35: =PL!K414 -> 923.89832 | R35: =PL!L414 -> 977.65976 | S35: =PL!M414 -> 988.44918 | V35: =PL!I414 -> 551.64 | W35: =PL!Q414 -> 0 | BC35: =-#REF! -> #REF! | BD35: =-#REF! -> #REF! | BE35: =-#REF! -> #REF! | BF35: =-#REF! -> #REF! | BG35: =-Data!BA480 -> 46.408615 | BH35: =-Data!BB480 -> 55.088753 | BI35: =-Data!BC480 -> 62.035658 | BJ35: =-Data!BD480 -> 74.811405 | BK35: =-Data!BE480 -> 72.702858 | BL35: =-Data!BF480 -> 72.389485 | BM35: =-Data!BG480 -> 100.50592 | BN35: =-Data!BH480 -> 120.74686 | ... CM35: =-Data!CG480 -> 179.46121 | CN35: =CM35*4 -> 717.84483 | CO35: =Q35/CN35 -> 1.2870446 | CR35: Interest expense | CS35: =BW35+BX35 -> 322.59994 | CT35: =CA35+CB35 -> 360.34967 | CU35: =CK35+CJ35+CI35 -> 602.73375 | CV35: =CG35+CF35+CE35 -> 416.78509 | CW35: =CI35+CJ35 -> 369.15083 | CX35: =CE35+CF35 -> 287.95914 | CY35: =CW35/CX35-1 -> 0.2819556 | CZ35: =CJ35 -> 216.7613 | DA35: =CF35 -> 150.12542 | DB35: =CZ35/DA35-1 -> 0.44386802 | DE35: =SUM(BW35) -> 145.81974 | DF35: =SUM(CA35) -> 147.98567 | DG35: =DF35/DE35-1 -> 0.014853456 | DO35: Technology
B36: Interest expenses (%) | D36: =D35/AVERAGE(BS!C58:D58) -> 0.037302915 | E36: =E35/AVERAGE(BS!D58:E58) -> 0.029975145 | F36: =F35/AVERAGE(BS!E58:F58) -> 0.033502716 | G36: =G35/AVERAGE(BS!F58:G58) -> 0.039923736 | H36: =H35/AVERAGE(BS!G58:H58) -> 0.050411258 | I36: =I35/AVERAGE(BS!H58:I58) -> 0.040925014 | J36: =J35/AVERAGE(BS!I58:J58) -> 0.04841674 | K36: =K35/AVERAGE(BS!J58:K58) -> 0.037404874 | ... P36: =P35/AVERAGE(BS!O58:P58) -> 0.04496063 | Q36: =Q35/AVERAGE(BS!Q58:Q58) -> 0.043 | R36: =R35/AVERAGE(BS!Q58:R58) -> 0.045 | S36: =S35/AVERAGE(BS!R58:S58) -> 0.045 | V36: =V35/AVERAGE(BS!V58:W58) -> 0.037910929 | W36: =W35/AVERAGE(BS!W58:X58) -> 0 | BW36: =BW35/12382.1 -> 0.011776657 | CA36: =CA35/12356.245 -> 0.011976589 | CN36: =CM36*4 -> 0 | CO36: =Q36/CN36 -> #DIV/0! | CR36: Interest expenses (%) | DO36: Global IT | DP36: =SUM(DP37:DP40) -> 5435 | DQ36: =SUM(DQ37:DQ40) -> 7000 | DR36: =DQ36/DP36-1 -> 0.28794848
B37: FX loss | V37: =V38*V11 -> #REF! | CN37: =CM37*4 -> 0 | CO37: =Q37/CN37 -> #DIV/0! | CR37: FX loss | DE37: =SUM(BS37:BT37) -> 0 | DF37: =SUM(BW37:BX37) -> 0 | DG37: =DF37/DE37-1 -> #DIV/0! | DO37: Japan IT | DP37: 2019 | DQ37: 2695 | DR37: =DQ37/DP37-1 -> 0.33481922
B38: % of COGS | V38: =#REF! -> #REF! | BC38: =BC37/BC9 -> #REF! | BD38: =BD37/BD9 -> #REF! | BE38: =BE37/BE9 -> #REF! | BF38: =BF37/BF9 -> #REF! | BG38: =BG37/BG9 -> 0 | BH38: =BH37/BH9 -> 0 | BI38: =BI37/BI9 -> 0 | BJ38: =BJ37/BJ9 -> 0 | ... BZ38: =BZ37/BZ9 -> 0 | CN38: =CM38*4 -> 0 | CO38: =Q38/CN38 -> #DIV/0! | CR38: % of COGS | DO38: US IT | DP38: 1606 | DQ38: 1858 | DR38: =DQ38/DP38-1 -> 0.15691158
A39: LN từ thu nhập tài chính | B39: Profit/Loss from Financial activities | C39: =C32-C34 -> 86.629644 | D39: =D32-D34 -> 115.16579 | E39: =E32-E34 -> 13.568243 | F39: =F32-F34 -> -167.86488 | G39: =G32-G34 -> -119.45425 | H39: =H32-H34 -> 982.22814 | I39: =I32-I34 -> 239.04674 | J39: =J32-J34 -> 58.108491 | ... S39: =S32-S34 -> 1029.452 | V39: =V32-V34 -> 124.2 | W39: =W32-W34 -> 0 | BC39: =BC32-BC34 -> #REF! | BD39: =BD32-BD34 -> #REF! | BE39: =BE32-BE34 -> #REF! | BF39: =BF32-BF34 -> #REF! | BG39: =BG32-BG34 -> 11.197162 | BH39: =BH32-BH34 -> 42.683315 | BI39: =BI32-BI34 -> 57.473337 | BJ39: =BJ32-BJ34 -> 127.69293 | ... CM39: =CM32-CM34 -> 48.652484 | CN39: =CM39*4 -> 194.60994 | CO39: =Q39/CN39 -> 2.8661229 | CR39: Profit/Loss from Financial activities | CS39: =BW39+BX39 -> 317.52603 | CT39: =CA39+CB39 -> 515.20687 | CU39: =CK39+CJ39+CI39 -> 1228.1503 | CV39: =CG39+CF39+CE39 -> 372.90254 | CW39: =CI39+CJ39 -> 967.61494 | CX39: =CE39+CF39 -> 354.39234 | CY39: =CW39/CX39-1 -> 1.7303494 | CZ39: =CJ39 -> 705.62681 | DA39: =CF39 -> 231.36464 | DB39: =CZ39/DA39-1 -> 2.0498473 | DE39: =SUM(BW39) -> 148.21378 | DF39: =SUM(CA39) -> 179.66121 | DG39: =DF39/DE39-1 -> 0.21217616 | DO39: EU IT | DP39: 384 | DQ39: 552 | DR39: =DQ39/DP39-1 -> 0.4375
B40: margin (%) | I40: =I39/I9 -> 0.01029773 | J40: =J39/J9 -> 0.0020964958 | K40: =K39/K9 -> 0.00917625 | L40: =L39/L47 -> 0.019977563 | M40: =M39/M47 -> 0.04060595 | N40: =N39/N47 -> 0.067127047 | O40: =O39/O47 -> 0.011219857 | P40: =P39/P47 -> 0.099370932 | Q40: =Q39/Q47 -> 0.042027084 | R40: =R39/R47 -> 0.066881993 | S40: =S39/S47 -> 0.060503585 | W40: =W39/W9 -> 0 | BG40: =BG39/BG47 -> 0.014341027 | BH40: =BH39/BH47 -> 0.047095493 | BI40: =BI39/BI47 -> 0.054701246 | BJ40: =BJ39/BJ47 -> 0.11457079 | BK40: =BK39/BK47 -> 0.033606512 | BL40: =BL39/BL47 -> -0.034031304 | BM40: =BM39/BM47 -> 0.025847498 | BN40: =BN39/BN47 -> 0.02973315 | ... CM40: =CM39/CM47 -> 0.017352064 | CN40: =CM40*4 -> 0.069408255 | CO40: =Q40/CN40 -> 0.60550556 | CR40: margin (%) | CW40: =CW39/CW9 -> 0.029606195 | CX40: =CX39/CX9 -> 0.012079572 | CZ40: =CZ39/CZ9 -> 0.042444451 | DA40: =DA39/DA9 -> 0.015176202 | DB40: =CZ40/DA40-1 -> 1.7967768 | DO40: APAC IT | DP40: 1426 | DQ40: 1895 | DR40: =DQ40/DP40-1 -> 0.32889201
CN41: =CM41*4 -> 0 | CO41: =Q41/CN41 -> #DIV/0! | CZ41: =CJ41 -> 0 | DA41: =CF41 -> 0 | DB41: =CZ41/DA41-1 -> #DIV/0! | DO41: Domestic IT | DP41: 1407 | DQ41: 1472 | DR41: =DQ41/DP41-1 -> 0.046197584
B42: Other income | C42: =Data!L345 -> 167.74404 | D42: =Data!M345 -> 204.95931 | E42: =Data!N345 -> 166.75564 | F42: =Data!O345 -> 146.79607 | G42: =Data!P345 -> 99.83984 | H42: =Data!Q345 -> 101.84719 | I42: =Data!R345 -> 60.448926 | J42: =Data!S345 -> 112.68356 | ... P42: =Data!Y345 -> 142.89 | Q42: =Q9*Assumptions!Q50 -> 171.58382 | R42: =R9*Assumptions!R50 -> 197.83506 | S42: =S9*Assumptions!S50 -> 229.61022 | V42: =V9*Assumptions!AG50 -> 167.23383 | W42: =W9*Assumptions!P50 -> 198.92469 | BC42: =#REF! -> #REF! | BD42: =#REF! -> #REF! | BE42: =#REF! -> #REF! | BF42: =#REF! -> #REF! | BG42: =Data!BA485 -> 33.761809 | BH42: =Data!BB485 -> 27.692098 | BI42: =Data!BC485 -> 13.190925 | BJ42: =Data!BD485 -> -14.195906 | BK42: =Data!BE485 -> 34.065048 | BL42: =Data!BF485 -> 9.543484 | BM42: =Data!BG485 -> 34.369795 | BN42: =Data!BH485 -> 82.751354 | ... CD42: =Data!BX485 -> 48.394509 | CE42: =Data!BY487 -> 18.054932 | CF42: =Data!BZ487 -> 28.515588 | CG42: =Data!CA487 -> -39.605371 | CH42: =Data!CB485 -> 37.62 | CI42: =Data!CC485 -> 30.850132 | CJ42: =Data!CD485 -> 28.751046 | CK42: =Data!CE485 -> 34.8394 | CL42: =Data!CF485 -> 40.089603 | CM42: =Data!CG485 -> 61.674012 | CN42: =CM42*4 -> 246.69605 | CO42: =Q42/CN42 -> 0.69552723 | CR42: Other income | CS42: =BW42+BX42 -> 71.087057 | CT42: =CA42+CB42 -> 89.858371 | CU42: =CK42+CJ42+CI42 -> 94.440578 | CV42: =CG42+CF42+CE42 -> 6.9651486 | CW42: =CI42+CJ42 -> 59.601178 | CX42: =CE42+CF42 -> 46.57052 | CY42: =CW42/CX42-1 -> 0.27980488 | CZ42: =CJ42 -> 28.751046 | DA42: =CF42 -> 28.515588 | DB42: =CZ42/DA42-1 -> 0.0082571738 | DO42: Telecommunications
B43: Other expenses | C43: =-Data!L346 -> 112.05054 | D43: =-Data!M346 -> 162.08767 | E43: =-Data!N346 -> 96.627048 | F43: =-Data!O346 -> 97.416624 | G43: =-Data!P346 -> 50.14237 | H43: =-Data!Q346 -> 66.681481 | I43: =-Data!R346 -> 2.6775264 | J43: =-Data!S346 -> 58.026215 | ... P43: =-Data!Y346 -> 50.94 | Q43: =Q11*Assumptions!Q51 -> 74.741764 | R43: =R11*Assumptions!R51 -> 87.336824 | S43: =S11*Assumptions!S51 -> 101.91798 | V43: =V11*Assumptions!AG51 -> 91.448742 | W43: =W11*Assumptions!P51 -> 82.90717 | BC43: =-#REF! -> #REF! | BD43: =-#REF! -> #REF! | BE43: =-#REF! -> #REF! | BF43: =-#REF! -> #REF! | BG43: =-Data!BA486 -> 24.369541 | BH43: =-Data!BB486 -> 0.92987601 | BI43: =-Data!BC486 -> 19.815204 | BJ43: =-Data!BD486 -> -42.294318 | BK43: =-Data!BE486 -> 10.932348 | BL43: =-Data!BF486 -> -4.5496768 | BM43: =-Data!BG486 -> 13.30144 | BN43: =-Data!BH486 -> 61.262097 | ... CD43: =-Data!BX486 -> -64.518574 | CE43: =-Data!BY485 -> -44.782908 | CF43: =-Data!BZ485 -> -28.515588 | CG43: =-Data!CA485 -> 39.605371 | CH43: =Data!CB486 -> 68.48 | CI43: =Data!CC486 -> 39.212522 | CJ43: =Data!CD486 -> -17.127044 | CK43: =Data!CE486 -> -6.4765343 | CL43: =Data!CF486 -> -18.969734 | CM43: =Data!CG486 -> -5.5935575 | CN43: =CM43*4 -> -22.37423 | CO43: =Q43/CN43 -> -3.340529 | CR43: Other expenses | CS43: =BW43+BX43 -> 43.065279 | CT43: =CA43+CB43 -> 37.781744 | CU43: =CK43+CJ43+CI43 -> 15.608943 | CV43: =CG43+CF43+CE43 -> -33.693125 | CW43: =CI43+CJ43 -> 22.085478 | CX43: =CE43+CF43 -> -73.298496 | CY43: =CW43/CX43-1 -> -1.3013087 | CZ43: =CJ43 -> -17.127044 | DA43: =CF43 -> -28.515588 | DB43: =CZ43/DA43-1 -> -0.3993796 | DO43: Broadband | DP43: 3695 | DQ43: 3885 | DR43: =DQ43/DP43-1 -> 0.051420839
B44: Profit/Loss from Other activities | C44: =C42-C43 -> 55.693497 | D44: =D42-D43 -> 42.871639 | E44: =E42-E43 -> 70.12859 | F44: =F42-F43 -> 49.379443 | G44: =G42-G43 -> 49.69747 | H44: =H42-H43 -> 35.165712 | I44: =I42-I43 -> 57.7714 | J44: =J42-J43 -> 54.657348 | ... S44: =S42-S43 -> 127.69224 | V44: =V42-V43 -> 75.785088 | W44: =W42-W43 -> 116.01752 | BC44: =BC42-BC43 -> #REF! | BD44: =BD42-BD43 -> #REF! | BE44: =BE42-BE43 -> #REF! | BF44: =BF42-BF43 -> #REF! | BG44: =Data!BA487 -> 9.3922677 | BH44: =Data!BB487 -> 26.762222 | BI44: =Data!BC487 -> -6.6242784 | BJ44: =Data!BD487 -> 28.098412 | BK44: =Data!BE487 -> 23.1327 | BL44: =Data!BF487 -> 14.093161 | BM44: =Data!BG487 -> 21.068355 | BN44: =Data!BH487 -> 21.489258 | ... CM44: =Data!CG487 -> 56.080455 | CN44: =CM44*4 -> 224.32182 | CO44: =Q44/CN44 -> 0.43171037 | CR44: Profit/Loss from Other activities | CS44: =BW44+BX44 -> 28.021778 | CT44: =CA44+CB44 -> 52.076627 | CU44: =CK44+CJ44+CI44 -> 70.837 | CV44: =CG44+CF44+CE44 -> 6.9651486 | CW44: =CI44+CJ44 -> 42.474134 | CX44: =CE44+CF44 -> 46.57052 | CY44: =CW44/CX44-1 -> -0.08796091 | CZ44: =CJ44 -> 11.624002 | DA44: =CF44 -> 28.515588 | DB44: =CZ44/DA44-1 -> -0.59236322 | DE44: =SUM(BW44) -> 6.3472676 | DF44: =SUM(CA44) -> 23.710365 | DG44: =DF44/DE44-1 -> 2.7355231 | DO44: Digital Media | DP44: 95 | DQ44: 127 | DR44: =DQ44/DP44-1 -> 0.33684211
A45: LN từ công ty con | B45: Profit from Joint venture partners/ Affiliates | C45: =Data!L341+Data!L348 -> 32.661858 | D45: =Data!M341+Data!M348 -> 21.520886 | E45: =Data!N341+Data!N348 -> 40.858599 | F45: =Data!O341+Data!O348 -> 34.474687 | G45: =Data!P341+Data!P348 -> 35.133362 | H45: =Data!Q341+Data!Q348 -> 71.085355 | I45: =Data!R341+Data!R348 -> 439.02711 | J45: =Data!S341+Data!S348 -> 404.92747 | ... P45: =Data!Y341+Data!Y348 -> 658.02 | Q45: =Q9*Scenarios!H43 -> 2859.7303 | R45: =R9*Scenarios!I43 -> 3099.4159 | S45: =S9*Scenarios!J43 -> 3597.2268 | V45: =AVERAGE(K45:N45)/3 -> 127.08361 | W45: =W9*Scenarios!G43 -> 663.0823 | BC45: =#REF!+#REF! -> #REF! | BD45: =#REF!+#REF! -> #REF! | BE45: =#REF!+#REF! -> #REF! | BF45: =#REF!+#REF! -> #REF! | BG45: =Data!BA481+Data!BA488 -> 97.762342 | BH45: =Data!BB481+Data!BB488 -> 117.92138 | BI45: =Data!BC481+Data!BC488 -> 112.62002 | BJ45: =Data!BD481+Data!BD488 -> 110.72338 | BK45: =Data!BE481+Data!BE488 -> 94.80396 | BL45: =Data!BF481+Data!BF488 -> 124.25263 | BM45: =Data!BG481+Data!BG488 -> 119.41368 | BN45: =Data!BH481+Data!BH488 -> 66.457196 | ... CM45: =Data!CG481+Data!CG488 -> 666.84127 | CN45: =CM45*4 -> 2667.3651 | CO45: =Q45/CN45 -> 1.0721181 | CP45: =CM45/CL45-1 -> 1.3501334 | CR45: Profit from Joint venture partners/ Affiliates | CS45: =BW45+BX45 -> 294.98303 | CT45: =CA45+CB45 -> -21.991234 | CU45: =CK45+CJ45+CI45 -> 374.2787 | CV45: =CG45+CF45+CE45 -> 275.63651 | CW45: =CI45+CJ45 -> 243.44527 | CX45: =CE45+CF45 -> 133.05557 | CY45: =CW45/CX45-1 -> 0.82965118 | CZ45: =CJ45 -> 106.71494 | DA45: =CF45 -> 58.601427 | DB45: =CZ45/DA45-1 -> 0.82102963 | DO45: Investment, education & others | DP45: 1048 | DQ45: 1609 | DR45: =DQ45/DP45-1 -> 0.53530534
B46: margin (%) | D46: =D45/D47 -> 0.0085548695 | E46: =E45/E47 -> 0.016614426 | F46: =F45/F47 -> 0.012091507 | G46: =G45/G47 -> 0.011657115 | H46: =H45/H47 -> 0.016705849 | I46: =I45/I47 -> 0.11380828 | J46: =J45/J47 -> 0.086809908 | K46: =K45/K47 -> 0.059313412 | ... S46: =S45/S47 -> 0.21141841 | U46: =Q45/P45-1 -> 3.3459626 | V46: =V45/N45-1 -> 2.0010056 | W46: =W45/O45-1 -> 0.68925254 | CN46: =CM46*4 -> 0 | CO46: =Q46/CN46 -> #DIV/0! | CR46: Growth (%) | DO46: Profit Before Tax | DP46: =Data!BU515 -> 0 | DQ46: =Data!BY515 -> 0
B47: Profit before tax | C47: =C24+C39+C44+C45 -> 2406.5606 | D47: =D24+D39+D44+D45 -> 2515.63 | E47: =E24+E39+E44+E45 -> 2459.2242 | F47: =F24+F39+F44+F45 -> 2851.1488 | G47: =G24+G39+G44+G45 -> 3013.8987 | H47: =H24+H39+H44+H45 -> 4255.1178 | I47: =I24+I39+I44+I45 -> 3857.6026 | J47: =J24+J39+J44+J45 -> 4664.5305 | ... S47: =S24+S39+S44+S45 -> 17014.728 | V47: =V24+V39+V44+V45 -> 7211.7715 | W47: =W24+W39+W44+W45 -> 11045.934 | BC47: =BC24+BC39+BC44+BC45 -> #REF! | BD47: =BD24+BD39+BD44+BD45 -> #REF! | BE47: =BE24+BE39+BE44+BE45 -> #REF! | BF47: =BF24+BF39+BF44+BF45 -> #REF! | BG47: =BG24+BG39+BG44+BG45 -> 780.77821 | BH47: =BH24+BH39+BH44+BH45 -> 906.31422 | BI47: =BI24+BI39+BI44+BI45 -> 1050.6769 | BJ47: =BJ24+BJ39+BJ44+BJ45 -> 1114.533 | ... CM47: =CM24+CM39+CM44+CM45 -> 2803.8443 | CN47: =CM47*4 -> 11215.377 | CO47: =Q47/CN47 -> 1.1833594 | CR47: Profit before tax | CS47: =BW47+BX47 -> 3636.8925 | CT47: =CA47+CB47 -> 4338.7763 | CU47: =CK47+CJ47+CI47 -> 9540.4354 | CV47: =CG47+CF47+CE47 -> 8111.1712 | CW47: =CI47+CJ47 -> 6165.6968 | CX47: =CE47+CF47 -> 5202.5506 | CY47: =CW47/CX47-1 -> 0.18512961 | CZ47: =CJ47 -> 3141.0033 | DA47: =CF47 -> 2668.9686 | DB47: =CZ47/DA47-1 -> 0.17686035 | DE47: =SUM(BW47) -> 1779.0478 | DF47: =SUM(CA47) -> 2120.6436 | DG47: =DF47/DE47-1 -> 0.19201046 | DH47: 7618 | DJ47: =DF47/DI47 -> #DIV/0! | DO47: Technology
B48: Growth (%) | C48: =C47/B47-1 -> #VALUE! | D48: =D47/C47-1 -> 0.045321685 | E48: =E47/D47-1 -> -0.022422133 | F48: =F47/E47-1 -> 0.15936921 | G48: =G47/F47-1 -> 0.057082197 | H48: =H47/G47-1 -> 0.41183173 | I48: `` | J48: =J47/I47-1 -> 0.20917861 | K48: =K47/J47-1 -> 0.12840009 | L48: =L47/K47-1 -> 0.20400089 | M48: =M47/L47-1 -> 0.20909474 | N48: =N47/M47-1 -> 0.20107886 | O48: =O47/N47-1 -> 0.20283089 | P48: =P47/O47-1 -> 0.18646101 | Q48: =Q47/P47-1 -> 0.010515097 | ... S48: =S47/R47-1 -> 0.13307511 | U48: =Q47/P47-1 -> 0.010515097 | V48: =V47/N47-1 -> -0.21636784 | W48: =W47/O47-1 -> -0.0021433115 | CN48: =CM48*4 -> 0 | CO48: =Q48/CN48 -> #DIV/0! | CR48: Growth (%) | DB48: =CZ48/DA48-1 -> #DIV/0! | DO48: Global IT | DP48: 889 | DQ48: 1115 | DR48: =DQ48/DP48-1 -> 0.25421822
B49: PBT margin (%) | C49: =C47/C9 -> 0.097850325 | D49: =D47/D9 -> 0.093075342 | E49: =E47/E9 -> 0.075333132 | F49: =F47/F9 -> 0.075109891 | G49: =G47/G9 -> 0.076240493 | H49: =H47/H9 -> 0.099748156 | I49: =I47/I9 -> 0.16617901 | J49: =J47/J9 -> 0.16829156 | ... S49: =S47/S9 -> 0.22230798 | V49: =V47/V9 -> 0.12937164 | W49: =W47/W9 -> 0.16658466 | BZ49: =BZ47/BZ9 -> 0.15250449 | CA49: =CA47/CA9 -> 0.18154052 | CB49: =CB47/CB9 -> 0.17767285 | CC49: =CC47/CC9 -> 0.17651471 | CD49: =CD47/CD9 -> 0.16576068 | CE49: =CE47/CE9 -> 0.17977683 | CF49: =CF47/CF9 -> 0.17506913 | CG49: =CG47/CG9 -> 0.18289966 | ... CM49: =CM47/CM9 -> 0.22466706 | CN49: =CM49*4 -> 0.89866824 | CO49: =Q49/CN49 -> 0.2582118 | CR49: PBT margin (%) | CW49: =CW47/CW9 -> 0.18865234 | CX49: =CX47/CX9 -> 0.17733053 | CY49: =CW49/CX49-1 -> 0.063845771 | CZ49: =CZ47/CZ9 -> 0.18893579 | DA49: =DA47/DA9 -> 0.17506913 | DB49: =CZ49/DA49-1 -> 0.079206747 | DO49: Domestic IT | DP49: 18 | DQ49: 41 | DR49: =DQ49/DP49-1 -> 1.2777778 | DT49: =DQ49/DP49 -> 2.2777778
B50: Enterprises effective income tax | C50: =-Data!L352 -> 421.07378 | D50: =-Data!M352 -> 450.317 | E50: =-Data!N352 -> 380.0994 | F50: =-Data!O352 -> 413.06406 | G50: =-Data!P352 -> 438.20782 | H50: =-Data!Q352 -> 727.00386 | I50: =-Data!R352 -> 623.60541 | J50: =-Data!S352 -> 752.81834 | ... P50: =-Data!Y352 -> 1813.35 | Q50: =Q47*15% -> 1990.7734 | R50: =R47*15% -> 2252.4625 | S50: =S47*15% -> 2552.2092 | W50: =W47*Assumptions!P44 -> 1656.8901 | BC50: =-#REF! -> #REF! | BD50: =-#REF! -> #REF! | BE50: =-#REF! -> #REF! | BF50: =-#REF! -> #REF! | BG50: =-Data!BA491-Data!BA492 -> 149.95685 | BH50: =-Data!BB491-Data!BB492 -> 147.49996 | BI50: =-Data!BC491-Data!BC492 -> 160.62767 | BJ50: =-Data!BD491-Data!BD492 -> 190.11546 | BK50: =-Data!BE491-Data!BE492 -> 164.74281 | BL50: =-Data!BF491-Data!BF492 -> 189.70409 | BM50: =-Data!BG491-Data!BG492 -> 209.92644 | BN50: =-Data!BH491-Data!BH492 -> 179.27374 | ... CM50: =-Data!CG491-Data!CG492 -> 199.4303 | CN50: =CM50*4 -> 797.7212 | CO50: =Q50/CN50 -> 2.4955753 | CR50: Enterprises effective income tax | CS50: =BW50+BX50 -> 525.24876 | CT50: =CA50+CB50 -> 700.55366 | CU50: =CK50+CJ50+CI50 -> 1186.7293 | CV50: =CG50+CF50+CE50 -> 1184.5952 | CW50: =CI50+CJ50 -> 829.89721 | CX50: =CE50+CF50 -> 754.57218 | CY50: =CW50/CX50-1 -> 0.09982482 | CZ50: =CJ50 -> 400.76118 | DA50: =CF50 -> 381.25542 | DB50: =CZ50/DA50-1 -> 0.05116194 | DE50: =SUM(BW50) -> 216.82813 | DF50: =SUM(CA50) -> 313.35824 | DO50: Telecommunications
B51: Effective tax rate (%) | C51: =C50/C47 -> 0.17496911 | D51: =D50/D47 -> 0.17900764 | E51: =E50/E47 -> 0.1545607 | F51: =F50/F47 -> 0.14487636 | G51: =G50/G47 -> 0.14539567 | H51: =H50/H47 -> 0.17085399 | I51: =I50/I47 -> 0.16165621 | J51: =J50/J47 -> 0.16139209 | ... S51: =S50/S47 -> 0.15 | V51: =V50/V47 -> 0 | W51: =W50/W47 -> 0.15 | BC51: =BC50/BC47 -> #REF! | BD51: =BD50/BD47 -> #REF! | BE51: =BE50/BE47 -> #REF! | BF51: =BF50/BF47 -> #REF! | BG51: =BG50/BG47 -> 0.19206075 | BH51: =BH50/BH47 -> 0.16274704 | BI51: =BI50/BI47 -> 0.15288017 | BJ51: =BJ50/BJ47 -> 0.17057858 | ... CM51: =CM50/CM47 -> 0.071127452 | CN51: =CM51*4 -> 0.28450981 | CO51: =Q51/CN51 -> 0.5272226 | CR51: Effective tax rate (%) | CS51: =CS50/CS47 -> 0.14442241 | CT51: =CT50/CT47 -> 0.16146342 | CW51: =CW50/CW47 -> 0.1345991 | CX51: =CX50/CX47 -> 0.14503889 | CY51: =CW51/CX51-1 -> -0.071979292 | CZ51: =CJ51 -> 0.12759018 | DA51: =CF51 -> 0.14284747 | DB51: =CZ51/DA51-1 -> -0.10680826 | DE51: =DE50/DE47 -> 0.12187875 | DF51: =DF50/DF47 -> 0.14776563 | DO51: Broadband | DP51: 723 | DQ51: 805 | DR51: =DQ51/DP51-1 -> 0.11341632
CN52: =CM52*4 -> 0 | CO52: =Q52/CN52 -> #DIV/0! | DO52: Digital Media | DP52: 1 | DQ52: 20 | DR52: =DQ52/DP52-1 -> 19
B53: Profit after tax | C53: =C47-C50 -> 1985.4868 | D53: =D47-D50 -> 2065.313 | E53: =E47-E50 -> 2079.1248 | F53: =F47-F50 -> 2438.0848 | G53: =G47-G50 -> 2575.6908 | H53: =H47-H50 -> 3528.1139 | I53: =I47-I50 -> 3233.9971 | J53: =J47-J50 -> 3911.7122 | ... S53: =S47-S50 -> 14462.519 | V53: =V47-V50 -> 7211.7715 | W53: =W47-W50 -> 9389.0441 | BC53: =BC47-BC50 -> #REF! | BD53: =BD47-BD50 -> #REF! | BE53: =BE47-BE50 -> #REF! | BF53: =BF47-BF50 -> #REF! | BG53: =BG47-BG50 -> 630.82136 | BH53: =BH47-BH50 -> 758.81426 | BI53: =BI47-BI50 -> 890.04925 | BJ53: =BJ47-BJ50 -> 924.41755 | ... CM53: =CM47-CM50 -> 2604.414 | CN53: =CM53*4 -> 10417.656 | CO53: =Q53/CN53 -> 1.0828779 | CR53: Profit after tax | CS53: =BW53+BX53 -> 3111.6437 | CT53: =CA53+CB53 -> 3638.2226 | CU53: =CK53+CJ53+CI53 -> 8353.7061 | CV53: =CG53+CF53+CE53 -> 6926.576 | CW53: =CI53+CJ53 -> 5335.7996 | CX53: =CE53+CF53 -> 4447.9784 | CY53: =CW53/CX53-1 -> 0.19960104 | CZ53: =CJ53 -> 2740.2421 | DA53: =CF53 -> 2287.7131 | DB53: =CZ53/DA53-1 -> 0.19780843 | DE53: =SUM(BW53) -> 1562.2197 | DF53: =SUM(CA53) -> 1807.2854 | DG53: =DF53/DE53-1 -> 0.15687018 | DO53: Investment, education & others | DP53: 491 | DQ53: 553 | DR53: =DQ53/DP53-1 -> 0.12627291
B54: Minority interest | C54: =Data!L354 -> 445.15993 | D54: =Data!M354 -> 457.60478 | E54: =Data!N354 -> 447.03971 | F54: =Data!O354 -> 507.18884 | G54: =Data!P354 -> 585.04827 | H54: =Data!Q354 -> 596.58305 | I54: =Data!R354 -> 613.81851 | J54: =Data!S354 -> 776.36179 | ... P54: =Data!Y354 -> 1856.21 | Q54: =(AVERAGE($P$54)/AVERAGE($P$53))*Q53*1/11 -> 168.16023 | R54: =(AVERAGE($P$54)/AVERAGE($P$53))*R53*1/10 -> 209.29156 | S54: =(AVERAGE($P$54)/AVERAGE($P$53))*S53*1/10 -> 237.14306 | V54: =(AVERAGE($N$54)/AVERAGE($N$53))*V53 -> 1224.9741 | W54: =(AVERAGE($O$54)/AVERAGE($O$53))*W53 -> 1564.2564 | BC54: =#REF! -> #REF! | BD54: =#REF! -> #REF! | BE54: =#REF! -> #REF! | BF54: =#REF! -> #REF! | BG54: =Data!BA494 -> 143.75471 | BH54: =Data!BB494 -> 164.74649 | BI54: =Data!BC494 -> 165.3459 | BJ54: =Data!BD494 -> 139.97141 | BK54: =Data!BE494 -> 167.61855 | BL54: =Data!BF494 -> 194.46295 | BM54: =Data!BG494 -> 199.60395 | BN54: =Data!BH494 -> 214.67634 | ... CM54: =Data!CG494 -> -10.581754 | CN54: =CM54*4 -> -42.327014 | CO54: =Q54/CN54 -> -3.9728818 | CR54: Minority interest | CS54: =BW54+BX54 -> 610.4325 | CT54: =CA54+CB54 -> 662.5996 | CU54: =CK54+CJ54+CI54 -> 1370.7692 | CV54: =CG54+CF54+CE54 -> 1161.2061 | CW54: =CI54+CJ54 -> 904.06491 | CX54: =CE54+CF54 -> 771.46066 | CY54: =CW54/CX54-1 -> 0.17188724 | CZ54: =CJ54 -> 482.80881 | DA54: =CF54 -> 409.22624 | DB54: =CZ54/DA54-1 -> 0.17980903
B55: Net profit attributable to equity shareholders | C55: =C53-C54 -> 1540.3269 | D55: =D53-D54 -> 1607.7082 | E55: =E53-E54 -> 1632.0851 | F55: =F53-F54 -> 1930.8959 | G55: =G53-G54 -> 1990.6426 | H55: =H53-H54 -> 2931.5309 | I55: =I53-I54 -> 2620.1786 | J55: =J53-J54 -> 3135.3504 | ... S55: =S53-S54 -> 14225.376 | V55: =V53-V54 -> 5986.7974 | W55: =W53-W54 -> 7824.7877 | Z55: =(R55/M55)^(1/5)-1 -> 0.18779182 | BC55: =BC53-BC54 -> #REF! | BD55: =BD53-BD54 -> #REF! | BE55: =BE53-BE54 -> #REF! | BF55: =BF53-BF54 -> #REF! | BG55: =BG53-BG54 -> 487.06665 | BH55: =BH53-BH54 -> 594.06778 | BI55: =BI53-BI54 -> 724.70335 | BJ55: =BJ53-BJ54 -> 784.44613 | ... CM55: =CM53-CM54 -> 2614.9957 | CN55: =CM55*4 -> 10459.983 | CO55: =Q55/CN55 -> 1.0624194 | CR55: Net profit attributable to equity shareholders | CS55: =BW55+BX55 -> 2501.2112 | CT55: =CA55+CB55 -> 2975.623 | CU55: =CK55+CJ55+CI55 -> 6982.9369 | CV55: =CG55+CF55+CE55 -> 5765.37 | CW55: =CI55+CJ55 -> 4431.7347 | CX55: =CE55+CF55 -> 3676.5178 | CY55: =CW55/CX55-1 -> 0.20541636 | CZ55: =CJ55 -> 2257.4333 | DA55: =CF55 -> 1878.4869 | DB55: =CZ55/DA55-1 -> 0.20172958 | DE55: =SUM(BW55) -> 1262.541 | DF55: =SUM(CA55) -> 1491.0485 | DG55: =DF55/DE55-1 -> 0.18099016
B56: NPATMI growth rate | J56: =J55/I55-1 -> 0.19661703 | K56: =K55/J55-1 -> 0.128425 | L56: =L55/K55-1 -> 0.22594754 | M56: =M55/L55-1 -> 0.2242574 | N56: =N55/M55-1 -> 0.21752509 | O56: =O55/N55-1 -> 0.21524185 | P56: =P55/O55-1 -> 0.20458662 | Q56: =Q55/P55-1 -> 0.17420762 | ... S56: =S55/R55-1 -> 0.13307511 | W56: =W55/O55-1 -> -0.0040706652 | CN56: =CM56*4 -> 0 | CO56: =Q56/CN56 -> #DIV/0!
B57: Net margin (%) | C57: =C53/C9 -> 0.08072954 | D57: =D53/D9 -> 0.076414145 | E57: =E53/E9 -> 0.063689591 | F57: =F53/F9 -> 0.064228243 | G57: =G53/G9 -> 0.065155455 | H57: =H53/H9 -> 0.082705785 | I57: =I53/I9 -> 0.13931514 | J57: =J53/J9 -> 0.14113063 | ... S57: =S53/S9 -> 0.18896178 | V57: =V53/V9 -> 0.12937164 | W57: =W53/W9 -> 0.14159697 | BC57: =BC55/BC9 -> #REF! | BD57: =BD55/BD9 -> #REF! | BE57: =BE55/BE9 -> #REF! | BF57: =BF55/BF9 -> #REF! | BG57: =BG55/BG9 -> 0.10252376 | BH57: =BH55/BH9 -> 0.10852014 | BI57: =BI55/BI9 -> 0.12006234 | BJ57: =BJ55/BJ9 -> 0.11283023 | ... CM57: =CM55/CM9 -> 0.20953496 | CN57: =CM57*4 -> 0.83813985 | CO57: =Q57/CN57 -> 0.23533034 | CR57: Net margin (%) | CS57: =CS55/CS9 -> 0.12615614 | CT57: =CT55/CT9 -> 0.12313393 | CW57: =CW55/CW9 -> 0.13559815 | CX57: =CX55/CX9 -> 0.12531523 | CY57: =CW57/CX57-1 -> 0.082056414 | CZ57: =CJ57 -> 0.1357878 | DA57: =CF57 -> 0.12321804 | DB57: =CZ57/DA57-1 -> 0.10201238 | DE57: =DE55/DE9 -> 0.12975417 | DF57: =DF55/DF9 -> 0.1276432
B58: Net profit growth (%) | D58: =D55/C55-1 -> 0.043744817 | E58: =E55/D55-1 -> 0.015162495 | F58: =F55/E55-1 -> 0.18308533 | G58: =G55/F55-1 -> 0.030942454 | H58: =H55/G55-1 -> 0.47265556 | I58: =I55/H55-1 -> -0.10620807 | J58: =J55/I55-1 -> 0.19661703 | K58: =K55/J55-1 -> 0.128425 | ... S58: =S55/R55-1 -> 0.13307511 | V58: =V55/N55-1 -> -0.07399519 | W58: =W55/O55-1 -> -0.0040706652 | BK58: =BK55/BG55-1 -> 0.28936225 | BL58: =BL55/BH55-1 -> 0.33732505 | BM58: =BM55/BI55-1 -> 0.32321817 | BN58: =BN55/BJ55-1 -> -0.027193969 | BO58: =BO55/BK55-1 -> 0.18826825 | BP58: =BP55/BL55-1 -> 0.087320411 | BQ58: =BQ55/BM55-1 -> -0.02952053 | BR58: =BR55/BN55-1 -> 0.43510334 | ... CC58: =CC55/BY55-1 -> 0.16296337 | CD58: =CD55/CA55-1 -> 0.15918424 | CE58: =CE55/CB55-1 -> 0.21114223 | CF58: =CF55/CC55-1 -> 0.085419966 | CG58: =CG55/CD55-1 -> 0.20854678 | CH58: =CH55/CE55-1 -> 0.16500253 | CI58: =CI55/CE55-1 -> 0.20926811 | CJ58: =CJ55/CF55-1 -> 0.20172958 | CK58: =CK55/CG55-1 -> 0.22134165 | CL58: =CL55/CH55-1 -> 0.18752167 | CM58: =CM55/CI55-1 -> 0.20268319 | CN58: =CM58*4 -> 0.81073278 | CO58: =Q58/CN58 -> 0.21487674 | CR58: Net profit growth (%)
B59: PBT growth (%) | D59: =D47/C47-1 -> 0.045321685 | E59: =E47/D47-1 -> -0.022422133 | F59: =F47/E47-1 -> 0.15936921 | G59: =G47/F47-1 -> 0.057082197 | H59: =H47/G47-1 -> 0.41183173 | I59: =I47/H47-1 -> -0.093420498 | J59: =J47/I47-1 -> 0.20917861 | K59: =K47/J47-1 -> 0.12840009 | ... S59: =S47/R47-1 -> 0.13307511 | V59: =V47/N47-1 -> -0.21636784 | W59: =W47/O47-1 -> -0.0021433115 | CN59: =CM59*4 -> 0 | CO59: =Q59/CN59 -> #DIV/0! | CR59: PBT growth (%)
CN60: =CM60*4 -> 0 | CO60: =Q60/CN60 -> #DIV/0!
B61: Gross margins | L61: =L14 -> 0.38230541 | M61: =M14 -> 0.39008096 | N61: =N14 -> 0.38617188 | O61: =O14 -> 0.37706915 | P61: =P14 -> 0.37019121 | Q61: =Q14 -> 0.34660129 | R61: =R14 -> 0.33780577 | S61: =S14 -> 0.33418917 | W61: =W14 -> 0.37483499 | CD61: =CD14 -> 0.38337 | CE61: =CE14 -> 0.39100927 | CF61: =CF14 -> 0.37069684 | CG61: =CG14 -> 0.38728697 | CH61: =CH14 -> 0.362201 | CI61: =CI14 -> 0.39240831 | CJ61: =CJ14 -> 0.36217407 | CK61: =CK14 -> 0.37890427 | ... CM61: =CM14 -> 0.34013548 | CN61: =CM61*4 -> 1.3605419 | CO61: =Q61/CN61 -> 0.25475238 | CR61: Gross margin (%) | CS61: =CS14 -> 0.39321528 | CT61: =CT14 -> 0.38077469 | CW61: =CW14 -> 0.37702913 | CX61: =CX14 -> 0.38045416 | CY61: =CY14 -> -0.0090024776 | CZ61: =CZ14 -> 0.36217407 | DA61: =DA14 -> 0.37069684
B62: EBIT margins | L62: =L26 -> 0.15186324 | M62: =M26 -> 0.15438833 | N62: =N26 -> 0.16062267 | O62: =O26 -> 0.16720036 | P62: =P26 -> 0.1577981 | Q62: =Q26 -> 0.17060129 | R62: =R26 -> 0.16380577 | S62: =S26 -> 0.16018917 | W62: =W26 -> 0.15483499 | CD62: =CD26 -> 0.15899913 | CE62: =CE26 -> 0.16448287 | CF62: =CF26 -> 0.15417855 | CG62: =CG26 -> 0.1752604 | CH62: =CH26 -> 0.1733707 | CI62: =CI26 -> 0.16160805 | CJ62: =CJ26 -> 0.13937308 | CK62: =CK26 -> 0.17175758 | ... CM62: =CM26 -> 0.16284219 | CN62: =CM62*4 -> 0.65136876 | CO62: =Q62/CN62 -> 0.261912 | CR62: Selling expenses/ Sales (%) | CS62: =CS19 -> 0.10193098 | CT62: =CT19 -> 0.096838241 | CW62: =CW19 -> 0.11073335 | CX62: =CX19 -> 0.10079574 | CY62: =CY19 -> 0.098591569 | CZ62: =CZ19 -> 0.10768883 | DA62: =DA19 -> 0.10417768
B63: EBIT/PBT | C63: =C24/C47 -> 0.92728835 | D63: =D24/D47 -> 0.92862292 | E63: =E24/E47 -> 0.94935174 | F63: =F24/F47 -> 1.0294656 | G63: =G24/G47 -> 1.0114879 | H63: =H24/H47 -> 0.74419528 | I63: =I24/I47 -> 0.80924804 | J63: =J24/J47 -> 0.88901492 | ... S63: =S24/S47 -> 0.7205732 | W63: =W24/W47 -> 0.92946728 | BG63: =BG24/BG47 -> 0.84841819 | BH63: =BH24/BH47 -> 0.79326495 | BI63: =BI24/BI47 -> 0.84441547 | BJ63: =BJ24/BJ47 -> 0.76087319 | BK63: =BK24/BK47 -> 0.84358971 | BL63: =BL24/BL47 -> 0.91665271 | BM63: =BM24/BM47 -> 0.8714963 | BN63: =BN24/BN47 -> 0.89425856 | ... CM63: =CM24/CM47 -> 0.7248156 | CN63: =CM63*4 -> 2.8992624 | CO63: =Q63/CN63 -> 0.25358252 | CR63: Administration /Net sales (%) | CS63: =CS22 -> 0.14015376 | CT63: =CT22 -> 0.1269587 | CW63: =CW22 -> 0.11599794 | CX63: =CX22 -> 0.12053007 | CY63: =CY22 -> -0.03760167 | CZ63: =CZ22 -> 0.11511216 | DA63: =DA22 -> 0.11234061
B64: Net FX gain | CN64: =CM64*4 -> 0 | CO64: =Q64/CN64 -> #DIV/0!
B65: Financial income | C65: =C39/C47 -> 0.035997283 | D65: =D39/D47 -> 0.0457801 | E65: =E39/E47 -> 0.0055172857 | F65: =F39/F47 -> -0.058876224 | G65: =G39/G47 -> -0.039634462 | H65: =H39/H47 -> 0.23083454 | I65: =I39/I47 -> 0.061967696 | J65: =J39/J47 -> 0.012457522 | ... S65: =S39/S47 -> 0.060503585 | W65: =W39/W47 -> 0 | BG65: =BG39/BG47 -> 0.014341027 | BH65: =BH39/BH47 -> 0.047095493 | BI65: =BI39/BI47 -> 0.054701246 | BJ65: =BJ39/BJ47 -> 0.11457079 | BK65: =BK39/BK47 -> 0.033606512 | BL65: =BL39/BL47 -> -0.034031304 | BM65: =BM39/BM47 -> 0.025847498 | BN65: =BN39/BN47 -> 0.02973315 | ... CM65: =CM39/CM47 -> 0.017352064 | CN65: =CM65*4 -> 0.069408255 | CO65: =Q65/CN65 -> 0.60550556 | CR65: SG&A/Net sales (%) | CS65: =CS62+CS63 -> 0.24208474 | CT65: =CT62+CT63 -> 0.22379694 | CW65: =CW62+CW63 -> 0.22673129 | CX65: =CX62+CX63 -> 0.22132581 | CY65: =CY62+CY63 -> 0.060989899 | CZ65: =CZ62+CZ63 -> 0.22280099 | DA65: =DA62+DA63 -> 0.21651829
B66: Other activities | C66: =C44/C47 -> 0.023142362 | D66: =D44/D47 -> 0.017042109 | E66: =E44/E47 -> 0.02851655 | F66: =F44/F47 -> 0.017319139 | G66: =G44/G47 -> 0.01648943 | H66: =H44/H47 -> 0.0082643334 | I66: =I44/I47 -> 0.014975985 | J66: =J44/J47 -> 0.011717653 | ... S66: =S44/S47 -> 0.0075048064 | W66: =W44/W47 -> 0.010503188 | BG66: =BG44/BG47 -> 0.012029367 | BH66: =BH44/BH47 -> 0.029528635 | BI66: =BI44/BI47 -> -0.006304772 | BJ66: =BJ44/BJ47 -> 0.025210929 | BK66: =BK44/BK47 -> 0.024087361 | BL66: =BL44/BL47 -> 0.011957252 | BM66: =BM44/BM47 -> 0.015395543 | BN66: =BN44/BN47 -> 0.018572229 | ... CM66: =CM44/CM47 -> 0.020001273 | CN66: =CM66*4 -> 0.080005092 | CO66: =Q66/CN66 -> 0.091204405 | CR66: EBIT margin (%) | CS66: =CS26 -> 0.15113055 | CT66: =CT26 -> 0.15697775 | CW66: =CW26 -> 0.15029784 | CX66: =CX26 -> 0.15912835 | CY66: =CY26 -> -0.055492991 | CZ66: =CZ26 -> 0.13937308 | DA66: =DA26 -> 0.15417855
B67: Income from subsidiaries | C67: =C45/C47 -> 0.013572007 | D67: =D45/D47 -> 0.0085548695 | E67: =E45/E47 -> 0.016614426 | F67: =F45/F47 -> 0.012091507 | G67: =G45/G47 -> 0.011657115 | H67: =H45/H47 -> 0.016705849 | I67: =I45/I47 -> 0.11380828 | J67: =J45/J47 -> 0.086809908 | ... S67: =S45/S47 -> 0.21141841 | W67: =W45/W47 -> 0.060029535 | BG67: =BG45/BG47 -> 0.12521141 | BH67: =BH45/BH47 -> 0.13011092 | BI67: =BI45/BI47 -> 0.10718806 | BJ67: =BJ45/BJ47 -> 0.099345086 | BK67: =BK45/BK47 -> 0.098716415 | BL67: =BL45/BL47 -> 0.10542134 | BM67: =BM45/BM47 -> 0.087260659 | BN67: =BN45/BN47 -> 0.057436059 | ... CM67: =CM45/CM47 -> 0.23783106 | CN67: =CM67*4 -> 0.95132426 | CO67: =Q67/CN67 -> 0.22649882 | CR67: PBT margin (%) | CS67: =CS47/CS9 -> 0.18343765 | CT67: =CT47/CT9 -> 0.17954243 | CW67: =CW47/CW9 -> 0.18865234 | CX67: =CX47/CX9 -> 0.17733053 | CY67: =CY47/CY9 -> 1.6238714 | CZ67: =CZ47/CZ9 -> 0.18893579 | DA67: =DA47/DA9 -> 0.17506913
CR68: Net margin (%) | CS68: =CS57 -> 0.12615614 | CT68: =CT57 -> 0.12313393 | CW68: =CW57 -> 0.13559815 | CX68: =CX57 -> 0.12531523 | CY68: =CY57 -> 0.082056414 | CZ68: =CZ57 -> 0.1357878 | DA68: =DA57 -> 0.12321804
B70: Net revenue growth (%) | I70: =I10 -> -0.45582999 | J70: =J10 -> 0.19399988 | K70: =K10 -> 0.0762508 | L70: =L10 -> 0.19533301 | M70: =M10 -> 0.23423742 | N70: =N10 -> 0.19560249 | O70: =O10 -> 0.19443743 | P70: =P10 -> 0.11708897 | ... S70: =S10 -> 0.1606144 | W70: =W10 -> 0.05504386
B71: COGS growth (%) | I71: =I8 -> 0.0019600659 | J71: =J8 -> 0.0026994125 | K71: =K8 -> 0.0030512178 | L71: =L8 -> 0.00038657925 | M71: =M8 -> 0.0003062762 | N71: =N8 -> 0.00013822346 | O71: =O8 -> 0.0018083737 | P71: =P8 -> 0.001351134 | ... S71: =S8 -> 0.001351134 | W71: =W8 -> 0.0018083737
B72: EBIT growth (%) | I72: =I18 -> 0 | J72: =J25 -> 0.32836631 | K72: =K25 -> 0.11041969 | L72: =L25 -> 0.17597077 | M72: =M25 -> 0.25475951 | N72: =N25 -> 0.24388206 | O72: =O25 -> 0.243351 | P72: =P25 -> 0.054271179 | Q72: =Q25 -> -0.11925345 | ... S72: =S25 -> 0.1349897 | W72: =W25 -> -0.022982274
B74: Net revenue growth (%)
B75: COGS growth (%)
B82: Earnings per share (EPS)
B83: Reported EPS on Historical FS | I83: 3903 | J83: 4220 | K83: 4120 | L83: 4349 | M83: 4429
B85: No Dilution Case
B86: NPATMNI excluding bonus & welfare fund | C86: =C55-C87 -> 1386.2942 | D86: =D55-D87 -> 1446.9374 | E86: =E55-E87 -> 1468.8766 | F86: =F55-F87 -> 1737.8063 | G86: =G55-G87 -> 1791.5783 | H86: =H55-H87 -> 2638.3778 | I86: =I55-I87 -> 2391.2396 | J86: =J55-J87 -> 2858.8564 | ... S86: =S55-S87 -> 13388.161 | V86: =V55-V87 -> 5441.0788 | W86: =W55-W87 -> 7824.7877
B87: Deducted: Welfare and bonus fund | C87: =C55*C88 -> 154.03269 | D87: =D55*D88 -> 160.77082 | E87: =E55*E88 -> 163.20851 | F87: =F55*F88 -> 193.08959 | G87: =G55*G88 -> 199.06426 | H87: =H55*H88 -> 293.15309 | I87: =I55*I88 -> 228.939 | J87: =J55*J88 -> 276.494 | ... S87: =S55*S88 -> 837.21474 | V87: =V55*V88 -> 545.71867 | W87: =W55*W88 -> 0
B88: % of net profit | C88: 0.1 | D88: 0.1 | E88: 0.1 | F88: 0.1 | G88: 0.1 | H88: 0.1 | I88: 0.08737534 | J88: 0.088185997 | K88: 0.088160632 | L88: 0.091578806 | M88: 0.086910464 | N88: 0.086910464 | O88: 0.086910464 | P88: 0.086910464 | Q88: =BS!Q100 -> 0.058853612 | R88: =BS!R100 -> 0.058853612 | S88: =BS!S100 -> 0.058853612 | V88: =BS!W100 -> 0.091153688 | W88: =BS!X100 -> 0
B90: Outstanding shares in the beginning | C90: =(BS!C66*10^9)/(10^4) -> 273848833 | D90: =C91 -> 273848833 | E90: =D91 -> 275201755 | F90: =E91 -> 343976600 | G90: =F91 -> 397531640 | H90: =G91 -> 459426684 | I90: =H91 -> 530961105 | J90: =I91 -> 613636772 | K90: =J91 -> 678358688 | ... P90: =O91 -> 1471069000 | Q90: =W91 -> 1703507121 | R90: =Q91 -> 1703507121 | S90: =R91 -> 1703507121 | V90: =N91 -> 1269968875 | W90: =O91 -> 1471069000
B91: Outstanding shares at the year end | C91: =(BS!C66*10^9)/(10^4) -> 273848833 | D91: =(BS!D66*10^9)/(10^4) -> 275201755 | E91: =(BS!E66*10^9)/(10^4) -> 343976600 | F91: =(BS!F66*10^9)/(10^4) -> 397531640 | G91: =(BS!G66*10^9)/(10^4) -> 459426684 | H91: =(BS!H66*10^9)/(10^4) -> 530961105 | I91: =(BS!I66*10^9)/(10^4) -> 613636772 | J91: =(BS!J66*10^9)/(10^4) -> 678358688 | ... P91: =(BS!P66*10^9)/(10^4) -> 1.7035071e+09 | Q91: =Q90 -> 1703507121 | R91: =R90 -> 1703507121 | S91: =S90 -> 1703507121 | V91: =V90 -> 1269968875 | W91: 1703507121
B92: Par value | C92: 10000 | D92: 10000 | E92: 10000 | F92: 10000 | G92: 10000 | H92: 10000 | I92: 10000 | J92: 10000 | K92: 10000 | L92: 10000 | M92: 10000 | N92: 10000 | O92: 10000 | P92: 10001 | Q92: 10000 | R92: 10000 | S92: 10001 | V92: 10000 | W92: 10000
B94: EPS (ex bonus and welfare fund) | C94: =(C55-C87)*10^9/C91 -> 5062.2608 | D94: =(D55-D87)*10^9/D91 -> 5257.7332 | E94: =(E55-E87)*10^9/E91 -> 4270.2805 | F94: =(F55-F87)*10^9/F91 -> 4371.4919 | G94: =(G55-G87)*10^9/G91 -> 3899.5957 | H94: =(H86)*10^9/H91 -> 4969.0604 | I94: =(I86)*10^9/I91 -> 3896.8324 | J94: =(J86)*10^9/J91 -> 4214.3728 | K94: =(K86)*10^9/K91 -> 4114.9824 | L94: =(L86)*10^9/L91 -> 4341.5676 | M94: =(M86)*10^9/M91 -> 4419.7695 | N94: =(N86)*10^9/N91 -> 4648.3799 | O94: =(O86)*10^9/O91 -> 4876.6812 | ... S94: =(S86)*10^9/S91 -> 7859.1752 | V94: =(V86)*10^9/V91 -> 4284.419 | W94: =(W86)*10^9/W91 -> 4593.3402
B95: Growth (%) | D95: =D94/C94-1 -> 0.038613653 | E95: =E94/D94-1 -> -0.18780958 | F95: =F94/E94-1 -> 0.02370133 | G95: =G94/F94-1 -> -0.10794854 | H95: =H94/G94-1 -> 0.27425014 | I95: =I94/H94-1 -> -0.21578083 | J95: =J94/I94-1 -> 0.0814868 | K95: =K94/J94-1 -> -0.023583657 | ... S95: =S94/R94-1 -> 0.13307511 | V95: =V94/N94-1 -> -0.078298433 | W95: =W94/O94-1 -> -0.058101188
B97: Dilution Case
B98: ESOP distribution | M98: =(M99*M101)/10^9 -> 66.44265 | N98: =(N99*N101)/10^9 -> 63.49622 | O98: =(O99*O101)/10^9 -> 63.50258 | P98: =(P99*P101)/10^9 -> 63.508939
B99: ESOP shares | M99: =2107000+4537265 -> 6644265 | N99: 6349622 | O99: 6349623 | P99: 6349624
B100: % charter capital | M100: =M99/L91 -> 0.0073210875 | N100: =N99/K91 -> 0.0080991369 | O100: =O99/L91 -> 0.0069964316 | P100: =P99/M91 -> 0.0057880312
B101: Issue price | M101: 10000 | N101: 10000 | O101: 10001 | P101: 10002
B103: Stock dividend ratio | C103: 0 | D103: 0 | E103: 0.25 | F103: 0.15 | G103: 0.15 | H103: 0.15 | I103: 0.15 | J103: 0.1 | K103: 0.15 | L103: 0.2 | M103: 0.15 | N103: 0.15 | O103: 0.15 | P103: 0.15 | Q103: 0.1 | R103: 0.1 | S103: 1.1 | V103: 0.1 | W103: 0.1 | AA103: =#REF!*20%*10000 -> #REF! | AB103: =#REF!*20%*10000 -> #REF! | AC103: =#REF!*20%*10000 -> #REF! | AD103: =#REF!*20%*10000 -> #REF! | AE103: =#REF!*20%*10000 -> #REF! | AF103: =#REF!*20%*10000 -> #REF! | AG103: =#REF!*20%*10000 -> #REF! | AH103: =#REF!*20%*10000 -> #REF! | ... AT103: =#REF!*20%*10000 -> #REF! | AU103: =A113*20%*10000 -> 0 | AV103: =B91*20%*10000 -> #VALUE! | AW103: =C91*20%*10000 -> 547697666000 | AX103: =D91*20%*10000 -> 550403510000 | AY103: =E91*20%*10000 -> 687953200000 | AZ103: =F91*20%*10000 -> 795063280000 | BA103: =G91*20%*10000 -> 9.1885337e+11 | BB103: =H91*20%*10000 -> 1061922210000 | BC103: =I91*20%*10000 -> 1227273544000 | ... BF103: =L91*20%*10000 -> 1815103298000
B104: Stock dividend distribution | Q104: =(PL!Q105*PL!Q106)/10^9 -> 1703.5072 | R104: =(PL!R105*PL!R106)/10^9 -> 1873.8579 | S104: =(PL!S105*PL!S106)/10^9 -> 2061.2437 | V104: =(PL!V105*PL!V106)/10^9 -> 1904.9533 | W104: =(PL!W105*PL!W106)/10^9 -> 2206.6035
B105: Stock dividend shares | N105: =N108*M103 -> 1.6564976e+08 | O105: =O108*N103 -> 1.6564976e+08 | P105: =P108*O103 -> 220660350 | Q105: =Q108*W103 -> 1.7035072e+08 | R105: =R108*Q103 -> 1.8738579e+08 | S105: =S108*R103 -> 2.0612437e+08 | V105: 190495331 | W105: =W108*O103 -> 220660350
B106: Issue price | N106: 10000 | O106: 10000 | P106: 10000 | Q106: =W106 -> 10000 | R106: =Q106 -> 10000 | S106: =R106 -> 10000 | V106: =N106 -> 10000 | W106: =V106 -> 10000
B108: Outstanding shares in the beginning | C108: 273848833 | D108: 273848833 | E108: 275201755 | F108: 343976600 | G108: 397531640 | H108: 459426684 | I108: 530961105 | J108: 613636772 | K108: 678358688 | L108: 783987486 | M108: 907551649 | N108: 1104331702 | O108: 1104331702 | P108: =O109 -> 1471069000 | Q108: =P109 -> 1703507201 | R108: =Q109 -> 1.8738579e+09 | S108: =R109 -> 2.0612437e+09 | V108: =N109 -> 1.2699815e+09 | W108: =O109 -> 1471069000
B109: Outstanding shares at the year end | C109: 273848833 | D109: 275201755 | E109: 343976600 | F109: 397531640 | G109: 459426684 | H109: 530961105 | I109: 613636772 | J109: 678358688 | K109: 783987486 | L109: 907551649 | M109: 1097026572 | N109: 1.2699815e+09 | O109: =O91 -> 1471069000 | P109: 1703507201 | Q109: =Q108+Q105 -> 1.8738579e+09 | R109: =R108+R105 -> 2.0612437e+09 | S109: =S108+S105 -> 2.2673681e+09 | V109: =V108+V105 -> 1.4604768e+09 | W109: =W108+W105 -> 1691729350
B110: Par value | C110: 10000 | D110: 10000 | E110: 10000 | F110: 10000 | G110: 10000 | H110: 10000 | I110: 10000 | J110: 10000 | K110: 10000 | L110: 10000 | M110: 10000 | N110: 10000 | O110: 10000 | P110: 10000 | Q110: 10000 | R110: 10000 | S110: 10001 | V110: 10000 | W110: 10000
B113: EPS (ex bonus and welfare fund) | C113: =(C86)*10^9/C109 -> 5062.2608 | D113: =(D86)*10^9/D109 -> 5257.7332 | E113: =(E86)*10^9/E109 -> 4270.2805 | F113: =(F86)*10^9/F109 -> 4371.4919 | G113: =(G86)*10^9/G109 -> 3899.5957 | H113: =(H86)*10^9/H109 -> 4969.0604 | I113: =(I86)*10^9/I109 -> 3896.8324 | J113: =(J86)*10^9/J109 -> 4214.3728 | ... S113: =(S86)*10^9/S109 -> 5904.7144 | V113: =(V86)*10^9/V109 -> 3725.5496 | W113: =(W86)*10^9/W109 -> 4625.3189
B114: Growth (%) | D114: =D113/C113-1 -> 0.038613653 | E114: =E113/D113-1 -> -0.18780958 | F114: =F113/E113-1 -> 0.02370133 | G114: =G113/F113-1 -> -0.10794854 | H114: =H113/G113-1 -> 0.27425014 | I114: =I113/H113-1 -> -0.21578083 | J114: =J113/I113-1 -> 0.0814868 | K114: =K113/J113-1 -> -0.023583657 | ... S114: =S113/R113-1 -> 0.030068283 | V114: =V113/N113-1 -> -0.19851934 | W114: =W113/O113-1 -> -0.051543716
B117: EPS unadjusted (VND) | C117: =C55*10^9/C91 -> 5624.7342 | D117: =D55*10^9/D91 -> 5841.9258 | E117: =E55*10^9/E91 -> 4744.7561 | F117: =F55*10^9/F91 -> 4857.2132 | G117: =G55*10^9/G91 -> 4332.8841 | H117: =H55*10^9/H91 -> 5521.1782 | I117: =I55*10^9/I91 -> 4269.9179 | J117: =J55*10^9/J91 -> 4621.9654 | ... S117: =S55*10^9/S91 -> 8350.6406 | V117: =V55*10^9/V91 -> 4714.1293 | W117: =W55*10^9/W91 -> 4593.3402
B118: Cash dividend | C118: =(C120*C91)/10^9 -> 547.69767 | D118: =(D120*D91)/10^9 -> 825.60527 | E118: =(E120*E91)/10^9 -> 687.9532 | F118: =(F120*F91)/10^9 -> 795.06328 | G118: =(G120*G91)/10^9 -> 918.85337 | H118: =(H120*H91)/10^9 -> 1327.4028 | I118: 1413.854 | J118: 1294.8979 | K118: 1465.573 | L118: 1696.584 | M118: 2011.223 | N118: 2374.3 | O118: 3000 | P118: 3000 | Q118: 4000 | R118: 4000 | S118: 4000 | V118: =V55*V119 -> 2321.9574 | W118: =W55*W119 -> 2987.788
...

Sheet BS
V2: OLD | W2: OLD
B3: BALANCE SHEET | P3: Historical | V3: Projection
B4: VND bn | C4: 2012 | D4: 2013 | E4: 2014 | F4: 2015 | G4: 2016 | H4: 2017 | I4: 2018 | J4: 2019 | K4: 2020 | L4: 2021 | M4: 2022 | N4: 2023 | O4: 2024 | P4: 2025 | Q4: 2026 | R4: 2027 | S4: 2028 | V4: 2023 | W4: 2024 | AD4: % change | AE4: % weight
B6: Cash & cash equivalents | C6: =Data!L16 -> 2318.915 | D6: =Data!M16 -> 2750.9711 | E6: =Data!N16 -> 4336.2824 | F6: =Data!O16 -> 3584.7092 | G6: =Data!P16 -> 6013.3614 | H6: =Data!Q16 -> 3480.6595 | I6: =Data!R16 -> 3925.7272 | J6: =Data!S16 -> 3453.3886 | ... P6: =Data!Y16 -> 10540.182 | Q6: =P6+CF!L87 -> 17810.108 | R6: =Q6+CF!M87 -> 20356.574 | S6: =R6+CF!N87 -> 22560.078 | V6: =M6+CF!Q87 -> #REF! | W6: =N6+CF!R87 -> 8279.1567 | AC6: OOOOO | AD6: =M6/L6-1 -> 0.18869713 | AE6: =M6/$M$38 -> 0.12468784
B7: Short-term financial investment | C7: =Data!L20+Data!L22 -> 677.62739 | D7: =Data!M20+Data!M22 -> 1452.8549 | E7: =Data!N20+Data!N22 -> 1428.4791 | F7: =Data!O20+Data!O22 -> 2617.4419 | G7: =Data!P20+Data!P22 -> 3472.0873 | H7: =Data!Q20+Data!Q22 -> 4379.4462 | I7: =Data!R20+Data!R22 -> 5568.6237 | J7: =Data!S20+Data!S22 -> 6708.9782 | ... P7: =Data!Y20+Data!Y22 -> 29612.987 | Q7: =P7 -> 29612.987 | R7: =Q7 -> 29612.987 | S7: =R7 -> 29612.987 | V7: =M7+833.58 -> 13880.814 | W7: =N7 -> 16104.205 | AD7: =M7/L7-1 -> -0.37063287 | AE7: =M7/$M$38 -> 0.25260662
B8: Provision for diminution (stock) | C8: =Data!L21 -> -15.606622 | D8: =Data!M21 -> -9.4054971 | E8: =Data!N21 -> 0 | F8: =Data!O21 -> 0 | G8: =Data!P21 -> 0 | H8: =Data!Q21 -> 0 | I8: =Data!R21 -> 0 | J8: =Data!S21 -> 0 | ... P8: =Data!Y21 -> 0 | Q8: =P8 -> 0 | R8: =Q8 -> 0 | S8: =R8 -> 0 | V8: =M8 -> 0 | W8: =N8 -> 0
B9: Account Receivable | C9: =Data!L24 -> 3208.6016 | D9: =Data!M24 -> 3658.2672 | E9: =Data!N24 -> 3919.5427 | F9: =Data!O24 -> 4477.1221 | G9: =Data!P24 -> 4813.6449 | H9: =Data!Q24 -> 5038.3789 | I9: =Data!R24 -> 5561.5458 | J9: =Data!S24 -> 5812.9381 | ... P9: =Data!Y24 -> 12733.505 | Q9: =Assumptions!Q74*PL!Q9 -> 9088.458 | R9: =Assumptions!R74*PL!R9 -> 10478.935 | S9: =Assumptions!S74*PL!S9 -> 12162.002 | V9: =Assumptions!AF74*PL!#REF! -> #REF! | W9: =Assumptions!AG74*PL!V9 -> 9621.6724 | AC9: Assumptions | AD9: =M9/L9-1 -> 0.28624161 | AE9: =M9/$M$38 -> 0.15469534
B10: Provision for bad debts | C10: =Data!L30 -> -181.02703 | D10: =Data!M30 -> -240.2717 | E10: =Data!N30 -> -243.08307 | F10: =Data!O30 -> -282.20223 | G10: =Data!P30 -> -142.68823 | H10: =Data!Q30 -> -180.5188 | I10: =Data!R30 -> -264.66691 | J10: =Data!S30 -> -361.51561 | ... P10: =Data!Y30 -> -586.16674 | Q10: =P10 -> -586.16674 | R10: =Q10 -> -586.16674 | S10: =R10 -> -586.16674 | V10: -747.991 | W10: =N10 -> -912.15665 | AD10: =M10/L10-1 -> 0.31970066 | AE10: =M10/$M$38 -> -0.013541734
B11: Inventory | C11: =Data!L33 -> 2710.3012 | D11: =Data!M33 -> 3353.8056 | E11: =Data!N33 -> 4652.3332 | F11: =Data!O33 -> 5332.0317 | G11: =Data!P33 -> 4617.0301 | H11: =Data!Q33 -> 1024.044 | I11: =Data!R33 -> 1401.3027 | J11: =Data!S33 -> 1349.9589 | ... P11: =Data!Y33 -> 2250.8125 | Q11: =PL!Q11*Assumptions!Q72 -> 1740.5616 | R11: =PL!R11*Assumptions!R72 -> 2033.8712 | S11: =PL!S11*Assumptions!S72 -> 2373.4324 | V11: =PL!#REF!*Assumptions!AF72 -> #REF! | W11: =PL!V11*Assumptions!AG72 -> 2674.1197 | AC11: Assumptions | AD11: =M11/L11-1 -> 0.30665805 | AE11: =M11/$M$38 -> 0.041066824
B12: Provision for decline in inventories | C12: =Data!L34 -> -10.792414 | D12: =Data!M34 -> -24.924631 | E12: =Data!N34 -> -79.697061 | F12: =Data!O34 -> -63.932037 | G12: =Data!P34 -> -63.221664 | H12: =Data!Q34 -> -3.8315289 | I12: =Data!R34 -> -60.61545 | J12: =Data!S34 -> -65.758167 | ... P12: =Data!Y34 -> -83.623808 | Q12: =P12 -> -83.623808 | R12: =Q12 -> -83.623808 | S12: =R12 -> -83.623808 | V12: -150.958 | W12: =N12 -> -131.54585 | AD12: =M12/L12-1 -> 0.3393727 | AE12: =M12/$M$38 -> -0.0030073396
B13: Other current assets | C13: =SUM(Data!L25:L29,Data!L31,Data!L35) -> 1521.4511 | D13: =SUM(Data!M25:M29,Data!M31,Data!M35) -> 1966.9465 | E13: =SUM(Data!N25:N29,Data!N31,Data!N35) -> 2695.2998 | F13: =SUM(Data!O25:O29,Data!O31,Data!O35) -> 3293.8386 | G13: =SUM(Data!P25:P29,Data!P31,Data!P35) -> 3198.4491 | H13: =SUM(Data!Q25:Q29,Data!Q31,Data!Q35) -> 2321.7595 | I13: =SUM(Data!R25:R29,Data!R31,Data!R35) -> 2274.1702 | J13: =SUM(Data!S25:S29,Data!S31,Data!S35) -> 2081.1861 | ... P13: =SUM(Data!Y25:Y29,Data!Y31,Data!Y35) -> 3635.2757 | Q13: =P13/PL!P9*PL!Q9 -> 2961.4728 | R13: =Q13/PL!Q9*PL!R9 -> 3414.5595 | S13: =R13/PL!R9*PL!S9 -> 3962.9869 | V13: =M13/PL!M9*PL!#REF! -> #REF! | W13: =N13/PL!#REF!*PL!V9 -> #REF! | AD13: =M13/L13-1 -> 0.23216338 | AE13: =M13/$M$38 -> 0.042475391
B14: Current Asset | C14: =SUM(C6:C13) -> 10229.47 | D14: =SUM(D6:D13) -> 12908.243 | E14: =SUM(E6:E13) -> 16709.157 | F14: =SUM(F6:F13) -> 18959.009 | G14: =SUM(G6:G13) -> 21908.663 | H14: =SUM(H6:H13) -> 16059.938 | I14: =SUM(I6:I13) -> 18406.087 | J14: =SUM(J6:J13) -> 18979.176 | ... S14: =SUM(S6:S13) -> 70001.696 | V14: =SUM(V6:V13) -> #REF! | W14: =SUM(W6:W13) -> #REF! | AD14: =M14/L14-1 -> -0.11904486 | AE14: =M14/$M$38 -> 0.59898295
B16: Tangible Fixed Assets | C16: =C17+C18 -> 1806.9098 | D16: =D17+D18 -> 2263.587 | E16: =E17+E18 -> 2998.0023 | F16: =F17+F18 -> 3971.4021 | G16: =G17+G18 -> 4131.2986 | H16: =H17+H18 -> 4585.4931 | I16: =I17+I18 -> 5207.126 | J16: =J17+J18 -> 6295.2618 | ... S16: =S17+S18 -> 7969.9679 | V16: =V17+V18 -> #REF! | W16: =W17+W18 -> 13972.33 | AD16: =M16/L16-1 -> 0.15692762 | AE16: =M16/$M$38 -> 0.20743751
B17: Historical price | C17: =Data!L52 -> 3396.1142 | D17: =Data!M52 -> 4132.4221 | E17: =Data!N52 -> 5352.533 | F17: =Data!O52 -> 6937.0724 | G17: =Data!P52 -> 7932.0273 | H17: =Data!Q52 -> 8260.1736 | I17: =Data!R52 -> 9471.9841 | J17: =Data!S52 -> 11301.062 | ... P17: =Data!Y52 -> 29148.693 | Q17: =BS!Q219 -> 28800.985 | R17: =BS!R219 -> 30323.749 | S17: =BS!S219 -> 29577.733 | V17: =BS!V219 -> #REF! | W17: =BS!Y219 -> 26054.638 | AD17: =M17/L17-1 -> 0.18202761 | AE17: =M17/$M$38 -> 0.36801227
B18: Depreciation | C18: =Data!L53 -> -1589.2044 | D18: =Data!M53 -> -1868.8351 | E18: =Data!N53 -> -2354.5306 | F18: =Data!O53 -> -2965.6703 | G18: =Data!P53 -> -3800.7287 | H18: =Data!Q53 -> -3674.6805 | I18: =Data!R53 -> -4264.8582 | J18: =Data!S53 -> -5005.7999 | ... P18: =Data!Y53 -> -13762.876 | Q18: =BS!Q220 -> -16370.611 | R18: =BS!R220 -> -18972.1 | S18: =BS!S220 -> -21607.765 | V18: =BS!V220 -> #REF! | W18: =BS!Y220 -> -12082.307 | AD18: =M18/L18-1 -> 0.21611164 | AE18: =M18/$M$38 -> -0.16057476
B19: Intangible Fixed Assets | C19: =C20+C21 -> 269.1098 | D19: =D20+D21 -> 272.62771 | E19: =E20+E21 -> 301.80373 | F19: =F20+F21 -> 319.11401 | G19: =G20+G21 -> 456.22089 | H19: =H20+H21 -> 658.13585 | I19: =I20+I21 -> 1303.585 | J19: =J20+J21 -> 1194.061 | ... S19: =S20+S21 -> 1645.0131 | V19: =V20+V21 -> #REF! | W19: =W20+W21 -> 1226.8562 | AD19: =M19/L19-1 -> 0.13591524 | AE19: =M19/$M$38 -> 0.024918686
B20: Historical price | C20: =Data!L58 -> 432.86682 | D20: =Data!M58 -> 480.19103 | E20: =Data!N58 -> 529.38756 | F20: =Data!O58 -> 610.34511 | G20: =Data!P58 -> 821.22796 | H20: =Data!Q58 -> 1117.4194 | I20: =Data!R58 -> 1915.3624 | J20: =Data!S58 -> 1973.8144 | ... P20: =Data!Y58 -> 3868.8841 | Q20: =BS!Q222 -> 3868.8841 | R20: =BS!R222 -> 3868.8841 | S20: =BS!S222 -> 3868.8841 | V20: =BS!V222 -> #REF! | W20: =BS!Y222 -> 2595.5867 | AD20: =M20/L20-1 -> 0.13284238 | AE20: =M20/$M$38 -> 0.049329398
B21: Amortisation | C21: =Data!L59 -> -163.75702 | D21: =Data!M59 -> -207.56332 | E21: =Data!N59 -> -227.58383 | F21: =Data!O59 -> -291.23109 | G21: =Data!P59 -> -365.00707 | H21: =Data!Q59 -> -459.28354 | I21: =Data!R59 -> -611.77739 | J21: =Data!S59 -> -779.75334 | ... P21: =Data!Y59 -> -1925.9445 | Q21: =BS!Q223 -> -2025.2533 | R21: =BS!R223 -> -2124.5622 | S21: =BS!S223 -> -2223.871 | V21: =BS!V223 -> #REF! | W21: =BS!Y223 -> -1368.7305 | AD21: =M21/L21-1 -> 0.12972267 | AE21: =M21/$M$38 -> -0.024410712
AD22: =M22/L22-1 -> #DIV/0! | AE22: =M22/$M$38 -> 0
B23: Financial Lease Assets | C23: =C24+C25 -> 0.6459734 | D23: =D24+D25 -> 0.54587003 | E23: =E24+E25 -> 0.74044148 | F23: =F24+F25 -> 1.7370039 | G23: =G24+G25 -> 2.4637167 | H23: =H24+H25 -> 3.6561164 | I23: =I24+I25 -> 3.0245934 | J23: =J24+J25 -> 2.8450858 | ... S23: =S24+S25 -> 9.4647998 | V23: =V24+V25 -> #REF! | W23: =W24+W25 -> 12.046298 | AD23: =M23/L23-1 -> 5.5300451 | AE23: =M23/$M$38 -> 0.0006122631
B24: Historical price | C24: =Data!L55 -> 1.1721243 | D24: =Data!M55 -> 0.79446081 | E24: =Data!N55 -> 0.95894619 | F24: =Data!O55 -> 2.4006015 | G24: =Data!P55 -> 3.4465069 | H24: =Data!Q55 -> 4.7024264 | I24: =Data!R55 -> 5.2085428 | J24: =Data!S55 -> 6.0576532 | ... P24: =Data!Y55 -> 5.8710062 | Q24: =BS!Q225 -> 4.8710062 | R24: =BS!R225 -> 4.8710062 | S24: =BS!S225 -> 4.8710062 | V24: =BS!V225 -> #REF! | W24: =BS!Y225 -> 8.0324653 | AD24: =M24/L24-1 -> 5.8024687 | AE24: =M24/$M$38 -> 0.0010539979
B25: Depreciation | C25: =Data!L56 -> -0.5261509 | D25: =Data!M56 -> -0.24859078 | E25: =Data!N56 -> -0.21850472 | F25: =Data!O56 -> -0.66359758 | G25: =Data!P56 -> -0.98279025 | H25: =Data!Q56 -> -1.04631 | I25: =Data!R56 -> -2.1839494 | J25: =Data!S56 -> -3.2125674 | ... P25: =Data!Y56 -> -4.5937936 | Q25: =BS!Q226 -> 4.5937936 | R25: =BS!R226 -> 4.5937936 | S25: =BS!S226 -> 4.5937936 | V25: =BS!V226 -> #REF! | W25: =BS!Y226 -> 4.0138322 | AD25: =M25/L25-1 -> 6.2199521 | AE25: =M25/$M$38 -> -0.00044173485
B26: Investment properties | C26: =C27+C28 -> 0 | D26: =D27+D28 -> 0 | E26: =E27+E28 -> 0 | F26: =F27+F28 -> 0 | G26: =G27+G28 -> 0 | H26: =H27+H28 -> 0 | I26: =I27+I28 -> 0 | J26: =J27+J28 -> 0 | ... S26: =S27+S28 -> 0 | V26: =V27+V28 -> 0 | W26: =W27+W28 -> 0 | AE26: =M26/$M$38 -> 0
B27: Historical price | C27: =Data!L62 -> 0 | D27: =Data!M62 -> 0 | E27: =Data!N62 -> 0 | F27: =Data!O62 -> 0 | G27: =Data!P62 -> 0 | H27: =Data!Q62 -> 0 | I27: =Data!R62 -> 0 | J27: =Data!S62 -> 0 | ... P27: =Data!Y62 -> 0 | Q27: =SUM(Q172:Q173) -> 0 | R27: =SUM(R172:R173) -> 0 | S27: =SUM(S172:S173) -> 0 | V27: =SUM(V172:V173) -> 0 | W27: =SUM(W172:W173) -> 0 | AE27: =M27/$M$38 -> 0
B28: Depreciation | C28: =Data!L63 -> 0 | D28: =Data!M63 -> 0 | E28: =Data!N63 -> 0 | F28: =Data!O63 -> 0 | G28: =Data!P63 -> 0 | H28: =Data!Q63 -> 0 | I28: =Data!R63 -> 0 | J28: =Data!S63 -> 0 | ... P28: =Data!Y63 -> 0 | Q28: =Q174 -> 0 | R28: =R174 -> 0 | S28: =S174 -> 0 | V28: =V174 -> 0 | W28: =W174 -> 0 | AE28: =M28/$M$38 -> 0
B29: Work-in-progress | C29: =Data!L60+Data!L64 -> 540.99636 | D29: =Data!M60+Data!M64 -> 539.1027 | E29: =Data!N60+Data!N64 -> 537.24167 | F29: =Data!O60+Data!O64 -> 692.57537 | G29: =Data!P60+Data!P64 -> 1020.9804 | H29: =Data!Q60+Data!Q64 -> 805.5599 | I29: =Data!R60+Data!R64 -> 1174.7781 | J29: =Data!S60+Data!S64 -> 1650.4709 | ... P29: =Data!Y60+Data!Y64 -> 1604.916 | Q29: =BS!Q227 -> -1479.0525 | R29: =BS!R227 -> 2273.7843 | S29: =BS!S227 -> 9142.7403 | V29: =BS!V227 -> #REF! | W29: =BS!Y227 -> 1451.7172 | AD29: =M29/L29-1 -> -0.17698297 | AE29: =M29/$M$38 -> 0.020564888
B30: Long-term financial investment | C30: =SUM(Data!L68:L70,Data!L72) -> 873.79872 | D30: =SUM(Data!M68:M70,Data!M72) -> 888.99398 | E30: =SUM(Data!N68:N70,Data!N72) -> 976.66701 | F30: =SUM(Data!O68:O70,Data!O72) -> 904.08337 | G30: =SUM(Data!P68:P70,Data!P72) -> 1047.3857 | H30: =SUM(Data!Q68:Q70,Data!Q72) -> 2082.9643 | I30: =SUM(Data!R68:R70,Data!R72) -> 2469.5925 | J30: =SUM(Data!S68:S70,Data!S72) -> 2806.3367 | ... P30: =SUM(Data!Y68:Y70,Data!Y72) -> 7404.8915 | Q30: =Q130+Q135 -> 15384.883 | R30: =R130+R135 -> 18960.877 | S30: =S130+S135 -> 23134.967 | V30: =V130+V135 -> #REF! | W30: =W130+W135 -> 5300.6538 | AC30: OOOOO | AD30: =M30/L30-1 -> 0.16858993 | AE30: =M30/$M$38 -> 0.089350888
B31: Provision for LT investment | C31: =Data!L71 -> -177.51311 | D31: =Data!M71 -> -182.26664 | E31: =Data!N71 -> -167.15046 | F31: =Data!O71 -> -176.17768 | G31: =Data!P71 -> -221.05818 | H31: =Data!Q71 -> -299.59528 | I31: =Data!R71 -> -267.12588 | J31: =Data!S71 -> -309.78463 | ... P31: =Data!Y71 -> -2667.0275 | Q31: =P31 -> -2667.0275 | R31: =Q31 -> -2667.0275 | S31: =R31 -> -2667.0275 | V31: =M31-PL!P418 -> -1453.7102 | W31: =N31-PL!I418 -> -2376.2264 | AC31: Assumptions | AD31: =M31/L31-1 -> 0.62497684 | AE31: =M31/$M$38 -> -0.026654395
B32: Long-term account receivable | C32: =SUM(Data!L43:L48) -> 1.4340848 | D32: =SUM(Data!M43:M48) -> 1.2126645 | E32: =SUM(Data!N43:N48) -> 370.46839 | F32: =SUM(Data!O43:O48) -> 402.48941 | G32: =SUM(Data!P43:P48) -> 434.66674 | H32: =SUM(Data!Q43:Q48) -> 286.3863 | I32: =SUM(Data!R43:R48) -> 164.51741 | J32: =SUM(Data!S43:S48) -> 317.21376 | ... P32: =SUM(Data!Y43:Y48) -> 616.71455 | Q32: =PL!Q9/Assumptions!Q80 -> 348.7476 | R32: =PL!R9/Assumptions!R80 -> 402.10378 | S32: =PL!S9/Assumptions!S80 -> 466.68744 | V32: =PL!#REF!/Assumptions!AF80 -> #REF! | W32: =PL!V9/Assumptions!AG80 -> 348.40381 | AC32: Assumptions | AD32: =M32/L32-1 -> 0.24998532 | AE32: =M32/$M$38 -> 0.0053719495
B33: Provision for LT receivable | C33: =Data!L49 -> 0 | D33: =Data!M49 -> 0 | E33: =Data!N49 -> -52.372483 | F33: =Data!O49 -> -53.850828 | G33: =Data!P49 -> -53.700828 | H33: =Data!Q49 -> -54.729174 | I33: =Data!R49 -> -54.729174 | J33: =Data!S49 -> -54.729174 | ... P33: =Data!Y49 -> -52.372483 | Q33: =P33 -> -52.372483 | R33: =Q33 -> -52.372483 | S33: =R33 -> -52.372483 | V33: =M33 -> -52.372483 | W33: =N33 -> -52.372483 | AE33: =M33/$M$38 -> -0.0010139801
B34: Goodwill | C34: =Data!L73+Data!L79 -> 216.36636 | D34: =Data!M73+Data!M79 -> 231.50828 | E34: =Data!N73+Data!N79 -> 333.17044 | F34: =Data!O73+Data!O79 -> 0 | G34: =Data!P73+Data!P79 -> 0 | H34: =Data!Q73+Data!Q79 -> 0 | I34: =Data!R73+Data!R79 -> 326.01772 | J34: =Data!S73+Data!S79 -> 225.92942 | ... P34: =Data!Y73+Data!Y79 -> 1015.7303 | Q34: =BS!Q248 -> 1015.7303 | R34: =BS!R248 -> 1015.7303 | S34: =BS!S248 -> 1015.7303 | V34: =BS!V248 -> #REF! | W34: =BS!Y248 -> 1155.4111 | AD34: =M34/L34-1 -> -0.12455446 | AE34: =M34/$M$38 -> 0.0078981928
